oscillator/oscillator.v
// Critical path delay = period/2 = 57 ns
module oscillator(en, w0);
   input en;
   output w0;
   wire   r = 0;
   wire   [55:0] w;
   and #(3) and_0(w[55], en, w[0]);
   genvar i;
   generate
      for (i = 54; i >= 0; i = i-1) begin
         not #(1) not_i(/*输出*/w[i], /*输入*/w[i+1]);
      end
   endgenerate
   buf buf_0(w0, w[0]);
endmodule;

oscillator/testbench.v
`timescale 1 ns/1 ns	//time scale for simulation

module testbench;
   reg en;
   wire w0;

   oscillator my_oscillator(.en(en), .w0(w0));

   initial begin
      $dumpfile("test.vcd");
      $dumpvars(0, testbench);
      en = 0;
      #58;
      en = 1; // then oscillator will run until $finish
      #232 $finish; // finish simulation
   end
endmodule

oscillator/test.vcd
$date
	Sun Aug  7 11:01:47 2022
$end
$version
	Icarus Verilog
$end
$timescale
	1ns
$end
$scope module testbench $end
$var wire 1 ! w0 $end
$var reg 1 " en $end
$scope module my_oscillator $end
$var wire 1 " en $end
$var wire 1 # r $end
$var wire 1 ! w0 $end
$var wire 56 $ w [55:0] $end
$scope begin genblk1[0] $end
$upscope $end
$scope begin genblk1[1] $end
$upscope $end
$scope begin genblk1[2] $end
$upscope $end
$scope begin genblk1[3] $end
$upscope $end
$scope begin genblk1[4] $end
$upscope $end
$scope begin genblk1[5] $end
$upscope $end
$scope begin genblk1[6] $end
$upscope $end
$scope begin genblk1[7] $end
$upscope $end
$scope begin genblk1[8] $end
$upscope $end
$scope begin genblk1[9] $end
$upscope $end
$scope begin genblk1[10] $end
$upscope $end
$scope begin genblk1[11] $end
$upscope $end
$scope begin genblk1[12] $end
$upscope $end
$scope begin genblk1[13] $end
$upscope $end
$scope begin genblk1[14] $end
$upscope $end
$scope begin genblk1[15] $end
$upscope $end
$scope begin genblk1[16] $end
$upscope $end
$scope begin genblk1[17] $end
$upscope $end
$scope begin genblk1[18] $end
$upscope $end
$scope begin genblk1[19] $end
$upscope $end
$scope begin genblk1[20] $end
$upscope $end
$scope begin genblk1[21] $end
$upscope $end
$scope begin genblk1[22] $end
$upscope $end
$scope begin genblk1[23] $end
$upscope $end
$scope begin genblk1[24] $end
$upscope $end
$scope begin genblk1[25] $end
$upscope $end
$scope begin genblk1[26] $end
$upscope $end
$scope begin genblk1[27] $end
$upscope $end
$scope begin genblk1[28] $end
$upscope $end
$scope begin genblk1[29] $end
$upscope $end
$scope begin genblk1[30] $end
$upscope $end
$scope begin genblk1[31] $end
$upscope $end
$scope begin genblk1[32] $end
$upscope $end
$scope begin genblk1[33] $end
$upscope $end
$scope begin genblk1[34] $end
$upscope $end
$scope begin genblk1[35] $end
$upscope $end
$scope begin genblk1[36] $end
$upscope $end
$scope begin genblk1[37] $end
$upscope $end
$scope begin genblk1[38] $end
$upscope $end
$scope begin genblk1[39] $end
$upscope $end
$scope begin genblk1[40] $end
$upscope $end
$scope begin genblk1[41] $end
$upscope $end
$scope begin genblk1[42] $end
$upscope $end
$scope begin genblk1[43] $end
$upscope $end
$scope begin genblk1[44] $end
$upscope $end
$scope begin genblk1[45] $end
$upscope $end
$scope begin genblk1[46] $end
$upscope $end
$scope begin genblk1[47] $end
$upscope $end
$scope begin genblk1[48] $end
$upscope $end
$scope begin genblk1[49] $end
$upscope $end
$scope begin genblk1[50] $end
$upscope $end
$scope begin genblk1[51] $end
$upscope $end
$scope begin genblk1[52] $end
$upscope $end
$scope begin genblk1[53] $end
$upscope $end
$scope begin genblk1[54] $end
$upscope $end
$upscope $end
$upscope $end
$enddefinitions $end
#0
$dumpvars
bx $
0#
0"
x!
$end
#3
b0xxxxxxxxxxxxxxxxxxxxxxxxxxxxxxxxxxxxxxxxxxxxxxxxxxxxxxx $
#4
b1xxxxxxxxxxxxxxxxxxxxxxxxxxxxxxxxxxxxxxxxxxxxxxxxxxxxxx $
#5
b10xxxxxxxxxxxxxxxxxxxxxxxxxxxxxxxxxxxxxxxxxxxxxxxxxxxxx $
#6
b101xxxxxxxxxxxxxxxxxxxxxxxxxxxxxxxxxxxxxxxxxxxxxxxxxxxx $
#7
b1010xxxxxxxxxxxxxxxxxxxxxxxxxxxxxxxxxxxxxxxxxxxxxxxxxxx $
#8
b10101xxxxxxxxxxxxxxxxxxxxxxxxxxxxxxxxxxxxxxxxxxxxxxxxxx $
#9
b101010xxxxxxxxxxxxxxxxxxxxxxxxxxxxxxxxxxxxxxxxxxxxxxxxx $
#10
b1010101xxxxxxxxxxxxxxxxxxxxxxxxxxxxxxxxxxxxxxxxxxxxxxxx $
#11
b10101010xxxxxxxxxxxxxxxxxxxxxxxxxxxxxxxxxxxxxxxxxxxxxxx $
#12
b101010101xxxxxxxxxxxxxxxxxxxxxxxxxxxxxxxxxxxxxxxxxxxxxx $
#13
b1010101010xxxxxxxxxxxxxxxxxxxxxxxxxxxxxxxxxxxxxxxxxxxxx $
#14
b10101010101xxxxxxxxxxxxxxxxxxxxxxxxxxxxxxxxxxxxxxxxxxxx $
#15
b101010101010xxxxxxxxxxxxxxxxxxxxxxxxxxxxxxxxxxxxxxxxxxx $
#16
b1010101010101xxxxxxxxxxxxxxxxxxxxxxxxxxxxxxxxxxxxxxxxxx $
#17
b10101010101010xxxxxxxxxxxxxxxxxxxxxxxxxxxxxxxxxxxxxxxxx $
#18
b101010101010101xxxxxxxxxxxxxxxxxxxxxxxxxxxxxxxxxxxxxxxx $
#19
b1010101010101010xxxxxxxxxxxxxxxxxxxxxxxxxxxxxxxxxxxxxxx $
#20
b10101010101010101xxxxxxxxxxxxxxxxxxxxxxxxxxxxxxxxxxxxxx $
#21
b101010101010101010xxxxxxxxxxxxxxxxxxxxxxxxxxxxxxxxxxxxx $
#22
b1010101010101010101xxxxxxxxxxxxxxxxxxxxxxxxxxxxxxxxxxxx $
#23
b10101010101010101010xxxxxxxxxxxxxxxxxxxxxxxxxxxxxxxxxxx $
#24
b101010101010101010101xxxxxxxxxxxxxxxxxxxxxxxxxxxxxxxxxx $
#25
b1010101010101010101010xxxxxxxxxxxxxxxxxxxxxxxxxxxxxxxxx $
#26
b10101010101010101010101xxxxxxxxxxxxxxxxxxxxxxxxxxxxxxxx $
#27
b101010101010101010101010xxxxxxxxxxxxxxxxxxxxxxxxxxxxxxx $
#28
b1010101010101010101010101xxxxxxxxxxxxxxxxxxxxxxxxxxxxxx $
#29
b10101010101010101010101010xxxxxxxxxxxxxxxxxxxxxxxxxxxxx $
#30
b101010101010101010101010101xxxxxxxxxxxxxxxxxxxxxxxxxxxx $
#31
b1010101010101010101010101010xxxxxxxxxxxxxxxxxxxxxxxxxxx $
#32
b10101010101010101010101010101xxxxxxxxxxxxxxxxxxxxxxxxxx $
#33
b101010101010101010101010101010xxxxxxxxxxxxxxxxxxxxxxxxx $
#34
b1010101010101010101010101010101xxxxxxxxxxxxxxxxxxxxxxxx $
#35
b10101010101010101010101010101010xxxxxxxxxxxxxxxxxxxxxxx $
#36
b101010101010101010101010101010101xxxxxxxxxxxxxxxxxxxxxx $
#37
b1010101010101010101010101010101010xxxxxxxxxxxxxxxxxxxxx $
#38
b10101010101010101010101010101010101xxxxxxxxxxxxxxxxxxxx $
#39
b101010101010101010101010101010101010xxxxxxxxxxxxxxxxxxx $
#40
b1010101010101010101010101010101010101xxxxxxxxxxxxxxxxxx $
#41
b10101010101010101010101010101010101010xxxxxxxxxxxxxxxxx $
#42
b101010101010101010101010101010101010101xxxxxxxxxxxxxxxx $
#43
b1010101010101010101010101010101010101010xxxxxxxxxxxxxxx $
#44
b10101010101010101010101010101010101010101xxxxxxxxxxxxxx $
#45
b101010101010101010101010101010101010101010xxxxxxxxxxxxx $
#46
b1010101010101010101010101010101010101010101xxxxxxxxxxxx $
#47
b10101010101010101010101010101010101010101010xxxxxxxxxxx $
#48
b101010101010101010101010101010101010101010101xxxxxxxxxx $
#49
b1010101010101010101010101010101010101010101010xxxxxxxxx $
#50
b10101010101010101010101010101010101010101010101xxxxxxxx $
#51
b101010101010101010101010101010101010101010101010xxxxxxx $
#52
b1010101010101010101010101010101010101010101010101xxxxxx $
#53
b10101010101010101010101010101010101010101010101010xxxxx $
#54
b101010101010101010101010101010101010101010101010101xxxx $
#55
b1010101010101010101010101010101010101010101010101010xxx $
#56
b10101010101010101010101010101010101010101010101010101xx $
#57
b101010101010101010101010101010101010101010101010101010x $
#58
1!
b1010101010101010101010101010101010101010101010101010101 $
1"
#61
b11010101010101010101010101010101010101010101010101010101 $
#62
b10010101010101010101010101010101010101010101010101010101 $
#63
b10110101010101010101010101010101010101010101010101010101 $
#64
b10100101010101010101010101010101010101010101010101010101 $
#65
b10101101010101010101010101010101010101010101010101010101 $
#66
b10101001010101010101010101010101010101010101010101010101 $
#67
b10101011010101010101010101010101010101010101010101010101 $
#68
b10101010010101010101010101010101010101010101010101010101 $
#69
b10101010110101010101010101010101010101010101010101010101 $
#70
b10101010100101010101010101010101010101010101010101010101 $
#71
b10101010101101010101010101010101010101010101010101010101 $
#72
b10101010101001010101010101010101010101010101010101010101 $
#73
b10101010101011010101010101010101010101010101010101010101 $
#74
b10101010101010010101010101010101010101010101010101010101 $
#75
b10101010101010110101010101010101010101010101010101010101 $
#76
b10101010101010100101010101010101010101010101010101010101 $
#77
b10101010101010101101010101010101010101010101010101010101 $
#78
b10101010101010101001010101010101010101010101010101010101 $
#79
b10101010101010101011010101010101010101010101010101010101 $
#80
b10101010101010101010010101010101010101010101010101010101 $
#81
b10101010101010101010110101010101010101010101010101010101 $
#82
b10101010101010101010100101010101010101010101010101010101 $
#83
b10101010101010101010101101010101010101010101010101010101 $
#84
b10101010101010101010101001010101010101010101010101010101 $
#85
b10101010101010101010101011010101010101010101010101010101 $
#86
b10101010101010101010101010010101010101010101010101010101 $
#87
b10101010101010101010101010110101010101010101010101010101 $
#88
b10101010101010101010101010100101010101010101010101010101 $
#89
b10101010101010101010101010101101010101010101010101010101 $
#90
b10101010101010101010101010101001010101010101010101010101 $
#91
b10101010101010101010101010101011010101010101010101010101 $
#92
b10101010101010101010101010101010010101010101010101010101 $
#93
b10101010101010101010101010101010110101010101010101010101 $
#94
b10101010101010101010101010101010100101010101010101010101 $
#95
b10101010101010101010101010101010101101010101010101010101 $
#96
b10101010101010101010101010101010101001010101010101010101 $
#97
b10101010101010101010101010101010101011010101010101010101 $
#98
b10101010101010101010101010101010101010010101010101010101 $
#99
b10101010101010101010101010101010101010110101010101010101 $
#100
b10101010101010101010101010101010101010100101010101010101 $
#101
b10101010101010101010101010101010101010101101010101010101 $
#102
b10101010101010101010101010101010101010101001010101010101 $
#103
b10101010101010101010101010101010101010101011010101010101 $
#104
b10101010101010101010101010101010101010101010010101010101 $
#105
b10101010101010101010101010101010101010101010110101010101 $
#106
b10101010101010101010101010101010101010101010100101010101 $
#107
b10101010101010101010101010101010101010101010101101010101 $
#108
b10101010101010101010101010101010101010101010101001010101 $
#109
b10101010101010101010101010101010101010101010101011010101 $
#110
b10101010101010101010101010101010101010101010101010010101 $
#111
b10101010101010101010101010101010101010101010101010110101 $
#112
b10101010101010101010101010101010101010101010101010100101 $
#113
b10101010101010101010101010101010101010101010101010101101 $
#114
b10101010101010101010101010101010101010101010101010101001 $
#115
b10101010101010101010101010101010101010101010101010101011 $
#116
0!
b10101010101010101010101010101010101010101010101010101010 $
#119
b101010101010101010101010101010101010101010101010101010 $
#120
b1101010101010101010101010101010101010101010101010101010 $
#121
b1001010101010101010101010101010101010101010101010101010 $
#122
b1011010101010101010101010101010101010101010101010101010 $
#123
b1010010101010101010101010101010101010101010101010101010 $
#124
b1010110101010101010101010101010101010101010101010101010 $
#125
b1010100101010101010101010101010101010101010101010101010 $
#126
b1010101101010101010101010101010101010101010101010101010 $
#127
b1010101001010101010101010101010101010101010101010101010 $
#128
b1010101011010101010101010101010101010101010101010101010 $
#129
b1010101010010101010101010101010101010101010101010101010 $
#130
b1010101010110101010101010101010101010101010101010101010 $
#131
b1010101010100101010101010101010101010101010101010101010 $
#132
b1010101010101101010101010101010101010101010101010101010 $
#133
b1010101010101001010101010101010101010101010101010101010 $
#134
b1010101010101011010101010101010101010101010101010101010 $
#135
b1010101010101010010101010101010101010101010101010101010 $
#136
b1010101010101010110101010101010101010101010101010101010 $
#137
b1010101010101010100101010101010101010101010101010101010 $
#138
b1010101010101010101101010101010101010101010101010101010 $
#139
b1010101010101010101001010101010101010101010101010101010 $
#140
b1010101010101010101011010101010101010101010101010101010 $
#141
b1010101010101010101010010101010101010101010101010101010 $
#142
b1010101010101010101010110101010101010101010101010101010 $
#143
b1010101010101010101010100101010101010101010101010101010 $
#144
b1010101010101010101010101101010101010101010101010101010 $
#145
b1010101010101010101010101001010101010101010101010101010 $
#146
b1010101010101010101010101011010101010101010101010101010 $
#147
b1010101010101010101010101010010101010101010101010101010 $
#148
b1010101010101010101010101010110101010101010101010101010 $
#149
b1010101010101010101010101010100101010101010101010101010 $
#150
b1010101010101010101010101010101101010101010101010101010 $
#151
b1010101010101010101010101010101001010101010101010101010 $
#152
b1010101010101010101010101010101011010101010101010101010 $
#153
b1010101010101010101010101010101010010101010101010101010 $
#154
b1010101010101010101010101010101010110101010101010101010 $
#155
b1010101010101010101010101010101010100101010101010101010 $
#156
b1010101010101010101010101010101010101101010101010101010 $
#157
b1010101010101010101010101010101010101001010101010101010 $
#158
b1010101010101010101010101010101010101011010101010101010 $
#159
b1010101010101010101010101010101010101010010101010101010 $
#160
b1010101010101010101010101010101010101010110101010101010 $
#161
b1010101010101010101010101010101010101010100101010101010 $
#162
b1010101010101010101010101010101010101010101101010101010 $
#163
b1010101010101010101010101010101010101010101001010101010 $
#164
b1010101010101010101010101010101010101010101011010101010 $
#165
b1010101010101010101010101010101010101010101010010101010 $
#166
b1010101010101010101010101010101010101010101010110101010 $
#167
b1010101010101010101010101010101010101010101010100101010 $
#168
b1010101010101010101010101010101010101010101010101101010 $
#169
b1010101010101010101010101010101010101010101010101001010 $
#170
b1010101010101010101010101010101010101010101010101011010 $
#171
b1010101010101010101010101010101010101010101010101010010 $
#172
b1010101010101010101010101010101010101010101010101010110 $
#173
b1010101010101010101010101010101010101010101010101010100 $
#174
1!
b1010101010101010101010101010101010101010101010101010101 $
#177
b11010101010101010101010101010101010101010101010101010101 $
#178
b10010101010101010101010101010101010101010101010101010101 $
#179
b10110101010101010101010101010101010101010101010101010101 $
#180
b10100101010101010101010101010101010101010101010101010101 $
#181
b10101101010101010101010101010101010101010101010101010101 $
#182
b10101001010101010101010101010101010101010101010101010101 $
#183
b10101011010101010101010101010101010101010101010101010101 $
#184
b10101010010101010101010101010101010101010101010101010101 $
#185
b10101010110101010101010101010101010101010101010101010101 $
#186
b10101010100101010101010101010101010101010101010101010101 $
#187
b10101010101101010101010101010101010101010101010101010101 $
#188
b10101010101001010101010101010101010101010101010101010101 $
#189
b10101010101011010101010101010101010101010101010101010101 $
#190
b10101010101010010101010101010101010101010101010101010101 $
#191
b10101010101010110101010101010101010101010101010101010101 $
#192
b10101010101010100101010101010101010101010101010101010101 $
#193
b10101010101010101101010101010101010101010101010101010101 $
#194
b10101010101010101001010101010101010101010101010101010101 $
#195
b10101010101010101011010101010101010101010101010101010101 $
#196
b10101010101010101010010101010101010101010101010101010101 $
#197
b10101010101010101010110101010101010101010101010101010101 $
#198
b10101010101010101010100101010101010101010101010101010101 $
#199
b10101010101010101010101101010101010101010101010101010101 $
#200
b10101010101010101010101001010101010101010101010101010101 $
#201
b10101010101010101010101011010101010101010101010101010101 $
#202
b10101010101010101010101010010101010101010101010101010101 $
#203
b10101010101010101010101010110101010101010101010101010101 $
#204
b10101010101010101010101010100101010101010101010101010101 $
#205
b10101010101010101010101010101101010101010101010101010101 $
#206
b10101010101010101010101010101001010101010101010101010101 $
#207
b10101010101010101010101010101011010101010101010101010101 $
#208
b10101010101010101010101010101010010101010101010101010101 $
#209
b10101010101010101010101010101010110101010101010101010101 $
#210
b10101010101010101010101010101010100101010101010101010101 $
#211
b10101010101010101010101010101010101101010101010101010101 $
#212
b10101010101010101010101010101010101001010101010101010101 $
#213
b10101010101010101010101010101010101011010101010101010101 $
#214
b10101010101010101010101010101010101010010101010101010101 $
#215
b10101010101010101010101010101010101010110101010101010101 $
#216
b10101010101010101010101010101010101010100101010101010101 $
#217
b10101010101010101010101010101010101010101101010101010101 $
#218
b10101010101010101010101010101010101010101001010101010101 $
#219
b10101010101010101010101010101010101010101011010101010101 $
#220
b10101010101010101010101010101010101010101010010101010101 $
#221
b10101010101010101010101010101010101010101010110101010101 $
#222
b10101010101010101010101010101010101010101010100101010101 $
#223
b10101010101010101010101010101010101010101010101101010101 $
#224
b10101010101010101010101010101010101010101010101001010101 $
#225
b10101010101010101010101010101010101010101010101011010101 $
#226
b10101010101010101010101010101010101010101010101010010101 $
#227
b10101010101010101010101010101010101010101010101010110101 $
#228
b10101010101010101010101010101010101010101010101010100101 $
#229
b10101010101010101010101010101010101010101010101010101101 $
#230
b10101010101010101010101010101010101010101010101010101001 $
#231
b10101010101010101010101010101010101010101010101010101011 $
#232
0!
b10101010101010101010101010101010101010101010101010101010 $
#235
b101010101010101010101010101010101010101010101010101010 $
#236
b1101010101010101010101010101010101010101010101010101010 $
#237
b1001010101010101010101010101010101010101010101010101010 $
#238
b1011010101010101010101010101010101010101010101010101010 $
#239
b1010010101010101010101010101010101010101010101010101010 $
#240
b1010110101010101010101010101010101010101010101010101010 $
#241
b1010100101010101010101010101010101010101010101010101010 $
#242
b1010101101010101010101010101010101010101010101010101010 $
#243
b1010101001010101010101010101010101010101010101010101010 $
#244
b1010101011010101010101010101010101010101010101010101010 $
#245
b1010101010010101010101010101010101010101010101010101010 $
#246
b1010101010110101010101010101010101010101010101010101010 $
#247
b1010101010100101010101010101010101010101010101010101010 $
#248
b1010101010101101010101010101010101010101010101010101010 $
#249
b1010101010101001010101010101010101010101010101010101010 $
#250
b1010101010101011010101010101010101010101010101010101010 $
#251
b1010101010101010010101010101010101010101010101010101010 $
#252
b1010101010101010110101010101010101010101010101010101010 $
#253
b1010101010101010100101010101010101010101010101010101010 $
#254
b1010101010101010101101010101010101010101010101010101010 $
#255
b1010101010101010101001010101010101010101010101010101010 $
#256
b1010101010101010101011010101010101010101010101010101010 $
#257
b1010101010101010101010010101010101010101010101010101010 $
#258
b1010101010101010101010110101010101010101010101010101010 $
#259
b1010101010101010101010100101010101010101010101010101010 $
#260
b1010101010101010101010101101010101010101010101010101010 $
#261
b1010101010101010101010101001010101010101010101010101010 $
#262
b1010101010101010101010101011010101010101010101010101010 $
#263
b1010101010101010101010101010010101010101010101010101010 $
#264
b1010101010101010101010101010110101010101010101010101010 $
#265
b1010101010101010101010101010100101010101010101010101010 $
#266
b1010101010101010101010101010101101010101010101010101010 $
#267
b1010101010101010101010101010101001010101010101010101010 $
#268
b1010101010101010101010101010101011010101010101010101010 $
#269
b1010101010101010101010101010101010010101010101010101010 $
#270
b1010101010101010101010101010101010110101010101010101010 $
#271
b1010101010101010101010101010101010100101010101010101010 $
#272
b1010101010101010101010101010101010101101010101010101010 $
#273
b1010101010101010101010101010101010101001010101010101010 $
#274
b1010101010101010101010101010101010101011010101010101010 $
#275
b1010101010101010101010101010101010101010010101010101010 $
#276
b1010101010101010101010101010101010101010110101010101010 $
#277
b1010101010101010101010101010101010101010100101010101010 $
#278
b1010101010101010101010101010101010101010101101010101010 $
#279
b1010101010101010101010101010101010101010101001010101010 $
#280
b1010101010101010101010101010101010101010101011010101010 $
#281
b1010101010101010101010101010101010101010101010010101010 $
#282
b1010101010101010101010101010101010101010101010110101010 $
#283
b1010101010101010101010101010101010101010101010100101010 $
#284
b1010101010101010101010101010101010101010101010101101010 $
#285
b1010101010101010101010101010101010101010101010101001010 $
#286
b1010101010101010101010101010101010101010101010101011010 $
#287
b1010101010101010101010101010101010101010101010101010010 $
#288
b1010101010101010101010101010101010101010101010101010110 $
#289
b1010101010101010101010101010101010101010101010101010100 $
#290
1!
b1010101010101010101010101010101010101010101010101010101 $
