oscillator/oscillator.v
// Critical path = period/2 = 76 ns
module oscillator(en, w0);
   parameter N = 137; // # of not gates
   input en;
   output w0;
   wire   [N:0] w;
   and #(3) and_0(w[N], en, w[0]);
   genvar i;
   generate
      for (i = N-1; i >= 0; i = i-1) begin
         not #(1) not_i(/*输出*/w[i], /*输入*/w[i+1]);
      end
   endgenerate
   buf buf_0(w0, w[0]);
endmodule;

oscillator/testbench.v
`timescale 1 ns/1 ns	//time scale for simulation

module testbench;
   reg en;
   wire w0;

   oscillator my_oscillator(.en(en), .w0(w0));

   initial begin
      $dumpfile("test.vcd");
      $dumpvars(0, testbench);
      en = 0;
      #140;
      en = 1; // then oscillator will run until $finish
      #560 $finish; // finish simulation
   end
endmodule

oscillator/test.vcd
$date
	Fri Sep  9 21:51:52 2022
$end
$version
	Icarus Verilog
$end
$timescale
	1ns
$end
$scope module testbench $end
$var wire 1 ! w0 $end
$var reg 1 " en $end
$scope module my_oscillator $end
$var wire 1 " en $end
$var wire 1 ! w0 $end
$var wire 138 # w [137:0] $end
$scope begin genblk1[0] $end
$upscope $end
$scope begin genblk1[1] $end
$upscope $end
$scope begin genblk1[2] $end
$upscope $end
$scope begin genblk1[3] $end
$upscope $end
$scope begin genblk1[4] $end
$upscope $end
$scope begin genblk1[5] $end
$upscope $end
$scope begin genblk1[6] $end
$upscope $end
$scope begin genblk1[7] $end
$upscope $end
$scope begin genblk1[8] $end
$upscope $end
$scope begin genblk1[9] $end
$upscope $end
$scope begin genblk1[10] $end
$upscope $end
$scope begin genblk1[11] $end
$upscope $end
$scope begin genblk1[12] $end
$upscope $end
$scope begin genblk1[13] $end
$upscope $end
$scope begin genblk1[14] $end
$upscope $end
$scope begin genblk1[15] $end
$upscope $end
$scope begin genblk1[16] $end
$upscope $end
$scope begin genblk1[17] $end
$upscope $end
$scope begin genblk1[18] $end
$upscope $end
$scope begin genblk1[19] $end
$upscope $end
$scope begin genblk1[20] $end
$upscope $end
$scope begin genblk1[21] $end
$upscope $end
$scope begin genblk1[22] $end
$upscope $end
$scope begin genblk1[23] $end
$upscope $end
$scope begin genblk1[24] $end
$upscope $end
$scope begin genblk1[25] $end
$upscope $end
$scope begin genblk1[26] $end
$upscope $end
$scope begin genblk1[27] $end
$upscope $end
$scope begin genblk1[28] $end
$upscope $end
$scope begin genblk1[29] $end
$upscope $end
$scope begin genblk1[30] $end
$upscope $end
$scope begin genblk1[31] $end
$upscope $end
$scope begin genblk1[32] $end
$upscope $end
$scope begin genblk1[33] $end
$upscope $end
$scope begin genblk1[34] $end
$upscope $end
$scope begin genblk1[35] $end
$upscope $end
$scope begin genblk1[36] $end
$upscope $end
$scope begin genblk1[37] $end
$upscope $end
$scope begin genblk1[38] $end
$upscope $end
$scope begin genblk1[39] $end
$upscope $end
$scope begin genblk1[40] $end
$upscope $end
$scope begin genblk1[41] $end
$upscope $end
$scope begin genblk1[42] $end
$upscope $end
$scope begin genblk1[43] $end
$upscope $end
$scope begin genblk1[44] $end
$upscope $end
$scope begin genblk1[45] $end
$upscope $end
$scope begin genblk1[46] $end
$upscope $end
$scope begin genblk1[47] $end
$upscope $end
$scope begin genblk1[48] $end
$upscope $end
$scope begin genblk1[49] $end
$upscope $end
$scope begin genblk1[50] $end
$upscope $end
$scope begin genblk1[51] $end
$upscope $end
$scope begin genblk1[52] $end
$upscope $end
$scope begin genblk1[53] $end
$upscope $end
$scope begin genblk1[54] $end
$upscope $end
$scope begin genblk1[55] $end
$upscope $end
$scope begin genblk1[56] $end
$upscope $end
$scope begin genblk1[57] $end
$upscope $end
$scope begin genblk1[58] $end
$upscope $end
$scope begin genblk1[59] $end
$upscope $end
$scope begin genblk1[60] $end
$upscope $end
$scope begin genblk1[61] $end
$upscope $end
$scope begin genblk1[62] $end
$upscope $end
$scope begin genblk1[63] $end
$upscope $end
$scope begin genblk1[64] $end
$upscope $end
$scope begin genblk1[65] $end
$upscope $end
$scope begin genblk1[66] $end
$upscope $end
$scope begin genblk1[67] $end
$upscope $end
$scope begin genblk1[68] $end
$upscope $end
$scope begin genblk1[69] $end
$upscope $end
$scope begin genblk1[70] $end
$upscope $end
$scope begin genblk1[71] $end
$upscope $end
$scope begin genblk1[72] $end
$upscope $end
$scope begin genblk1[73] $end
$upscope $end
$scope begin genblk1[74] $end
$upscope $end
$scope begin genblk1[75] $end
$upscope $end
$scope begin genblk1[76] $end
$upscope $end
$scope begin genblk1[77] $end
$upscope $end
$scope begin genblk1[78] $end
$upscope $end
$scope begin genblk1[79] $end
$upscope $end
$scope begin genblk1[80] $end
$upscope $end
$scope begin genblk1[81] $end
$upscope $end
$scope begin genblk1[82] $end
$upscope $end
$scope begin genblk1[83] $end
$upscope $end
$scope begin genblk1[84] $end
$upscope $end
$scope begin genblk1[85] $end
$upscope $end
$scope begin genblk1[86] $end
$upscope $end
$scope begin genblk1[87] $end
$upscope $end
$scope begin genblk1[88] $end
$upscope $end
$scope begin genblk1[89] $end
$upscope $end
$scope begin genblk1[90] $end
$upscope $end
$scope begin genblk1[91] $end
$upscope $end
$scope begin genblk1[92] $end
$upscope $end
$scope begin genblk1[93] $end
$upscope $end
$scope begin genblk1[94] $end
$upscope $end
$scope begin genblk1[95] $end
$upscope $end
$scope begin genblk1[96] $end
$upscope $end
$scope begin genblk1[97] $end
$upscope $end
$scope begin genblk1[98] $end
$upscope $end
$scope begin genblk1[99] $end
$upscope $end
$scope begin genblk1[100] $end
$upscope $end
$scope begin genblk1[101] $end
$upscope $end
$scope begin genblk1[102] $end
$upscope $end
$scope begin genblk1[103] $end
$upscope $end
$scope begin genblk1[104] $end
$upscope $end
$scope begin genblk1[105] $end
$upscope $end
$scope begin genblk1[106] $end
$upscope $end
$scope begin genblk1[107] $end
$upscope $end
$scope begin genblk1[108] $end
$upscope $end
$scope begin genblk1[109] $end
$upscope $end
$scope begin genblk1[110] $end
$upscope $end
$scope begin genblk1[111] $end
$upscope $end
$scope begin genblk1[112] $end
$upscope $end
$scope begin genblk1[113] $end
$upscope $end
$scope begin genblk1[114] $end
$upscope $end
$scope begin genblk1[115] $end
$upscope $end
$scope begin genblk1[116] $end
$upscope $end
$scope begin genblk1[117] $end
$upscope $end
$scope begin genblk1[118] $end
$upscope $end
$scope begin genblk1[119] $end
$upscope $end
$scope begin genblk1[120] $end
$upscope $end
$scope begin genblk1[121] $end
$upscope $end
$scope begin genblk1[122] $end
$upscope $end
$scope begin genblk1[123] $end
$upscope $end
$scope begin genblk1[124] $end
$upscope $end
$scope begin genblk1[125] $end
$upscope $end
$scope begin genblk1[126] $end
$upscope $end
$scope begin genblk1[127] $end
$upscope $end
$scope begin genblk1[128] $end
$upscope $end
$scope begin genblk1[129] $end
$upscope $end
$scope begin genblk1[130] $end
$upscope $end
$scope begin genblk1[131] $end
$upscope $end
$scope begin genblk1[132] $end
$upscope $end
$scope begin genblk1[133] $end
$upscope $end
$scope begin genblk1[134] $end
$upscope $end
$scope begin genblk1[135] $end
$upscope $end
$scope begin genblk1[136] $end
$upscope $end
$upscope $end
$upscope $end
$enddefinitions $end
#0
$dumpvars
bx #
0"
x!
$end
#3
b0xxxxxxxxxxxxxxxxxxxxxxxxxxxxxxxxxxxxxxxxxxxxxxxxxxxxxxxxxxxxxxxxxxxxxxxxxxxxxxxxxxxxxxxxxxxxxxxxxxxxxxxxxxxxxxxxxxxxxxxxxxxxxxxxxxxxxxxxx #
#4
b1xxxxxxxxxxxxxxxxxxxxxxxxxxxxxxxxxxxxxxxxxxxxxxxxxxxxxxxxxxxxxxxxxxxxxxxxxxxxxxxxxxxxxxxxxxxxxxxxxxxxxxxxxxxxxxxxxxxxxxxxxxxxxxxxxxxxxxxx #
#5
b10xxxxxxxxxxxxxxxxxxxxxxxxxxxxxxxxxxxxxxxxxxxxxxxxxxxxxxxxxxxxxxxxxxxxxxxxxxxxxxxxxxxxxxxxxxxxxxxxxxxxxxxxxxxxxxxxxxxxxxxxxxxxxxxxxxxxxxx #
#6
b101xxxxxxxxxxxxxxxxxxxxxxxxxxxxxxxxxxxxxxxxxxxxxxxxxxxxxxxxxxxxxxxxxxxxxxxxxxxxxxxxxxxxxxxxxxxxxxxxxxxxxxxxxxxxxxxxxxxxxxxxxxxxxxxxxxxxxx #
#7
b1010xxxxxxxxxxxxxxxxxxxxxxxxxxxxxxxxxxxxxxxxxxxxxxxxxxxxxxxxxxxxxxxxxxxxxxxxxxxxxxxxxxxxxxxxxxxxxxxxxxxxxxxxxxxxxxxxxxxxxxxxxxxxxxxxxxxxx #
#8
b10101xxxxxxxxxxxxxxxxxxxxxxxxxxxxxxxxxxxxxxxxxxxxxxxxxxxxxxxxxxxxxxxxxxxxxxxxxxxxxxxxxxxxxxxxxxxxxxxxxxxxxxxxxxxxxxxxxxxxxxxxxxxxxxxxxxxx #
#9
b101010xxxxxxxxxxxxxxxxxxxxxxxxxxxxxxxxxxxxxxxxxxxxxxxxxxxxxxxxxxxxxxxxxxxxxxxxxxxxxxxxxxxxxxxxxxxxxxxxxxxxxxxxxxxxxxxxxxxxxxxxxxxxxxxxxxx #
#10
b1010101xxxxxxxxxxxxxxxxxxxxxxxxxxxxxxxxxxxxxxxxxxxxxxxxxxxxxxxxxxxxxxxxxxxxxxxxxxxxxxxxxxxxxxxxxxxxxxxxxxxxxxxxxxxxxxxxxxxxxxxxxxxxxxxxxx #
#11
b10101010xxxxxxxxxxxxxxxxxxxxxxxxxxxxxxxxxxxxxxxxxxxxxxxxxxxxxxxxxxxxxxxxxxxxxxxxxxxxxxxxxxxxxxxxxxxxxxxxxxxxxxxxxxxxxxxxxxxxxxxxxxxxxxxxx #
#12
b101010101xxxxxxxxxxxxxxxxxxxxxxxxxxxxxxxxxxxxxxxxxxxxxxxxxxxxxxxxxxxxxxxxxxxxxxxxxxxxxxxxxxxxxxxxxxxxxxxxxxxxxxxxxxxxxxxxxxxxxxxxxxxxxxxx #
#13
b1010101010xxxxxxxxxxxxxxxxxxxxxxxxxxxxxxxxxxxxxxxxxxxxxxxxxxxxxxxxxxxxxxxxxxxxxxxxxxxxxxxxxxxxxxxxxxxxxxxxxxxxxxxxxxxxxxxxxxxxxxxxxxxxxxx #
#14
b10101010101xxxxxxxxxxxxxxxxxxxxxxxxxxxxxxxxxxxxxxxxxxxxxxxxxxxxxxxxxxxxxxxxxxxxxxxxxxxxxxxxxxxxxxxxxxxxxxxxxxxxxxxxxxxxxxxxxxxxxxxxxxxxxx #
#15
b101010101010xxxxxxxxxxxxxxxxxxxxxxxxxxxxxxxxxxxxxxxxxxxxxxxxxxxxxxxxxxxxxxxxxxxxxxxxxxxxxxxxxxxxxxxxxxxxxxxxxxxxxxxxxxxxxxxxxxxxxxxxxxxxx #
#16
b1010101010101xxxxxxxxxxxxxxxxxxxxxxxxxxxxxxxxxxxxxxxxxxxxxxxxxxxxxxxxxxxxxxxxxxxxxxxxxxxxxxxxxxxxxxxxxxxxxxxxxxxxxxxxxxxxxxxxxxxxxxxxxxxx #
#17
b10101010101010xxxxxxxxxxxxxxxxxxxxxxxxxxxxxxxxxxxxxxxxxxxxxxxxxxxxxxxxxxxxxxxxxxxxxxxxxxxxxxxxxxxxxxxxxxxxxxxxxxxxxxxxxxxxxxxxxxxxxxxxxxx #
#18
b101010101010101xxxxxxxxxxxxxxxxxxxxxxxxxxxxxxxxxxxxxxxxxxxxxxxxxxxxxxxxxxxxxxxxxxxxxxxxxxxxxxxxxxxxxxxxxxxxxxxxxxxxxxxxxxxxxxxxxxxxxxxxxx #
#19
b1010101010101010xxxxxxxxxxxxxxxxxxxxxxxxxxxxxxxxxxxxxxxxxxxxxxxxxxxxxxxxxxxxxxxxxxxxxxxxxxxxxxxxxxxxxxxxxxxxxxxxxxxxxxxxxxxxxxxxxxxxxxxxx #
#20
b10101010101010101xxxxxxxxxxxxxxxxxxxxxxxxxxxxxxxxxxxxxxxxxxxxxxxxxxxxxxxxxxxxxxxxxxxxxxxxxxxxxxxxxxxxxxxxxxxxxxxxxxxxxxxxxxxxxxxxxxxxxxxx #
#21
b101010101010101010xxxxxxxxxxxxxxxxxxxxxxxxxxxxxxxxxxxxxxxxxxxxxxxxxxxxxxxxxxxxxxxxxxxxxxxxxxxxxxxxxxxxxxxxxxxxxxxxxxxxxxxxxxxxxxxxxxxxxxx #
#22
b1010101010101010101xxxxxxxxxxxxxxxxxxxxxxxxxxxxxxxxxxxxxxxxxxxxxxxxxxxxxxxxxxxxxxxxxxxxxxxxxxxxxxxxxxxxxxxxxxxxxxxxxxxxxxxxxxxxxxxxxxxxxx #
#23
b10101010101010101010xxxxxxxxxxxxxxxxxxxxxxxxxxxxxxxxxxxxxxxxxxxxxxxxxxxxxxxxxxxxxxxxxxxxxxxxxxxxxxxxxxxxxxxxxxxxxxxxxxxxxxxxxxxxxxxxxxxxx #
#24
b101010101010101010101xxxxxxxxxxxxxxxxxxxxxxxxxxxxxxxxxxxxxxxxxxxxxxxxxxxxxxxxxxxxxxxxxxxxxxxxxxxxxxxxxxxxxxxxxxxxxxxxxxxxxxxxxxxxxxxxxxxx #
#25
b1010101010101010101010xxxxxxxxxxxxxxxxxxxxxxxxxxxxxxxxxxxxxxxxxxxxxxxxxxxxxxxxxxxxxxxxxxxxxxxxxxxxxxxxxxxxxxxxxxxxxxxxxxxxxxxxxxxxxxxxxxx #
#26
b10101010101010101010101xxxxxxxxxxxxxxxxxxxxxxxxxxxxxxxxxxxxxxxxxxxxxxxxxxxxxxxxxxxxxxxxxxxxxxxxxxxxxxxxxxxxxxxxxxxxxxxxxxxxxxxxxxxxxxxxxx #
#27
b101010101010101010101010xxxxxxxxxxxxxxxxxxxxxxxxxxxxxxxxxxxxxxxxxxxxxxxxxxxxxxxxxxxxxxxxxxxxxxxxxxxxxxxxxxxxxxxxxxxxxxxxxxxxxxxxxxxxxxxxx #
#28
b1010101010101010101010101xxxxxxxxxxxxxxxxxxxxxxxxxxxxxxxxxxxxxxxxxxxxxxxxxxxxxxxxxxxxxxxxxxxxxxxxxxxxxxxxxxxxxxxxxxxxxxxxxxxxxxxxxxxxxxxx #
#29
b10101010101010101010101010xxxxxxxxxxxxxxxxxxxxxxxxxxxxxxxxxxxxxxxxxxxxxxxxxxxxxxxxxxxxxxxxxxxxxxxxxxxxxxxxxxxxxxxxxxxxxxxxxxxxxxxxxxxxxxx #
#30
b101010101010101010101010101xxxxxxxxxxxxxxxxxxxxxxxxxxxxxxxxxxxxxxxxxxxxxxxxxxxxxxxxxxxxxxxxxxxxxxxxxxxxxxxxxxxxxxxxxxxxxxxxxxxxxxxxxxxxxx #
#31
b1010101010101010101010101010xxxxxxxxxxxxxxxxxxxxxxxxxxxxxxxxxxxxxxxxxxxxxxxxxxxxxxxxxxxxxxxxxxxxxxxxxxxxxxxxxxxxxxxxxxxxxxxxxxxxxxxxxxxxx #
#32
b10101010101010101010101010101xxxxxxxxxxxxxxxxxxxxxxxxxxxxxxxxxxxxxxxxxxxxxxxxxxxxxxxxxxxxxxxxxxxxxxxxxxxxxxxxxxxxxxxxxxxxxxxxxxxxxxxxxxxx #
#33
b101010101010101010101010101010xxxxxxxxxxxxxxxxxxxxxxxxxxxxxxxxxxxxxxxxxxxxxxxxxxxxxxxxxxxxxxxxxxxxxxxxxxxxxxxxxxxxxxxxxxxxxxxxxxxxxxxxxxx #
#34
b1010101010101010101010101010101xxxxxxxxxxxxxxxxxxxxxxxxxxxxxxxxxxxxxxxxxxxxxxxxxxxxxxxxxxxxxxxxxxxxxxxxxxxxxxxxxxxxxxxxxxxxxxxxxxxxxxxxxx #
#35
b10101010101010101010101010101010xxxxxxxxxxxxxxxxxxxxxxxxxxxxxxxxxxxxxxxxxxxxxxxxxxxxxxxxxxxxxxxxxxxxxxxxxxxxxxxxxxxxxxxxxxxxxxxxxxxxxxxxx #
#36
b101010101010101010101010101010101xxxxxxxxxxxxxxxxxxxxxxxxxxxxxxxxxxxxxxxxxxxxxxxxxxxxxxxxxxxxxxxxxxxxxxxxxxxxxxxxxxxxxxxxxxxxxxxxxxxxxxxx #
#37
b1010101010101010101010101010101010xxxxxxxxxxxxxxxxxxxxxxxxxxxxxxxxxxxxxxxxxxxxxxxxxxxxxxxxxxxxxxxxxxxxxxxxxxxxxxxxxxxxxxxxxxxxxxxxxxxxxxx #
#38
b10101010101010101010101010101010101xxxxxxxxxxxxxxxxxxxxxxxxxxxxxxxxxxxxxxxxxxxxxxxxxxxxxxxxxxxxxxxxxxxxxxxxxxxxxxxxxxxxxxxxxxxxxxxxxxxxxx #
#39
b101010101010101010101010101010101010xxxxxxxxxxxxxxxxxxxxxxxxxxxxxxxxxxxxxxxxxxxxxxxxxxxxxxxxxxxxxxxxxxxxxxxxxxxxxxxxxxxxxxxxxxxxxxxxxxxxx #
#40
b1010101010101010101010101010101010101xxxxxxxxxxxxxxxxxxxxxxxxxxxxxxxxxxxxxxxxxxxxxxxxxxxxxxxxxxxxxxxxxxxxxxxxxxxxxxxxxxxxxxxxxxxxxxxxxxxx #
#41
b10101010101010101010101010101010101010xxxxxxxxxxxxxxxxxxxxxxxxxxxxxxxxxxxxxxxxxxxxxxxxxxxxxxxxxxxxxxxxxxxxxxxxxxxxxxxxxxxxxxxxxxxxxxxxxxx #
#42
b101010101010101010101010101010101010101xxxxxxxxxxxxxxxxxxxxxxxxxxxxxxxxxxxxxxxxxxxxxxxxxxxxxxxxxxxxxxxxxxxxxxxxxxxxxxxxxxxxxxxxxxxxxxxxxx #
#43
b1010101010101010101010101010101010101010xxxxxxxxxxxxxxxxxxxxxxxxxxxxxxxxxxxxxxxxxxxxxxxxxxxxxxxxxxxxxxxxxxxxxxxxxxxxxxxxxxxxxxxxxxxxxxxxx #
#44
b10101010101010101010101010101010101010101xxxxxxxxxxxxxxxxxxxxxxxxxxxxxxxxxxxxxxxxxxxxxxxxxxxxxxxxxxxxxxxxxxxxxxxxxxxxxxxxxxxxxxxxxxxxxxxx #
#45
b101010101010101010101010101010101010101010xxxxxxxxxxxxxxxxxxxxxxxxxxxxxxxxxxxxxxxxxxxxxxxxxxxxxxxxxxxxxxxxxxxxxxxxxxxxxxxxxxxxxxxxxxxxxxx #
#46
b1010101010101010101010101010101010101010101xxxxxxxxxxxxxxxxxxxxxxxxxxxxxxxxxxxxxxxxxxxxxxxxxxxxxxxxxxxxxxxxxxxxxxxxxxxxxxxxxxxxxxxxxxxxxx #
#47
b10101010101010101010101010101010101010101010xxxxxxxxxxxxxxxxxxxxxxxxxxxxxxxxxxxxxxxxxxxxxxxxxxxxxxxxxxxxxxxxxxxxxxxxxxxxxxxxxxxxxxxxxxxxx #
#48
b101010101010101010101010101010101010101010101xxxxxxxxxxxxxxxxxxxxxxxxxxxxxxxxxxxxxxxxxxxxxxxxxxxxxxxxxxxxxxxxxxxxxxxxxxxxxxxxxxxxxxxxxxxx #
#49
b1010101010101010101010101010101010101010101010xxxxxxxxxxxxxxxxxxxxxxxxxxxxxxxxxxxxxxxxxxxxxxxxxxxxxxxxxxxxxxxxxxxxxxxxxxxxxxxxxxxxxxxxxxx #
#50
b10101010101010101010101010101010101010101010101xxxxxxxxxxxxxxxxxxxxxxxxxxxxxxxxxxxxxxxxxxxxxxxxxxxxxxxxxxxxxxxxxxxxxxxxxxxxxxxxxxxxxxxxxx #
#51
b101010101010101010101010101010101010101010101010xxxxxxxxxxxxxxxxxxxxxxxxxxxxxxxxxxxxxxxxxxxxxxxxxxxxxxxxxxxxxxxxxxxxxxxxxxxxxxxxxxxxxxxxx #
#52
b1010101010101010101010101010101010101010101010101xxxxxxxxxxxxxxxxxxxxxxxxxxxxxxxxxxxxxxxxxxxxxxxxxxxxxxxxxxxxxxxxxxxxxxxxxxxxxxxxxxxxxxxx #
#53
b10101010101010101010101010101010101010101010101010xxxxxxxxxxxxxxxxxxxxxxxxxxxxxxxxxxxxxxxxxxxxxxxxxxxxxxxxxxxxxxxxxxxxxxxxxxxxxxxxxxxxxxx #
#54
b101010101010101010101010101010101010101010101010101xxxxxxxxxxxxxxxxxxxxxxxxxxxxxxxxxxxxxxxxxxxxxxxxxxxxxxxxxxxxxxxxxxxxxxxxxxxxxxxxxxxxxx #
#55
b1010101010101010101010101010101010101010101010101010xxxxxxxxxxxxxxxxxxxxxxxxxxxxxxxxxxxxxxxxxxxxxxxxxxxxxxxxxxxxxxxxxxxxxxxxxxxxxxxxxxxxx #
#56
b10101010101010101010101010101010101010101010101010101xxxxxxxxxxxxxxxxxxxxxxxxxxxxxxxxxxxxxxxxxxxxxxxxxxxxxxxxxxxxxxxxxxxxxxxxxxxxxxxxxxxx #
#57
b101010101010101010101010101010101010101010101010101010xxxxxxxxxxxxxxxxxxxxxxxxxxxxxxxxxxxxxxxxxxxxxxxxxxxxxxxxxxxxxxxxxxxxxxxxxxxxxxxxxxx #
#58
b1010101010101010101010101010101010101010101010101010101xxxxxxxxxxxxxxxxxxxxxxxxxxxxxxxxxxxxxxxxxxxxxxxxxxxxxxxxxxxxxxxxxxxxxxxxxxxxxxxxxx #
#59
b10101010101010101010101010101010101010101010101010101010xxxxxxxxxxxxxxxxxxxxxxxxxxxxxxxxxxxxxxxxxxxxxxxxxxxxxxxxxxxxxxxxxxxxxxxxxxxxxxxxx #
#60
b101010101010101010101010101010101010101010101010101010101xxxxxxxxxxxxxxxxxxxxxxxxxxxxxxxxxxxxxxxxxxxxxxxxxxxxxxxxxxxxxxxxxxxxxxxxxxxxxxxx #
#61
b1010101010101010101010101010101010101010101010101010101010xxxxxxxxxxxxxxxxxxxxxxxxxxxxxxxxxxxxxxxxxxxxxxxxxxxxxxxxxxxxxxxxxxxxxxxxxxxxxxx #
#62
b10101010101010101010101010101010101010101010101010101010101xxxxxxxxxxxxxxxxxxxxxxxxxxxxxxxxxxxxxxxxxxxxxxxxxxxxxxxxxxxxxxxxxxxxxxxxxxxxxx #
#63
b101010101010101010101010101010101010101010101010101010101010xxxxxxxxxxxxxxxxxxxxxxxxxxxxxxxxxxxxxxxxxxxxxxxxxxxxxxxxxxxxxxxxxxxxxxxxxxxxx #
#64
b1010101010101010101010101010101010101010101010101010101010101xxxxxxxxxxxxxxxxxxxxxxxxxxxxxxxxxxxxxxxxxxxxxxxxxxxxxxxxxxxxxxxxxxxxxxxxxxxx #
#65
b10101010101010101010101010101010101010101010101010101010101010xxxxxxxxxxxxxxxxxxxxxxxxxxxxxxxxxxxxxxxxxxxxxxxxxxxxxxxxxxxxxxxxxxxxxxxxxxx #
#66
b101010101010101010101010101010101010101010101010101010101010101xxxxxxxxxxxxxxxxxxxxxxxxxxxxxxxxxxxxxxxxxxxxxxxxxxxxxxxxxxxxxxxxxxxxxxxxxx #
#67
b1010101010101010101010101010101010101010101010101010101010101010xxxxxxxxxxxxxxxxxxxxxxxxxxxxxxxxxxxxxxxxxxxxxxxxxxxxxxxxxxxxxxxxxxxxxxxxx #
#68
b10101010101010101010101010101010101010101010101010101010101010101xxxxxxxxxxxxxxxxxxxxxxxxxxxxxxxxxxxxxxxxxxxxxxxxxxxxxxxxxxxxxxxxxxxxxxxx #
#69
b101010101010101010101010101010101010101010101010101010101010101010xxxxxxxxxxxxxxxxxxxxxxxxxxxxxxxxxxxxxxxxxxxxxxxxxxxxxxxxxxxxxxxxxxxxxxx #
#70
b1010101010101010101010101010101010101010101010101010101010101010101xxxxxxxxxxxxxxxxxxxxxxxxxxxxxxxxxxxxxxxxxxxxxxxxxxxxxxxxxxxxxxxxxxxxxx #
#71
b10101010101010101010101010101010101010101010101010101010101010101010xxxxxxxxxxxxxxxxxxxxxxxxxxxxxxxxxxxxxxxxxxxxxxxxxxxxxxxxxxxxxxxxxxxxx #
#72
b101010101010101010101010101010101010101010101010101010101010101010101xxxxxxxxxxxxxxxxxxxxxxxxxxxxxxxxxxxxxxxxxxxxxxxxxxxxxxxxxxxxxxxxxxxx #
#73
b1010101010101010101010101010101010101010101010101010101010101010101010xxxxxxxxxxxxxxxxxxxxxxxxxxxxxxxxxxxxxxxxxxxxxxxxxxxxxxxxxxxxxxxxxxx #
#74
b10101010101010101010101010101010101010101010101010101010101010101010101xxxxxxxxxxxxxxxxxxxxxxxxxxxxxxxxxxxxxxxxxxxxxxxxxxxxxxxxxxxxxxxxxx #
#75
b101010101010101010101010101010101010101010101010101010101010101010101010xxxxxxxxxxxxxxxxxxxxxxxxxxxxxxxxxxxxxxxxxxxxxxxxxxxxxxxxxxxxxxxxx #
#76
b1010101010101010101010101010101010101010101010101010101010101010101010101xxxxxxxxxxxxxxxxxxxxxxxxxxxxxxxxxxxxxxxxxxxxxxxxxxxxxxxxxxxxxxxx #
#77
b10101010101010101010101010101010101010101010101010101010101010101010101010xxxxxxxxxxxxxxxxxxxxxxxxxxxxxxxxxxxxxxxxxxxxxxxxxxxxxxxxxxxxxxx #
#78
b101010101010101010101010101010101010101010101010101010101010101010101010101xxxxxxxxxxxxxxxxxxxxxxxxxxxxxxxxxxxxxxxxxxxxxxxxxxxxxxxxxxxxxx #
#79
b1010101010101010101010101010101010101010101010101010101010101010101010101010xxxxxxxxxxxxxxxxxxxxxxxxxxxxxxxxxxxxxxxxxxxxxxxxxxxxxxxxxxxxx #
#80
b10101010101010101010101010101010101010101010101010101010101010101010101010101xxxxxxxxxxxxxxxxxxxxxxxxxxxxxxxxxxxxxxxxxxxxxxxxxxxxxxxxxxxx #
#81
b101010101010101010101010101010101010101010101010101010101010101010101010101010xxxxxxxxxxxxxxxxxxxxxxxxxxxxxxxxxxxxxxxxxxxxxxxxxxxxxxxxxxx #
#82
b1010101010101010101010101010101010101010101010101010101010101010101010101010101xxxxxxxxxxxxxxxxxxxxxxxxxxxxxxxxxxxxxxxxxxxxxxxxxxxxxxxxxx #
#83
b10101010101010101010101010101010101010101010101010101010101010101010101010101010xxxxxxxxxxxxxxxxxxxxxxxxxxxxxxxxxxxxxxxxxxxxxxxxxxxxxxxxx #
#84
b101010101010101010101010101010101010101010101010101010101010101010101010101010101xxxxxxxxxxxxxxxxxxxxxxxxxxxxxxxxxxxxxxxxxxxxxxxxxxxxxxxx #
#85
b1010101010101010101010101010101010101010101010101010101010101010101010101010101010xxxxxxxxxxxxxxxxxxxxxxxxxxxxxxxxxxxxxxxxxxxxxxxxxxxxxxx #
#86
b10101010101010101010101010101010101010101010101010101010101010101010101010101010101xxxxxxxxxxxxxxxxxxxxxxxxxxxxxxxxxxxxxxxxxxxxxxxxxxxxxx #
#87
b101010101010101010101010101010101010101010101010101010101010101010101010101010101010xxxxxxxxxxxxxxxxxxxxxxxxxxxxxxxxxxxxxxxxxxxxxxxxxxxxx #
#88
b1010101010101010101010101010101010101010101010101010101010101010101010101010101010101xxxxxxxxxxxxxxxxxxxxxxxxxxxxxxxxxxxxxxxxxxxxxxxxxxxx #
#89
b10101010101010101010101010101010101010101010101010101010101010101010101010101010101010xxxxxxxxxxxxxxxxxxxxxxxxxxxxxxxxxxxxxxxxxxxxxxxxxxx #
#90
b101010101010101010101010101010101010101010101010101010101010101010101010101010101010101xxxxxxxxxxxxxxxxxxxxxxxxxxxxxxxxxxxxxxxxxxxxxxxxxx #
#91
b1010101010101010101010101010101010101010101010101010101010101010101010101010101010101010xxxxxxxxxxxxxxxxxxxxxxxxxxxxxxxxxxxxxxxxxxxxxxxxx #
#92
b10101010101010101010101010101010101010101010101010101010101010101010101010101010101010101xxxxxxxxxxxxxxxxxxxxxxxxxxxxxxxxxxxxxxxxxxxxxxxx #
#93
b101010101010101010101010101010101010101010101010101010101010101010101010101010101010101010xxxxxxxxxxxxxxxxxxxxxxxxxxxxxxxxxxxxxxxxxxxxxxx #
#94
b1010101010101010101010101010101010101010101010101010101010101010101010101010101010101010101xxxxxxxxxxxxxxxxxxxxxxxxxxxxxxxxxxxxxxxxxxxxxx #
#95
b10101010101010101010101010101010101010101010101010101010101010101010101010101010101010101010xxxxxxxxxxxxxxxxxxxxxxxxxxxxxxxxxxxxxxxxxxxxx #
#96
b101010101010101010101010101010101010101010101010101010101010101010101010101010101010101010101xxxxxxxxxxxxxxxxxxxxxxxxxxxxxxxxxxxxxxxxxxxx #
#97
b1010101010101010101010101010101010101010101010101010101010101010101010101010101010101010101010xxxxxxxxxxxxxxxxxxxxxxxxxxxxxxxxxxxxxxxxxxx #
#98
b10101010101010101010101010101010101010101010101010101010101010101010101010101010101010101010101xxxxxxxxxxxxxxxxxxxxxxxxxxxxxxxxxxxxxxxxxx #
#99
b101010101010101010101010101010101010101010101010101010101010101010101010101010101010101010101010xxxxxxxxxxxxxxxxxxxxxxxxxxxxxxxxxxxxxxxxx #
#100
b1010101010101010101010101010101010101010101010101010101010101010101010101010101010101010101010101xxxxxxxxxxxxxxxxxxxxxxxxxxxxxxxxxxxxxxxx #
#101
b10101010101010101010101010101010101010101010101010101010101010101010101010101010101010101010101010xxxxxxxxxxxxxxxxxxxxxxxxxxxxxxxxxxxxxxx #
#102
b101010101010101010101010101010101010101010101010101010101010101010101010101010101010101010101010101xxxxxxxxxxxxxxxxxxxxxxxxxxxxxxxxxxxxxx #
#103
b1010101010101010101010101010101010101010101010101010101010101010101010101010101010101010101010101010xxxxxxxxxxxxxxxxxxxxxxxxxxxxxxxxxxxxx #
#104
b10101010101010101010101010101010101010101010101010101010101010101010101010101010101010101010101010101xxxxxxxxxxxxxxxxxxxxxxxxxxxxxxxxxxxx #
#105
b101010101010101010101010101010101010101010101010101010101010101010101010101010101010101010101010101010xxxxxxxxxxxxxxxxxxxxxxxxxxxxxxxxxxx #
#106
b1010101010101010101010101010101010101010101010101010101010101010101010101010101010101010101010101010101xxxxxxxxxxxxxxxxxxxxxxxxxxxxxxxxxx #
