oscillator/oscillator.v
// Critical path = period/2 = 76 ns
module oscillator(en, w0);
   parameter N = 73; // # of not gates
   input en;
   output w0;
   wire   [N:0] w;
   and #(3) and_0(w[N], en, w[0]);
   genvar i;
   generate
      for (i = N-1; i >= 0; i = i-1) begin
         not #(1) not_i(/*输出*/w[i], /*输入*/w[i+1]);
      end
   endgenerate
   buf buf_0(w0, w[0]);
endmodule;

oscillator/testbench.v
`timescale 1 ns/1 ns	//time scale for simulation

module testbench;
   reg en;
   wire w0;

   oscillator my_oscillator(.en(en), .w0(w0));

   initial begin
      $dumpfile("test.vcd");
      $dumpvars(0, testbench);
      en = 0;
      #76;
      en = 1; // then oscillator will run until $finish
      #304 $finish; // finish simulation
   end
endmodule

oscillator/test.vcd
$date
	Fri Sep  9 12:06:14 2022
$end
$version
	Icarus Verilog
$end
$timescale
	1ns
$end
$scope module testbench $end
$var wire 1 ! w0 $end
$var reg 1 " en $end
$scope module my_oscillator $end
$var wire 1 " en $end
$var wire 1 ! w0 $end
$var wire 74 # w [73:0] $end
$scope begin genblk1[0] $end
$upscope $end
$scope begin genblk1[1] $end
$upscope $end
$scope begin genblk1[2] $end
$upscope $end
$scope begin genblk1[3] $end
$upscope $end
$scope begin genblk1[4] $end
$upscope $end
$scope begin genblk1[5] $end
$upscope $end
$scope begin genblk1[6] $end
$upscope $end
$scope begin genblk1[7] $end
$upscope $end
$scope begin genblk1[8] $end
$upscope $end
$scope begin genblk1[9] $end
$upscope $end
$scope begin genblk1[10] $end
$upscope $end
$scope begin genblk1[11] $end
$upscope $end
$scope begin genblk1[12] $end
$upscope $end
$scope begin genblk1[13] $end
$upscope $end
$scope begin genblk1[14] $end
$upscope $end
$scope begin genblk1[15] $end
$upscope $end
$scope begin genblk1[16] $end
$upscope $end
$scope begin genblk1[17] $end
$upscope $end
$scope begin genblk1[18] $end
$upscope $end
$scope begin genblk1[19] $end
$upscope $end
$scope begin genblk1[20] $end
$upscope $end
$scope begin genblk1[21] $end
$upscope $end
$scope begin genblk1[22] $end
$upscope $end
$scope begin genblk1[23] $end
$upscope $end
$scope begin genblk1[24] $end
$upscope $end
$scope begin genblk1[25] $end
$upscope $end
$scope begin genblk1[26] $end
$upscope $end
$scope begin genblk1[27] $end
$upscope $end
$scope begin genblk1[28] $end
$upscope $end
$scope begin genblk1[29] $end
$upscope $end
$scope begin genblk1[30] $end
$upscope $end
$scope begin genblk1[31] $end
$upscope $end
$scope begin genblk1[32] $end
$upscope $end
$scope begin genblk1[33] $end
$upscope $end
$scope begin genblk1[34] $end
$upscope $end
$scope begin genblk1[35] $end
$upscope $end
$scope begin genblk1[36] $end
$upscope $end
$scope begin genblk1[37] $end
$upscope $end
$scope begin genblk1[38] $end
$upscope $end
$scope begin genblk1[39] $end
$upscope $end
$scope begin genblk1[40] $end
$upscope $end
$scope begin genblk1[41] $end
$upscope $end
$scope begin genblk1[42] $end
$upscope $end
$scope begin genblk1[43] $end
$upscope $end
$scope begin genblk1[44] $end
$upscope $end
$scope begin genblk1[45] $end
$upscope $end
$scope begin genblk1[46] $end
$upscope $end
$scope begin genblk1[47] $end
$upscope $end
$scope begin genblk1[48] $end
$upscope $end
$scope begin genblk1[49] $end
$upscope $end
$scope begin genblk1[50] $end
$upscope $end
$scope begin genblk1[51] $end
$upscope $end
$scope begin genblk1[52] $end
$upscope $end
$scope begin genblk1[53] $end
$upscope $end
$scope begin genblk1[54] $end
$upscope $end
$scope begin genblk1[55] $end
$upscope $end
$scope begin genblk1[56] $end
$upscope $end
$scope begin genblk1[57] $end
$upscope $end
$scope begin genblk1[58] $end
$upscope $end
$scope begin genblk1[59] $end
$upscope $end
$scope begin genblk1[60] $end
$upscope $end
$scope begin genblk1[61] $end
$upscope $end
$scope begin genblk1[62] $end
$upscope $end
$scope begin genblk1[63] $end
$upscope $end
$scope begin genblk1[64] $end
$upscope $end
$scope begin genblk1[65] $end
$upscope $end
$scope begin genblk1[66] $end
$upscope $end
$scope begin genblk1[67] $end
$upscope $end
$scope begin genblk1[68] $end
$upscope $end
$scope begin genblk1[69] $end
$upscope $end
$scope begin genblk1[70] $end
$upscope $end
$scope begin genblk1[71] $end
$upscope $end
$scope begin genblk1[72] $end
$upscope $end
$upscope $end
$upscope $end
$enddefinitions $end
#0
$dumpvars
bx #
0"
x!
$end
#3
b0xxxxxxxxxxxxxxxxxxxxxxxxxxxxxxxxxxxxxxxxxxxxxxxxxxxxxxxxxxxxxxxxxxxxxxxxx #
#4
b1xxxxxxxxxxxxxxxxxxxxxxxxxxxxxxxxxxxxxxxxxxxxxxxxxxxxxxxxxxxxxxxxxxxxxxxx #
#5
b10xxxxxxxxxxxxxxxxxxxxxxxxxxxxxxxxxxxxxxxxxxxxxxxxxxxxxxxxxxxxxxxxxxxxxxx #
#6
b101xxxxxxxxxxxxxxxxxxxxxxxxxxxxxxxxxxxxxxxxxxxxxxxxxxxxxxxxxxxxxxxxxxxxxx #
#7
b1010xxxxxxxxxxxxxxxxxxxxxxxxxxxxxxxxxxxxxxxxxxxxxxxxxxxxxxxxxxxxxxxxxxxxx #
#8
b10101xxxxxxxxxxxxxxxxxxxxxxxxxxxxxxxxxxxxxxxxxxxxxxxxxxxxxxxxxxxxxxxxxxxx #
#9
b101010xxxxxxxxxxxxxxxxxxxxxxxxxxxxxxxxxxxxxxxxxxxxxxxxxxxxxxxxxxxxxxxxxxx #
#10
b1010101xxxxxxxxxxxxxxxxxxxxxxxxxxxxxxxxxxxxxxxxxxxxxxxxxxxxxxxxxxxxxxxxxx #
#11
b10101010xxxxxxxxxxxxxxxxxxxxxxxxxxxxxxxxxxxxxxxxxxxxxxxxxxxxxxxxxxxxxxxxx #
#12
b101010101xxxxxxxxxxxxxxxxxxxxxxxxxxxxxxxxxxxxxxxxxxxxxxxxxxxxxxxxxxxxxxxx #
#13
b1010101010xxxxxxxxxxxxxxxxxxxxxxxxxxxxxxxxxxxxxxxxxxxxxxxxxxxxxxxxxxxxxxx #
#14
b10101010101xxxxxxxxxxxxxxxxxxxxxxxxxxxxxxxxxxxxxxxxxxxxxxxxxxxxxxxxxxxxxx #
#15
b101010101010xxxxxxxxxxxxxxxxxxxxxxxxxxxxxxxxxxxxxxxxxxxxxxxxxxxxxxxxxxxxx #
#16
b1010101010101xxxxxxxxxxxxxxxxxxxxxxxxxxxxxxxxxxxxxxxxxxxxxxxxxxxxxxxxxxxx #
#17
b10101010101010xxxxxxxxxxxxxxxxxxxxxxxxxxxxxxxxxxxxxxxxxxxxxxxxxxxxxxxxxxx #
#18
b101010101010101xxxxxxxxxxxxxxxxxxxxxxxxxxxxxxxxxxxxxxxxxxxxxxxxxxxxxxxxxx #
#19
b1010101010101010xxxxxxxxxxxxxxxxxxxxxxxxxxxxxxxxxxxxxxxxxxxxxxxxxxxxxxxxx #
#20
b10101010101010101xxxxxxxxxxxxxxxxxxxxxxxxxxxxxxxxxxxxxxxxxxxxxxxxxxxxxxxx #
#21
b101010101010101010xxxxxxxxxxxxxxxxxxxxxxxxxxxxxxxxxxxxxxxxxxxxxxxxxxxxxxx #
#22
b1010101010101010101xxxxxxxxxxxxxxxxxxxxxxxxxxxxxxxxxxxxxxxxxxxxxxxxxxxxxx #
#23
b10101010101010101010xxxxxxxxxxxxxxxxxxxxxxxxxxxxxxxxxxxxxxxxxxxxxxxxxxxxx #
#24
b101010101010101010101xxxxxxxxxxxxxxxxxxxxxxxxxxxxxxxxxxxxxxxxxxxxxxxxxxxx #
#25
b1010101010101010101010xxxxxxxxxxxxxxxxxxxxxxxxxxxxxxxxxxxxxxxxxxxxxxxxxxx #
#26
b10101010101010101010101xxxxxxxxxxxxxxxxxxxxxxxxxxxxxxxxxxxxxxxxxxxxxxxxxx #
#27
b101010101010101010101010xxxxxxxxxxxxxxxxxxxxxxxxxxxxxxxxxxxxxxxxxxxxxxxxx #
#28
b1010101010101010101010101xxxxxxxxxxxxxxxxxxxxxxxxxxxxxxxxxxxxxxxxxxxxxxxx #
#29
b10101010101010101010101010xxxxxxxxxxxxxxxxxxxxxxxxxxxxxxxxxxxxxxxxxxxxxxx #
#30
b101010101010101010101010101xxxxxxxxxxxxxxxxxxxxxxxxxxxxxxxxxxxxxxxxxxxxxx #
#31
b1010101010101010101010101010xxxxxxxxxxxxxxxxxxxxxxxxxxxxxxxxxxxxxxxxxxxxx #
#32
b10101010101010101010101010101xxxxxxxxxxxxxxxxxxxxxxxxxxxxxxxxxxxxxxxxxxxx #
#33
b101010101010101010101010101010xxxxxxxxxxxxxxxxxxxxxxxxxxxxxxxxxxxxxxxxxxx #
#34
b1010101010101010101010101010101xxxxxxxxxxxxxxxxxxxxxxxxxxxxxxxxxxxxxxxxxx #
#35
b10101010101010101010101010101010xxxxxxxxxxxxxxxxxxxxxxxxxxxxxxxxxxxxxxxxx #
#36
b101010101010101010101010101010101xxxxxxxxxxxxxxxxxxxxxxxxxxxxxxxxxxxxxxxx #
#37
b1010101010101010101010101010101010xxxxxxxxxxxxxxxxxxxxxxxxxxxxxxxxxxxxxxx #
#38
b10101010101010101010101010101010101xxxxxxxxxxxxxxxxxxxxxxxxxxxxxxxxxxxxxx #
#39
b101010101010101010101010101010101010xxxxxxxxxxxxxxxxxxxxxxxxxxxxxxxxxxxxx #
#40
b1010101010101010101010101010101010101xxxxxxxxxxxxxxxxxxxxxxxxxxxxxxxxxxxx #
#41
b10101010101010101010101010101010101010xxxxxxxxxxxxxxxxxxxxxxxxxxxxxxxxxxx #
#42
b101010101010101010101010101010101010101xxxxxxxxxxxxxxxxxxxxxxxxxxxxxxxxxx #
#43
b1010101010101010101010101010101010101010xxxxxxxxxxxxxxxxxxxxxxxxxxxxxxxxx #
#44
b10101010101010101010101010101010101010101xxxxxxxxxxxxxxxxxxxxxxxxxxxxxxxx #
#45
b101010101010101010101010101010101010101010xxxxxxxxxxxxxxxxxxxxxxxxxxxxxxx #
#46
b1010101010101010101010101010101010101010101xxxxxxxxxxxxxxxxxxxxxxxxxxxxxx #
#47
b10101010101010101010101010101010101010101010xxxxxxxxxxxxxxxxxxxxxxxxxxxxx #
#48
b101010101010101010101010101010101010101010101xxxxxxxxxxxxxxxxxxxxxxxxxxxx #
#49
b1010101010101010101010101010101010101010101010xxxxxxxxxxxxxxxxxxxxxxxxxxx #
#50
b10101010101010101010101010101010101010101010101xxxxxxxxxxxxxxxxxxxxxxxxxx #
#51
b101010101010101010101010101010101010101010101010xxxxxxxxxxxxxxxxxxxxxxxxx #
#52
b1010101010101010101010101010101010101010101010101xxxxxxxxxxxxxxxxxxxxxxxx #
#53
b10101010101010101010101010101010101010101010101010xxxxxxxxxxxxxxxxxxxxxxx #
#54
b101010101010101010101010101010101010101010101010101xxxxxxxxxxxxxxxxxxxxxx #
#55
b1010101010101010101010101010101010101010101010101010xxxxxxxxxxxxxxxxxxxxx #
#56
b10101010101010101010101010101010101010101010101010101xxxxxxxxxxxxxxxxxxxx #
#57
b101010101010101010101010101010101010101010101010101010xxxxxxxxxxxxxxxxxxx #
#58
b1010101010101010101010101010101010101010101010101010101xxxxxxxxxxxxxxxxxx #
#59
b10101010101010101010101010101010101010101010101010101010xxxxxxxxxxxxxxxxx #
#60
b101010101010101010101010101010101010101010101010101010101xxxxxxxxxxxxxxxx #
#61
b1010101010101010101010101010101010101010101010101010101010xxxxxxxxxxxxxxx #
#62
b10101010101010101010101010101010101010101010101010101010101xxxxxxxxxxxxxx #
#63
b101010101010101010101010101010101010101010101010101010101010xxxxxxxxxxxxx #
#64
b1010101010101010101010101010101010101010101010101010101010101xxxxxxxxxxxx #
#65
b10101010101010101010101010101010101010101010101010101010101010xxxxxxxxxxx #
#66
b101010101010101010101010101010101010101010101010101010101010101xxxxxxxxxx #
#67
b1010101010101010101010101010101010101010101010101010101010101010xxxxxxxxx #
#68
b10101010101010101010101010101010101010101010101010101010101010101xxxxxxxx #
#69
b101010101010101010101010101010101010101010101010101010101010101010xxxxxxx #
#70
b1010101010101010101010101010101010101010101010101010101010101010101xxxxxx #
#71
b10101010101010101010101010101010101010101010101010101010101010101010xxxxx #
#72
b101010101010101010101010101010101010101010101010101010101010101010101xxxx #
#73
b1010101010101010101010101010101010101010101010101010101010101010101010xxx #
#74
b10101010101010101010101010101010101010101010101010101010101010101010101xx #
#75
b101010101010101010101010101010101010101010101010101010101010101010101010x #
#76
1!
b1010101010101010101010101010101010101010101010101010101010101010101010101 #
1"
#79
b11010101010101010101010101010101010101010101010101010101010101010101010101 #
#80
b10010101010101010101010101010101010101010101010101010101010101010101010101 #
#81
b10110101010101010101010101010101010101010101010101010101010101010101010101 #
#82
b10100101010101010101010101010101010101010101010101010101010101010101010101 #
#83
b10101101010101010101010101010101010101010101010101010101010101010101010101 #
#84
b10101001010101010101010101010101010101010101010101010101010101010101010101 #
#85
b10101011010101010101010101010101010101010101010101010101010101010101010101 #
#86
b10101010010101010101010101010101010101010101010101010101010101010101010101 #
#87
b10101010110101010101010101010101010101010101010101010101010101010101010101 #
#88
b10101010100101010101010101010101010101010101010101010101010101010101010101 #
#89
b10101010101101010101010101010101010101010101010101010101010101010101010101 #
#90
b10101010101001010101010101010101010101010101010101010101010101010101010101 #
#91
b10101010101011010101010101010101010101010101010101010101010101010101010101 #
#92
b10101010101010010101010101010101010101010101010101010101010101010101010101 #
#93
b10101010101010110101010101010101010101010101010101010101010101010101010101 #
#94
b10101010101010100101010101010101010101010101010101010101010101010101010101 #
#95
b10101010101010101101010101010101010101010101010101010101010101010101010101 #
#96
b10101010101010101001010101010101010101010101010101010101010101010101010101 #
#97
b10101010101010101011010101010101010101010101010101010101010101010101010101 #
#98
b10101010101010101010010101010101010101010101010101010101010101010101010101 #
#99
b10101010101010101010110101010101010101010101010101010101010101010101010101 #
#100
b10101010101010101010100101010101010101010101010101010101010101010101010101 #
#101
b10101010101010101010101101010101010101010101010101010101010101010101010101 #
#102
b10101010101010101010101001010101010101010101010101010101010101010101010101 #
#103
b10101010101010101010101011010101010101010101010101010101010101010101010101 #
#104
b10101010101010101010101010010101010101010101010101010101010101010101010101 #
#105
b10101010101010101010101010110101010101010101010101010101010101010101010101 #
#106
b10101010101010101010101010100101010101010101010101010101010101010101010101 #
#107
b10101010101010101010101010101101010101010101010101010101010101010101010101 #
#108
b10101010101010101010101010101001010101010101010101010101010101010101010101 #
#109
b10101010101010101010101010101011010101010101010101010101010101010101010101 #
#110
b10101010101010101010101010101010010101010101010101010101010101010101010101 #
#111
b10101010101010101010101010101010110101010101010101010101010101010101010101 #
#112
b10101010101010101010101010101010100101010101010101010101010101010101010101 #
#113
b10101010101010101010101010101010101101010101010101010101010101010101010101 #
#114
b10101010101010101010101010101010101001010101010101010101010101010101010101 #
#115
b10101010101010101010101010101010101011010101010101010101010101010101010101 #
#116
b10101010101010101010101010101010101010010101010101010101010101010101010101 #
#117
b10101010101010101010101010101010101010110101010101010101010101010101010101 #
#118
b10101010101010101010101010101010101010100101010101010101010101010101010101 #
#119
b10101010101010101010101010101010101010101101010101010101010101010101010101 #
#120
b10101010101010101010101010101010101010101001010101010101010101010101010101 #
#121
b10101010101010101010101010101010101010101011010101010101010101010101010101 #
#122
b10101010101010101010101010101010101010101010010101010101010101010101010101 #
#123
b10101010101010101010101010101010101010101010110101010101010101010101010101 #
#124
b10101010101010101010101010101010101010101010100101010101010101010101010101 #
#125
b10101010101010101010101010101010101010101010101101010101010101010101010101 #
#126
b10101010101010101010101010101010101010101010101001010101010101010101010101 #
#127
b10101010101010101010101010101010101010101010101011010101010101010101010101 #
#128
b10101010101010101010101010101010101010101010101010010101010101010101010101 #
#129
b10101010101010101010101010101010101010101010101010110101010101010101010101 #
#130
b10101010101010101010101010101010101010101010101010100101010101010101010101 #
#131
b10101010101010101010101010101010101010101010101010101101010101010101010101 #
#132
b10101010101010101010101010101010101010101010101010101001010101010101010101 #
#133
b10101010101010101010101010101010101010101010101010101011010101010101010101 #
#134
b10101010101010101010101010101010101010101010101010101010010101010101010101 #
#135
b10101010101010101010101010101010101010101010101010101010110101010101010101 #
#136
b10101010101010101010101010101010101010101010101010101010100101010101010101 #
#137
b10101010101010101010101010101010101010101010101010101010101101010101010101 #
#138
b10101010101010101010101010101010101010101010101010101010101001010101010101 #
#139
b10101010101010101010101010101010101010101010101010101010101011010101010101 #
#140
b10101010101010101010101010101010101010101010101010101010101010010101010101 #
#141
b10101010101010101010101010101010101010101010101010101010101010110101010101 #
#142
b10101010101010101010101010101010101010101010101010101010101010100101010101 #
#143
b10101010101010101010101010101010101010101010101010101010101010101101010101 #
#144
b10101010101010101010101010101010101010101010101010101010101010101001010101 #
#145
b10101010101010101010101010101010101010101010101010101010101010101011010101 #
#146
b10101010101010101010101010101010101010101010101010101010101010101010010101 #
#147
b10101010101010101010101010101010101010101010101010101010101010101010110101 #
#148
b10101010101010101010101010101010101010101010101010101010101010101010100101 #
#149
b10101010101010101010101010101010101010101010101010101010101010101010101101 #
#150
b10101010101010101010101010101010101010101010101010101010101010101010101001 #
#151
b10101010101010101010101010101010101010101010101010101010101010101010101011 #
#152
0!
b10101010101010101010101010101010101010101010101010101010101010101010101010 #
#155
b101010101010101010101010101010101010101010101010101010101010101010101010 #
#156
b1101010101010101010101010101010101010101010101010101010101010101010101010 #
#157
b1001010101010101010101010101010101010101010101010101010101010101010101010 #
#158
b1011010101010101010101010101010101010101010101010101010101010101010101010 #
#159
b1010010101010101010101010101010101010101010101010101010101010101010101010 #
#160
b1010110101010101010101010101010101010101010101010101010101010101010101010 #
#161
b1010100101010101010101010101010101010101010101010101010101010101010101010 #
#162
b1010101101010101010101010101010101010101010101010101010101010101010101010 #
#163
b1010101001010101010101010101010101010101010101010101010101010101010101010 #
#164
b1010101011010101010101010101010101010101010101010101010101010101010101010 #
#165
b1010101010010101010101010101010101010101010101010101010101010101010101010 #
#166
b1010101010110101010101010101010101010101010101010101010101010101010101010 #
#167
b1010101010100101010101010101010101010101010101010101010101010101010101010 #
#168
b1010101010101101010101010101010101010101010101010101010101010101010101010 #
#169
b1010101010101001010101010101010101010101010101010101010101010101010101010 #
#170
b1010101010101011010101010101010101010101010101010101010101010101010101010 #
#171
b1010101010101010010101010101010101010101010101010101010101010101010101010 #
#172
b1010101010101010110101010101010101010101010101010101010101010101010101010 #
#173
b1010101010101010100101010101010101010101010101010101010101010101010101010 #
#174
b1010101010101010101101010101010101010101010101010101010101010101010101010 #
#175
b1010101010101010101001010101010101010101010101010101010101010101010101010 #
#176
b1010101010101010101011010101010101010101010101010101010101010101010101010 #
#177
b1010101010101010101010010101010101010101010101010101010101010101010101010 #
#178
b1010101010101010101010110101010101010101010101010101010101010101010101010 #
#179
b1010101010101010101010100101010101010101010101010101010101010101010101010 #
#180
b1010101010101010101010101101010101010101010101010101010101010101010101010 #
#181
b1010101010101010101010101001010101010101010101010101010101010101010101010 #
#182
b1010101010101010101010101011010101010101010101010101010101010101010101010 #
#183
b1010101010101010101010101010010101010101010101010101010101010101010101010 #
#184
b1010101010101010101010101010110101010101010101010101010101010101010101010 #
#185
b1010101010101010101010101010100101010101010101010101010101010101010101010 #
#186
b1010101010101010101010101010101101010101010101010101010101010101010101010 #
#187
b1010101010101010101010101010101001010101010101010101010101010101010101010 #
#188
b1010101010101010101010101010101011010101010101010101010101010101010101010 #
#189
b1010101010101010101010101010101010010101010101010101010101010101010101010 #
#190
b1010101010101010101010101010101010110101010101010101010101010101010101010 #
#191
b1010101010101010101010101010101010100101010101010101010101010101010101010 #
#192
b1010101010101010101010101010101010101101010101010101010101010101010101010 #
#193
b1010101010101010101010101010101010101001010101010101010101010101010101010 #
#194
b1010101010101010101010101010101010101011010101010101010101010101010101010 #
#195
b1010101010101010101010101010101010101010010101010101010101010101010101010 #
#196
b1010101010101010101010101010101010101010110101010101010101010101010101010 #
#197
b1010101010101010101010101010101010101010100101010101010101010101010101010 #
#198
b1010101010101010101010101010101010101010101101010101010101010101010101010 #
#199
b1010101010101010101010101010101010101010101001010101010101010101010101010 #
#200
b1010101010101010101010101010101010101010101011010101010101010101010101010 #
#201
b1010101010101010101010101010101010101010101010010101010101010101010101010 #
#202
b1010101010101010101010101010101010101010101010110101010101010101010101010 #
#203
b1010101010101010101010101010101010101010101010100101010101010101010101010 #
#204
b1010101010101010101010101010101010101010101010101101010101010101010101010 #
#205
b1010101010101010101010101010101010101010101010101001010101010101010101010 #
#206
b1010101010101010101010101010101010101010101010101011010101010101010101010 #
#207
b1010101010101010101010101010101010101010101010101010010101010101010101010 #
#208
b1010101010101010101010101010101010101010101010101010110101010101010101010 #
#209
b1010101010101010101010101010101010101010101010101010100101010101010101010 #
#210
b1010101010101010101010101010101010101010101010101010101101010101010101010 #
#211
b1010101010101010101010101010101010101010101010101010101001010101010101010 #
#212
b1010101010101010101010101010101010101010101010101010101011010101010101010 #
#213
b1010101010101010101010101010101010101010101010101010101010010101010101010 #
#214
b1010101010101010101010101010101010101010101010101010101010110101010101010 #
#215
b1010101010101010101010101010101010101010101010101010101010100101010101010 #
#216
b1010101010101010101010101010101010101010101010101010101010101101010101010 #
#217
b1010101010101010101010101010101010101010101010101010101010101001010101010 #
#218
b1010101010101010101010101010101010101010101010101010101010101011010101010 #
#219
b1010101010101010101010101010101010101010101010101010101010101010010101010 #
#220
b1010101010101010101010101010101010101010101010101010101010101010110101010 #
#221
b1010101010101010101010101010101010101010101010101010101010101010100101010 #
#222
b1010101010101010101010101010101010101010101010101010101010101010101101010 #
#223
b1010101010101010101010101010101010101010101010101010101010101010101001010 #
#224
b1010101010101010101010101010101010101010101010101010101010101010101011010 #
#225
b1010101010101010101010101010101010101010101010101010101010101010101010010 #
#226
b1010101010101010101010101010101010101010101010101010101010101010101010110 #
#227
b1010101010101010101010101010101010101010101010101010101010101010101010100 #
#228
1!
b1010101010101010101010101010101010101010101010101010101010101010101010101 #
#231
b11010101010101010101010101010101010101010101010101010101010101010101010101 #
#232
b10010101010101010101010101010101010101010101010101010101010101010101010101 #
#233
b10110101010101010101010101010101010101010101010101010101010101010101010101 #
#234
b10100101010101010101010101010101010101010101010101010101010101010101010101 #
#235
b10101101010101010101010101010101010101010101010101010101010101010101010101 #
#236
b10101001010101010101010101010101010101010101010101010101010101010101010101 #
#237
b10101011010101010101010101010101010101010101010101010101010101010101010101 #
#238
b10101010010101010101010101010101010101010101010101010101010101010101010101 #
#239
b10101010110101010101010101010101010101010101010101010101010101010101010101 #
#240
b10101010100101010101010101010101010101010101010101010101010101010101010101 #
#241
b10101010101101010101010101010101010101010101010101010101010101010101010101 #
#242
b10101010101001010101010101010101010101010101010101010101010101010101010101 #
#243
b10101010101011010101010101010101010101010101010101010101010101010101010101 #
#244
b10101010101010010101010101010101010101010101010101010101010101010101010101 #
#245
b10101010101010110101010101010101010101010101010101010101010101010101010101 #
#246
b10101010101010100101010101010101010101010101010101010101010101010101010101 #
#247
b10101010101010101101010101010101010101010101010101010101010101010101010101 #
#248
b10101010101010101001010101010101010101010101010101010101010101010101010101 #
#249
b10101010101010101011010101010101010101010101010101010101010101010101010101 #
#250
b10101010101010101010010101010101010101010101010101010101010101010101010101 #
#251
b10101010101010101010110101010101010101010101010101010101010101010101010101 #
#252
b10101010101010101010100101010101010101010101010101010101010101010101010101 #
#253
b10101010101010101010101101010101010101010101010101010101010101010101010101 #
#254
b10101010101010101010101001010101010101010101010101010101010101010101010101 #
#255
b10101010101010101010101011010101010101010101010101010101010101010101010101 #
#256
b10101010101010101010101010010101010101010101010101010101010101010101010101 #
#257
b10101010101010101010101010110101010101010101010101010101010101010101010101 #
#258
b10101010101010101010101010100101010101010101010101010101010101010101010101 #
#259
b10101010101010101010101010101101010101010101010101010101010101010101010101 #
#260
b10101010101010101010101010101001010101010101010101010101010101010101010101 #
#261
b10101010101010101010101010101011010101010101010101010101010101010101010101 #
#262
b10101010101010101010101010101010010101010101010101010101010101010101010101 #
#263
b10101010101010101010101010101010110101010101010101010101010101010101010101 #
#264
b10101010101010101010101010101010100101010101010101010101010101010101010101 #
#265
b10101010101010101010101010101010101101010101010101010101010101010101010101 #
#266
b10101010101010101010101010101010101001010101010101010101010101010101010101 #
#267
b10101010101010101010101010101010101011010101010101010101010101010101010101 #
#268
b10101010101010101010101010101010101010010101010101010101010101010101010101 #
#269
b10101010101010101010101010101010101010110101010101010101010101010101010101 #
#270
b10101010101010101010101010101010101010100101010101010101010101010101010101 #
#271
b10101010101010101010101010101010101010101101010101010101010101010101010101 #
#272
b10101010101010101010101010101010101010101001010101010101010101010101010101 #
#273
b10101010101010101010101010101010101010101011010101010101010101010101010101 #
#274
b10101010101010101010101010101010101010101010010101010101010101010101010101 #
#275
b10101010101010101010101010101010101010101010110101010101010101010101010101 #
#276
b10101010101010101010101010101010101010101010100101010101010101010101010101 #
#277
b10101010101010101010101010101010101010101010101101010101010101010101010101 #
#278
b10101010101010101010101010101010101010101010101001010101010101010101010101 #
#279
b10101010101010101010101010101010101010101010101011010101010101010101010101 #
#280
b10101010101010101010101010101010101010101010101010010101010101010101010101 #
#281
b10101010101010101010101010101010101010101010101010110101010101010101010101 #
#282
b10101010101010101010101010101010101010101010101010100101010101010101010101 #
#283
b10101010101010101010101010101010101010101010101010101101010101010101010101 #
#284
b10101010101010101010101010101010101010101010101010101001010101010101010101 #
#285
b10101010101010101010101010101010101010101010101010101011010101010101010101 #
#286
b10101010101010101010101010101010101010101010101010101010010101010101010101 #
#287
b10101010101010101010101010101010101010101010101010101010110101010101010101 #
#288
b10101010101010101010101010101010101010101010101010101010100101010101010101 #
#289
b10101010101010101010101010101010101010101010101010101010101101010101010101 #
#290
b10101010101010101010101010101010101010101010101010101010101001010101010101 #
#291
b10101010101010101010101010101010101010101010101010101010101011010101010101 #
#292
b10101010101010101010101010101010101010101010101010101010101010010101010101 #
#293
b10101010101010101010101010101010101010101010101010101010101010110101010101 #
#294
b10101010101010101010101010101010101010101010101010101010101010100101010101 #
#295
b10101010101010101010101010101010101010101010101010101010101010101101010101 #
#296
b10101010101010101010101010101010101010101010101010101010101010101001010101 #
#297
b10101010101010101010101010101010101010101010101010101010101010101011010101 #
#298
b10101010101010101010101010101010101010101010101010101010101010101010010101 #
#299
b10101010101010101010101010101010101010101010101010101010101010101010110101 #
#300
b10101010101010101010101010101010101010101010101010101010101010101010100101 #
#301
b10101010101010101010101010101010101010101010101010101010101010101010101101 #
#302
b10101010101010101010101010101010101010101010101010101010101010101010101001 #
#303
b10101010101010101010101010101010101010101010101010101010101010101010101011 #
#304
0!
b10101010101010101010101010101010101010101010101010101010101010101010101010 #
#307
b101010101010101010101010101010101010101010101010101010101010101010101010 #
#308
b1101010101010101010101010101010101010101010101010101010101010101010101010 #
#309
b1001010101010101010101010101010101010101010101010101010101010101010101010 #
#310
b1011010101010101010101010101010101010101010101010101010101010101010101010 #
#311
b1010010101010101010101010101010101010101010101010101010101010101010101010 #
#312
b1010110101010101010101010101010101010101010101010101010101010101010101010 #
#313
b1010100101010101010101010101010101010101010101010101010101010101010101010 #
#314
b1010101101010101010101010101010101010101010101010101010101010101010101010 #
#315
b1010101001010101010101010101010101010101010101010101010101010101010101010 #
#316
b1010101011010101010101010101010101010101010101010101010101010101010101010 #
#317
b1010101010010101010101010101010101010101010101010101010101010101010101010 #
#318
b1010101010110101010101010101010101010101010101010101010101010101010101010 #
#319
b1010101010100101010101010101010101010101010101010101010101010101010101010 #
#320
b1010101010101101010101010101010101010101010101010101010101010101010101010 #
#321
b1010101010101001010101010101010101010101010101010101010101010101010101010 #
#322
b1010101010101011010101010101010101010101010101010101010101010101010101010 #
#323
b1010101010101010010101010101010101010101010101010101010101010101010101010 #
#324
b1010101010101010110101010101010101010101010101010101010101010101010101010 #
#325
b1010101010101010100101010101010101010101010101010101010101010101010101010 #
#326
b1010101010101010101101010101010101010101010101010101010101010101010101010 #
#327
b1010101010101010101001010101010101010101010101010101010101010101010101010 #
#328
b1010101010101010101011010101010101010101010101010101010101010101010101010 #
#329
b1010101010101010101010010101010101010101010101010101010101010101010101010 #
#330
b1010101010101010101010110101010101010101010101010101010101010101010101010 #
#331
b1010101010101010101010100101010101010101010101010101010101010101010101010 #
#332
b1010101010101010101010101101010101010101010101010101010101010101010101010 #
#333
b1010101010101010101010101001010101010101010101010101010101010101010101010 #
#334
b1010101010101010101010101011010101010101010101010101010101010101010101010 #
#335
b1010101010101010101010101010010101010101010101010101010101010101010101010 #
#336
b1010101010101010101010101010110101010101010101010101010101010101010101010 #
#337
b1010101010101010101010101010100101010101010101010101010101010101010101010 #
#338
b1010101010101010101010101010101101010101010101010101010101010101010101010 #
#339
b1010101010101010101010101010101001010101010101010101010101010101010101010 #
#340
b1010101010101010101010101010101011010101010101010101010101010101010101010 #
#341
b1010101010101010101010101010101010010101010101010101010101010101010101010 #
#342
b1010101010101010101010101010101010110101010101010101010101010101010101010 #
#343
b1010101010101010101010101010101010100101010101010101010101010101010101010 #
#344
b1010101010101010101010101010101010101101010101010101010101010101010101010 #
#345
b1010101010101010101010101010101010101001010101010101010101010101010101010 #
#346
b1010101010101010101010101010101010101011010101010101010101010101010101010 #
#347
b1010101010101010101010101010101010101010010101010101010101010101010101010 #
#348
b1010101010101010101010101010101010101010110101010101010101010101010101010 #
#349
b1010101010101010101010101010101010101010100101010101010101010101010101010 #
#350
b1010101010101010101010101010101010101010101101010101010101010101010101010 #
#351
b1010101010101010101010101010101010101010101001010101010101010101010101010 #
#352
b1010101010101010101010101010101010101010101011010101010101010101010101010 #
#353
b1010101010101010101010101010101010101010101010010101010101010101010101010 #
#354
b1010101010101010101010101010101010101010101010110101010101010101010101010 #
#355
b1010101010101010101010101010101010101010101010100101010101010101010101010 #
#356
b1010101010101010101010101010101010101010101010101101010101010101010101010 #
