mux_2_1_1b/mux_2_1_1b.v
// Critical path delay = 7ns
// 0 -> copy a
// 1 -> copy b
module mux_2_1_1b(a, b, sel, res);
   input a;
   input b;
   input sel;
   output res;
   wire   not_sel;
   not #(1) not0(not_sel, sel);
   wire   a_out;
   and #(3) and0(a_out, a, not_sel);
   wire   b_out;
   and #(3) and1(b_out, b, sel);
   or #(3) and2(res, a_out, b_out);
endmodule // mux1

mux_4_1_1b/mux_4_1_1b.v
// Critical path delay = 14ns
module mux_4_1_1b(a, b, c, d, sel1, sel0, res);
   input a;
   input b;
   input c;
   input d;
   input sel1;
   input sel0;
   output res;
   wire   ab_out;
   mux_2_1_1b mux_2_1_1b_0(.a(a), .b(b), .sel(sel0), .res(ab_out));
   wire   cd_out;
   mux_2_1_1b mux_2_1_1b_1(.a(c), .b(d), .sel(sel0), .res(cd_out));
   mux_2_1_1b mux_2_1_1b_2(.a(ab_out), .b(cd_out), .sel(sel1), .res(res));
endmodule // mux_4_1_1b

mux_8_1_1b/mux_8_1_1b.v
// Critical path delay = 21 ns
module mux_8_1_1b(a, b, c, d, e, f, g, h, sel2, sel1, sel0, res);
   input a;
   input b;
   input c;
   input d;
   input e;
   input f;
   input g;
   input h;
   input sel2;
   input sel1;
   input sel0;
   output res;

   wire   x;
   mux_4_1_1b mux_4_1_1b_0(.a(a), .b(b), .c(c), .d(d),
                           .sel1(sel1), .sel0(sel0), .res(x));
   wire   y;
   mux_4_1_1b mux_4_1_1b_1(.a(e), .b(f), .c(g), .d(h),
                           .sel1(sel1), .sel0(sel0), .res(y));
   mux_2_1_1b mux_2_1_1b_0(.a(x), .b(y), .sel(sel2), .res(res));
endmodule;

mux_8_1_1b/testbench.v
`timescale 1 ns/1 ns	//time scale for simulation

module testbench;
   reg a;
   reg b;
   reg c;
   reg d;
   reg e;
   reg f;
   reg g;
   reg h;
   reg sel2;
   reg sel1;
   reg sel0;
   wire res;

   mux_8_1_1b my_mux_8_1_1b(.a(a), .b(b), .c(c), .d(d),
                            .e(e), .f(f), .g(g), .h(h),
                            .sel2(sel2), .sel1(sel1), .sel0(sel0),
                            .res(res));

   initial begin
      $dumpfile("test.vcd");
      $dumpvars(0, testbench);

      // test 0, expected result = 1
      a = 1; b = 0; c = 0; d = 0;
      e = 0; f = 0; g = 0; h = 0;
      sel2 = 0;
      sel1 = 0;
      sel0 = 0;
      #21;

      // test 1, expected result = 0
      a = 1; b = 0; c = 1; d = 1;
      e = 1; f = 1; g = 1; h = 1;
      sel2 = 0;
      sel1 = 0;
      sel0 = 1;
      #21;

      // test 2, expected result = 1
      a = 0; b = 0; c = 1; d = 0;
      e = 0; f = 0; g = 0; h = 0;
      sel2 = 0;
      sel1 = 1;
      sel0 = 0;
      #21;

      // test 3, expected result = 0
      a = 1; b = 1; c = 1; d = 0;
      e = 1; f = 1; g = 1; h = 1;
      sel2 = 0;
      sel1 = 1;
      sel0 = 1;
      #21;

      // test 4, expected result = 0
      a = 1; b = 1; c = 1; d = 1;
      e = 0; f = 1; g = 1; h = 1;
      sel2 = 1;
      sel1 = 0;
      sel0 = 0;
      #21;

      // test 5, expected result = 1
      a = 0; b = 0; c = 0; d = 0;
      e = 0; f = 1; g = 0; h = 0;
      sel2 = 1;
      sel1 = 0;
      sel0 = 1;
      #21;

      // test 6, expected result = 0
      a = 1; b = 1; c = 1; d = 1;
      e = 1; f = 1; g = 0; h = 1;
      sel2 = 1;
      sel1 = 1;
      sel0 = 0;
      #21;

      // test 7, expected result = 1
      a = 0; b = 0; c = 0; d = 0;
      e = 0; f = 0; g = 0; h = 1;
      sel2 = 1;
      sel1 = 1;
      sel0 = 1;
      #21;
   end
endmodule

mux_8_1_1b/test.vcd
$date
	Sun Jul 10 17:11:19 2022
$end
$version
	Icarus Verilog
$end
$timescale
	1ns
$end
$scope module testbench $end
$var wire 1 ! res $end
$var reg 1 " a $end
$var reg 1 # b $end
$var reg 1 $ c $end
$var reg 1 % d $end
$var reg 1 & e $end
$var reg 1 ' f $end
$var reg 1 ( g $end
$var reg 1 ) h $end
$var reg 1 * sel0 $end
$var reg 1 + sel1 $end
$var reg 1 , sel2 $end
$scope module my_mux_8_1_1b $end
$var wire 1 " a $end
$var wire 1 # b $end
$var wire 1 $ c $end
$var wire 1 % d $end
$var wire 1 & e $end
$var wire 1 ' f $end
$var wire 1 ( g $end
$var wire 1 ) h $end
$var wire 1 * sel0 $end
$var wire 1 + sel1 $end
$var wire 1 , sel2 $end
$var wire 1 - y $end
$var wire 1 . x $end
$var wire 1 ! res $end
$scope module mux_2_1_1b_0 $end
$var wire 1 / a_out $end
$var wire 1 0 b_out $end
$var wire 1 1 not_sel $end
$var wire 1 ! res $end
$var wire 1 , sel $end
$var wire 1 - b $end
$var wire 1 . a $end
$upscope $end
$scope module mux_4_1_1b_0 $end
$var wire 1 " a $end
$var wire 1 # b $end
$var wire 1 $ c $end
$var wire 1 % d $end
$var wire 1 * sel0 $end
$var wire 1 + sel1 $end
$var wire 1 . res $end
$var wire 1 2 cd_out $end
$var wire 1 3 ab_out $end
$scope module mux_2_1_1b_0 $end
$var wire 1 " a $end
$var wire 1 4 a_out $end
$var wire 1 # b $end
$var wire 1 5 b_out $end
$var wire 1 6 not_sel $end
$var wire 1 3 res $end
$var wire 1 * sel $end
$upscope $end
$scope module mux_2_1_1b_1 $end
$var wire 1 $ a $end
$var wire 1 7 a_out $end
$var wire 1 % b $end
$var wire 1 8 b_out $end
$var wire 1 9 not_sel $end
$var wire 1 2 res $end
$var wire 1 * sel $end
$upscope $end
$scope module mux_2_1_1b_2 $end
$var wire 1 3 a $end
$var wire 1 : a_out $end
$var wire 1 2 b $end
$var wire 1 ; b_out $end
$var wire 1 < not_sel $end
$var wire 1 . res $end
$var wire 1 + sel $end
$upscope $end
$upscope $end
$scope module mux_4_1_1b_1 $end
$var wire 1 & a $end
$var wire 1 ' b $end
$var wire 1 ( c $end
$var wire 1 ) d $end
$var wire 1 * sel0 $end
$var wire 1 + sel1 $end
$var wire 1 - res $end
$var wire 1 = cd_out $end
$var wire 1 > ab_out $end
$scope module mux_2_1_1b_0 $end
$var wire 1 & a $end
$var wire 1 ? a_out $end
$var wire 1 ' b $end
$var wire 1 @ b_out $end
$var wire 1 A not_sel $end
$var wire 1 > res $end
$var wire 1 * sel $end
$upscope $end
$scope module mux_2_1_1b_1 $end
$var wire 1 ( a $end
$var wire 1 B a_out $end
$var wire 1 ) b $end
$var wire 1 C b_out $end
$var wire 1 D not_sel $end
$var wire 1 = res $end
$var wire 1 * sel $end
$upscope $end
$scope module mux_2_1_1b_2 $end
$var wire 1 > a $end
$var wire 1 E a_out $end
$var wire 1 = b $end
$var wire 1 F b_out $end
$var wire 1 G not_sel $end
$var wire 1 - res $end
$var wire 1 + sel $end
$upscope $end
$upscope $end
$upscope $end
$upscope $end
$enddefinitions $end
#0
$dumpvars
xG
xF
xE
xD
xC
xB
xA
x@
x?
x>
x=
x<
x;
x:
x9
x8
x7
x6
x5
x4
x3
x2
x1
x0
x/
x.
x-
0,
0+
0*
0)
0(
0'
0&
0%
0$
0#
1"
x!
$end
#1
16
19
1A
1D
1<
1G
11
#3
0F
0C
0B
0@
0?
0;
08
07
05
00
#4
14
#6
0=
0>
02
#7
13
#9
0E
#10
1:
#12
0-
#13
1.
#16
1/
#19
1!
#21
1*
1)
1(
1'
1&
1%
1$
#22
06
09
0A
0D
#24
1C
1@
18
#25
04
#27
1=
1>
12
#28
03
#30
1E
#31
0:
#33
1-
#34
0.
#37
0/
#40
0!
#42
0*
1+
0)
0(
0'
0&
0%
0"
#43
16
19
1A
1D
0<
0G
#45
1;
1F
0C
0@
08
#46
17
0E
#48
1.
0=
0>
#51
1/
0F
#54
1!
0-
#63
1*
1)
1(
1'
1&
1#
1"
#64
06
09
0A
0D
#66
1C
1@
15
#67
07
#69
1=
1>
13
#70
02
#72
1F
#73
0;
#75
1-
#76
0.
#79
0/
#82
0!
#84
0*
0+
1,
0&
1%
#85
16
19
1A
1D
1<
1G
01
#87
05
0@
0C
0F
10
#88
14
17
1B
1:
1E
#90
0>
1!
#91
12
1.
#93
0E
#96
0-
#99
00
#102
0!
#105
1*
0)
0(
0%
0$
0#
0"
#106
06
09
0A
0D
#108
1@
0B
07
04
#111
1>
0=
02
03
#114
1E
0:
#117
1-
0.
#120
10
#123
1!
#126
0*
1+
1)
1&
1%
1$
1#
1"
#127
16
19
1A
1D
0<
0G
#129
0@
#130
14
17
1?
0E
#133
13
12
0-
#136
1;
00
#139
1.
0!
#147
1*
0'
0&
0%
0$
0#
0"
#148
06
09
0A
0D
#150
1C
0?
07
04
#153
1=
0>
02
03
#156
1F
0;
#159
1-
0.
#162
10
#165
1!
