sr_latch/sr_latch.v
// Critical path delay = 6ns
module sr_latch(r, s, q, qb);
   input r;
   input s;
   output q;
   output qb;
   nor #(2) nor0(q, r, qb);
   nor #(2) nor1(qb, q, s);
endmodule; // d_latch

d_latch/d_latch.v
// Critical path delay = 6ns
module d_latch(d, g, q, qb);
   input d;
   input g;
   output q;
   output qb;
   wire   nd;
   not #(1) not0(nd, d);
   wire   r;
   and #(3) and0(r, nd, g);
   wire   s;
   and #(3) and1(s, d, g);
   sr_latch sr_latch_0(.r(r), .s(s), .q(q), .qb(qb));
endmodule; // d_latch

d_latch/testbench.v
`timescale 1 ns/1 ns	//time scale for simulation

module testbench;
   reg d;
   reg g;
   wire q;
   wire qb;

   d_latch d_latch_0(.d(d), .g(g), .q(q), .qb(qb));

   initial begin
      $dumpfile("test.vcd");
      $dumpvars(0, testbench);

      // UPDATE pattern = reset, hold, hold; set, hold, hold
      // Reset - q = 0, qb = 1
      d = 0;
      g = 1;
      #8;

      // Hold - q = 0, qb = 1
      d = 0;
      g = 0;
      #8;

      // Hold - q = 0, qb = 1
      d = 1;
      g = 0;
      #8;

      // Set - q = 1, qb = 0
      d = 1;
      g = 1;
      #8;

      // Hold - q = 1, qb = 0
      d = 0;
      g = 0;
      #8;

      // Hold - q = 1, qb = 0
      d = 1;
      g = 0;
      #8;
   end
endmodule

d_latch/test.vcd
$date
	Sat Jun  4 22:14:31 2022
$end
$version
	Icarus Verilog
$end
$timescale
	1ns
$end
$scope module testbench $end
$var wire 1 ! qb $end
$var wire 1 " q $end
$var reg 1 # d $end
$var reg 1 $ g $end
$scope module d_latch_0 $end
$var wire 1 # d $end
$var wire 1 $ g $end
$var wire 1 % nd $end
$var wire 1 & r $end
$var wire 1 ' s $end
$var wire 1 ! qb $end
$var wire 1 " q $end
$scope module sr_latch_0 $end
$var wire 1 " q $end
$var wire 1 ! qb $end
$var wire 1 & r $end
$var wire 1 ' s $end
$upscope $end
$upscope $end
$upscope $end
$enddefinitions $end
#0
$dumpvars
x'
x&
x%
1$
0#
x"
x!
$end
#1
1%
#3
0'
#4
1&
#6
0"
#8
1!
0$
#11
0&
#16
1#
#17
0%
#24
1$
#27
1'
#29
0!
#31
1"
#32
0$
0#
#33
1%
#35
0'
#40
1#
#41
0%
