decoder_24_1b/decoder_24_1b.v
module decoder_24_1b(w1, w0, d3, d2, d1, d0);
   input w1;
   input w0;
   output d3;
   output d2;
   output d1;
   output d0;
   
   wire nw0;
   not #(1) not0(nw0, w0);
   wire nw1;
   not #(1) not1(nw1, w1);

   and #(3) and0(d0, nw0, nw1);
   and #(3) and1(d1, w0, nw1);
   and #(3) and2(d2, w1, nw0);
   and #(3) and3(d3, w1, w0);
endmodule

decoder_24_1b/testbench.v
`timescale 1 ns/1 ns	//time scale for simulation

module testbench;
   reg w1;
   reg w0;
   
   wire d3;
   wire d2;
   wire d1;
   wire d0;

   decoder_24_1b decoder_24_1b_0(.w1(w1), .w0(w0), .d3(d3), .d2(d2), .d1(d1), .d0(d0));

   initial begin
      $dumpfile("test.vcd");
      $dumpvars(0, testbench);

      // test0, D = 3'b0001
      w1 = 0;
      w0 = 0;
      #4;

      // test1, D = 3'b0010
      w1 = 0;
      w0 = 1;
      #4;

      // test2, D = 3'b0100
      w1 = 1;
      w0 = 0;
      #4;

      // test3, D = 3'b1000
      w1 = 1;
      w0 = 1;
      #4;
   end
endmodule

decoder_24_1b/test.vcd
$date
	Sun Jun 12 20:32:53 2022
$end
$version
	Icarus Verilog
$end
$timescale
	1ns
$end
$scope module testbench $end
$var wire 1 ! d3 $end
$var wire 1 " d2 $end
$var wire 1 # d1 $end
$var wire 1 $ d0 $end
$var reg 1 % w0 $end
$var reg 1 & w1 $end
$scope module decoder_24_1b_0 $end
$var wire 1 $ d0 $end
$var wire 1 # d1 $end
$var wire 1 " d2 $end
$var wire 1 ! d3 $end
$var wire 1 ' nw0 $end
$var wire 1 ( nw1 $end
$var wire 1 % w0 $end
$var wire 1 & w1 $end
$upscope $end
$upscope $end
$enddefinitions $end
#0
$dumpvars
x(
x'
0&
0%
x$
x#
x"
x!
$end
#1
1'
1(
#3
0!
0"
0#
#4
1$
1%
#5
0'
#7
1#
#8
0$
0%
1&
#9
1'
0(
#11
0#
#12
1"
1%
#13
0'
#15
1!
#16
0"
