ins_dec/ins_dec.v
// Critical path delay = 4ns
module ins_dec(INS, sel_data, write_en, alu_op, SEL_A, SEL_B, SEL_W, IMM);
   input [8:0] INS;
   output      sel_data;
   output      write_en;
   output      alu_op;
   output [1:0] SEL_A;
   output [1:0] SEL_B;
   output [1:0] SEL_W;
   output [3:0] IMM;
   // sel_data = INS[7]
   buf #(1) buf_0(sel_data, INS[7]); // buf is wire delay
   // write_en = ~(INS[7]*INS[6])
   wire         w0;
   and #(3) and_0(w0, INS[7], INS[6]);
   not #(1) not_0(write_en, w0);
   // alu_op = INS[6]
   buf #(1) buf_1(alu_op, INS[6]);
   // SEL_A = INS[3:2]
   buf #(1) buf_2(SEL_A[1], INS[3]);
   buf #(1) buf_3(SEL_A[0], INS[2]);
   // SEL_B = INS[1:0]
   buf #(1) buf_4(SEL_B[1], INS[1]);
   buf #(1) buf_5(SEL_B[0], INS[0]);
   // SEL_W = INS[5:4]
   buf #(1) buf_6(SEL_W[1], INS[5]);
   buf #(1) buf_7(SEL_W[0], INS[4]);
   // IMM = INS[3:0]
   buf #(1) buf_8(IMM[3], INS[3]);
   buf #(1) buf_9(IMM[2], INS[2]);
   buf #(1) buf_10(IMM[1], INS[1]);
   buf #(1) buf_11(IMM[0], INS[0]);
endmodule

ins_dec/testbench.v
// note: testbench for instruction decoder
// note: actual instructions will be tested in ../datapath
`timescale 1 ns/1 ns	//time scale for simulation

module testbench;
   reg [8:0] INS;
   wire      sel_data;
   wire      write_en;
   wire      alu_op;
   wire [1:0] SEL_A;
   wire [1:0] SEL_B;
   wire [1:0] SEL_W;
   wire [3:0] IMM;

   ins_dec my_ins_dec(.INS(INS), .sel_data(sel_data), .write_en(write_en), .alu_op(alu_op), .SEL_A(SEL_A), .SEL_B(SEL_B), .SEL_W(SEL_W), .IMM(IMM));

   initial begin
      $dumpfile("test.vcd");
      $dumpvars(0, testbench);

      // test set 0: one hot
      // test 0.0
      // sel_data = INS[7] = 0
      // write_en = ~(INS[7]*INS[6]) = 1
      // alu_op = INS[6] = 0
      // SEL_A = INS[3:2] = 2'b00
      // SEL_B = INS[1:0] = 2'b01
      // SEL_W = INS[5:4] = 2'b00
      // IMM = INS[3:0] = 4'b0001
      INS = 9'b000000001;
      #4;

      // test 0.1
      // sel_data = INS[7] = 0
      // write_en = ~(INS[7]*INS[6]) = 1
      // alu_op = INS[6] = 0
      // SEL_A = INS[3:2] = 2'b00
      // SEL_B = INS[1:0] = 2'b10
      // SEL_W = INS[5:4] = 2'b00
      // IMM = INS[3:0] = 4'b0010
      INS = 9'b000000010;
      #4;

      // test 0.2
      // sel_data = INS[7] = 0
      // write_en = ~(INS[7]*INS[6]) = 1
      // alu_op = INS[6] = 0
      // SEL_A = INS[3:2] = 2'b01
      // SEL_B = INS[1:0] = 2'b00
      // SEL_W = INS[5:4] = 2'b00
      // IMM = INS[3:0] = 4'b0100
      INS = 9'b000000100;
      #4;

      // test 0.3
      // sel_data = INS[7] = 0
      // write_en = ~(INS[7]*INS[6]) = 1
      // alu_op = INS[6] = 0
      // SEL_A = INS[3:2] = 2'b10
      // SEL_B = INS[1:0] = 2'b00
      // SEL_W = INS[5:4] = 2'b00
      // IMM = INS[3:0] = 4'b1000
      INS = 9'b000001000;
      #4;

      // test 0.4
      // sel_data = INS[7] = 0
      // write_en = ~(INS[7]*INS[6]) = 1
      // alu_op = INS[6] = 0
      // SEL_A = INS[3:2] = 2'b00
      // SEL_B = INS[1:0] = 2'b00
      // SEL_W = INS[5:4] = 2'b01
      // IMM = INS[3:0] = 4'b0000
      INS = 9'b000010000;
      #4;

      // test 0.5
      // sel_data = INS[7] = 0
      // write_en = ~(INS[7]*INS[6]) = 1
      // alu_op = INS[6] = 0
      // SEL_A = INS[3:2] = 2'b00
      // SEL_B = INS[1:0] = 2'b00
      // SEL_W = INS[5:4] = 2'b10
      // IMM = INS[3:0] = 4'b0000
      INS = 9'b000100000;
      #4;

      // test 0.6
      // sel_data = INS[7] = 0
      // write_en = ~(INS[7]*INS[6]) = 1
      // alu_op = INS[6] = 1
      // SEL_A = INS[3:2] = 2'b00
      // SEL_B = INS[1:0] = 2'b00
      // SEL_W = INS[5:4] = 2'b00
      // IMM = INS[3:0] = 4'b0000
      INS = 9'b001000000;
      #4;

      // test 0.7
      // sel_data = INS[7] = 1
      // write_en = ~(INS[7]*INS[6]) = 1
      // alu_op = INS[6] = 0
      // SEL_A = INS[3:2] = 2'b00
      // SEL_B = INS[1:0] = 2'b00
      // SEL_W = INS[5:4] = 2'b00
      // IMM = INS[3:0] = 4'b0000
      INS = 9'b010000000;
      #4;

      // test 0.8
      // sel_data = INS[7] = 0
      // write_en = ~(INS[7]*INS[6]) = 1
      // alu_op = INS[6] = 0
      // SEL_A = INS[3:2] = 2'b00
      // SEL_B = INS[1:0] = 2'b00
      // SEL_W = INS[5:4] = 2'b00
      // IMM = INS[3:0] = 4'b0000
      INS = 9'b100000000;
      #4;

      // test set 1: edge cases
      // test 1.0: zero
      // sel_data = INS[7] = 0
      // write_en = ~(INS[7]*INS[6]) = 1
      // alu_op = INS[6] = 0
      // SEL_A = INS[3:2] = 2'b00
      // SEL_B = INS[1:0] = 2'b00
      // SEL_W = INS[5:4] = 2'b00
      // IMM = INS[3:0] = 4'b0000
      INS = 9'b000000000;
      #4;

      // test 1.1: INS[7] = INS[6] = 1 for write_en 
      // sel_data = INS[7] = 1
      // write_en = ~(INS[7]*INS[6]) = 0
      // alu_op = INS[6] = 1
      // SEL_A = INS[3:2] = 2'b11
      // SEL_B = INS[1:0] = 2'b11
      // SEL_W = INS[5:4] = 2'b11
      // IMM = INS[3:0] = 4'b1111
      INS = 9'b111111111;
      #4;
   end
endmodule

ins_dec/test.vcd
$date
	Sat Aug 13 16:21:07 2022
$end
$version
	Icarus Verilog
$end
$timescale
	1ns
$end
$scope module testbench $end
$var wire 1 ! write_en $end
$var wire 1 " sel_data $end
$var wire 1 # alu_op $end
$var wire 2 $ SEL_W [1:0] $end
$var wire 2 % SEL_B [1:0] $end
$var wire 2 & SEL_A [1:0] $end
$var wire 4 ' IMM [3:0] $end
$var reg 9 ( INS [8:0] $end
$scope module my_ins_dec $end
$var wire 9 ) INS [8:0] $end
$var wire 1 # alu_op $end
$var wire 1 " sel_data $end
$var wire 1 * w0 $end
$var wire 1 ! write_en $end
$var wire 2 + SEL_W [1:0] $end
$var wire 2 , SEL_B [1:0] $end
$var wire 2 - SEL_A [1:0] $end
$var wire 4 . IMM [3:0] $end
$upscope $end
$upscope $end
$enddefinitions $end
#0
$dumpvars
bx .
bx -
bx ,
bx +
x*
b1 )
b1 (
bx '
bx &
bx %
bx $
x#
x"
x!
$end
#1
0"
0#
b0 &
b0 -
b1 %
b1 ,
b0 $
b0 +
b1 '
b1 .
#3
0*
#4
1!
b10 (
b10 )
#5
b10 %
b10 ,
b10 '
b10 .
#8
b100 (
b100 )
#9
b1 &
b1 -
b0 %
b0 ,
b100 '
b100 .
#12
b1000 (
b1000 )
#13
b10 &
b10 -
b1000 '
b1000 .
#16
b10000 (
b10000 )
#17
b0 &
b0 -
b1 $
b1 +
b0 '
b0 .
#20
b100000 (
b100000 )
#21
b10 $
b10 +
#24
b1000000 (
b1000000 )
#25
1#
b0 $
b0 +
#28
b10000000 (
b10000000 )
#29
1"
0#
#32
b100000000 (
b100000000 )
#33
0"
#36
b0 (
b0 )
#40
b111111111 (
b111111111 )
#41
1"
1#
b11 &
b11 -
b11 %
b11 ,
b11 $
b11 +
b1111 '
b1111 .
#43
1*
#44
0!
