ins_dec/ins_dec.v
// Critical path delay = 7ns
module ins_dec(INS, sel_data, write_en, alu_op, SEL_A, SEL_B, SEL_W, IMM, JMP);
   input [10:0] INS;
   output      sel_data;
   output      write_en;
   output      alu_op;
   output [1:0] SEL_A;
   output [1:0] SEL_B;
   output [1:0] SEL_W;
   output [3:0] IMM;
   output [3:0] JMP;
   // sel_data = INS[9]
   buf #(1) buf_0(sel_data, INS[9]); // buf is wire delay
   // write_en = (INS[10]+~INS[9]+~INS[8])*(~INS[10]+INS[9]+INS[8])
   wire         w0, w1, w2, w3, w4;
   not #(1) not_0(w0, INS[9]);
   not #(1) not_1(w1, INS[8]);
   not #(1) not_2(w2, INS[10]);
   or #(3) or_0(w3, INS[10], w0, w1);
   or #(3) or_1(w4, w2, INS[9], INS[8]);
   and #(3) and_0(write_en, w3, w4);
   // alu_op = INS[8]
   buf #(1) buf_1(alu_op, INS[8]);
   // SEL_A = INS[3:2]
   buf #(1) buf_2(SEL_A[1], INS[3]);
   buf #(1) buf_3(SEL_A[0], INS[2]);
   // SEL_B = INS[1:0]
   buf #(1) buf_4(SEL_B[1], INS[1]);
   buf #(1) buf_5(SEL_B[0], INS[0]);
   // SEL_W = INS[5:4]
   buf #(1) buf_6(SEL_W[1], INS[5]);
   buf #(1) buf_7(SEL_W[0], INS[4]);
   // IMM = INS[3:0]
   buf #(1) buf_8(IMM[3], INS[3]);
   buf #(1) buf_9(IMM[2], INS[2]);
   buf #(1) buf_10(IMM[1], INS[1]);
   buf #(1) buf_11(IMM[0], INS[0]);
   // JMP = INS[7:4]
   buf #(1) buf_12(JMP[3], INS[7]);
   buf #(1) buf_13(JMP[2], INS[6]);
   buf #(1) buf_14(JMP[1], INS[5]);
   buf #(1) buf_15(JMP[0], INS[4]);
endmodule

ins_dec/testbench.v
// testbench for instruction decoder combination logic
// actual instructions will be tested in ../datapath
`timescale 1 ns/1 ns	//time scale for simulation

module testbench;
   reg [10:0] INS;
   wire      sel_data;
   wire      write_en;
   wire      alu_op;
   wire [1:0] SEL_A;
   wire [1:0] SEL_B;
   wire [1:0] SEL_W;
   wire [3:0] IMM;
   wire [3:0] JMP;

   ins_dec my_ins_dec(.INS(INS), .sel_data(sel_data), .write_en(write_en), .alu_op(alu_op), .SEL_A(SEL_A), .SEL_B(SEL_B), .SEL_W(SEL_W), .IMM(IMM), .JMP(JMP));

   initial begin
      $dumpfile("test.vcd");
      $dumpvars(0, testbench);

      // test 0: all zeros
      // sel_data = INS[9] = 0
      // write_en = (INS[10]+~INS[9]+~INS[8])*(~INS[10]+INS[9]+INS[8])
      //          = (0+1+1)*(1+0+0) = 1*1 = 1
      // alu_op = INS[8] = 0
      // SEL_A = INS[3:2] = 2'b00
      // SEL_B = INS[1:0] = 2'b00
      // SEL_W = INS[5:4] = 2'b00
      // IMM = INS[3:0] = 4'b0000
      // JMP = INS[7:4] = 4'b0000
      INS = 11'b000000000;
      #7;

      // test 1: all ones
      // sel_data = INS[9] = 1
      // write_en = (INS[10]+~INS[9]+~INS[8])*(~INS[10]+INS[9]+INS[8])
      //          = (1+0+0)*(0+1+1) = 1*1 = 1
      // alu_op = INS[8] = 1
      // SEL_A = INS[3:2] = 2'b11
      // SEL_B = INS[1:0] = 2'b11
      // SEL_W = INS[5:4] = 2'b11
      // IMM = INS[3:0] = 4'b1111
      // JMP = INS[7:4] = 4'b1111
      INS = 11'b11111111111;
      #7;

      // test 2: interlacing 1
      // sel_data = INS[9] = 0
      // write_en = (INS[10]+~INS[9]+~INS[8])*(~INS[10]+INS[9]+INS[8])
      //          = (1+1+0)*(0+0+1) = 1*1 = 1
      // alu_op = INS[8] = 1
      // SEL_A = INS[3:2] = 2'b01
      // SEL_B = INS[1:0] = 2'b01
      // SEL_W = INS[5:4] = 2'b01
      // IMM = INS[3:0] = 4'b0101
      // JMP = INS[7:4] = 4'b0101
      INS = 11'b10101010101;
      #7;
      
      // test 3: interlacing 2
      // sel_data = INS[9] = 1
      // write_en = (INS[10]+~INS[9]+~INS[8])*(~INS[10]+INS[9]+INS[8])
      //          = (0+0+1)*(1+1+0) = 1*1 = 1
      // alu_op = INS[8] = 0
      // SEL_A = INS[3:2] = 2'b10
      // SEL_B = INS[1:0] = 2'b10
      // SEL_W = INS[5:4] = 2'b10
      // IMM = INS[3:0] = 4'b1010
      // JMP = INS[7:4] = 4'b1010
      INS = 11'b01010101010;
      #7;
      
      // test 4: branch opcode, write_en should be 0
      // sel_data = INS[9] = 0
      // write_en = (INS[10]+~INS[9]+~INS[8])*(~INS[10]+INS[9]+INS[8])
      //          = (1+1+1)*(0+0+0) = 1*0 = 0
      // alu_op = INS[8] = 0
      // SEL_A = INS[3:2] = 2'b00
      // SEL_B = INS[1:0] = 2'b00
      // SEL_W = INS[5:4] = 2'b00
      // IMM = INS[3:0] = 4'b0000
      // JMP = INS[7:4] = 4'b0000
      INS = 11'b10000000000;
      #7;

      // test 5: noop opcode, write_en should be 0
      // sel_data = INS[9] = 1
      // write_en = (INS[10]+~INS[9]+~INS[8])*(~INS[10]+INS[9]+INS[8])
      //          = (0+0+0)*(1+1+1) = 0*1 = 0
      // alu_op = INS[8] = 1
      // SEL_A = INS[3:2] = 2'b00
      // SEL_B = INS[1:0] = 2'b00
      // SEL_W = INS[5:4] = 2'b00
      // IMM = INS[3:0] = 4'b0000
      // JMP = INS[7:4] = 4'b0000
      INS = 11'b01100000000;
      #7;      
   end
endmodule

ins_dec/test.vcd
$date
	Thu Sep  8 21:03:56 2022
$end
$version
	Icarus Verilog
$end
$timescale
	1ns
$end
$scope module testbench $end
$var wire 1 ! write_en $end
$var wire 1 " sel_data $end
$var wire 1 # alu_op $end
$var wire 2 $ SEL_W [1:0] $end
$var wire 2 % SEL_B [1:0] $end
$var wire 2 & SEL_A [1:0] $end
$var wire 4 ' JMP [3:0] $end
$var wire 4 ( IMM [3:0] $end
$var reg 11 ) INS [10:0] $end
$scope module my_ins_dec $end
$var wire 11 * INS [10:0] $end
$var wire 1 # alu_op $end
$var wire 1 " sel_data $end
$var wire 1 + w0 $end
$var wire 1 , w1 $end
$var wire 1 - w2 $end
$var wire 1 . w3 $end
$var wire 1 / w4 $end
$var wire 1 ! write_en $end
$var wire 2 0 SEL_W [1:0] $end
$var wire 2 1 SEL_B [1:0] $end
$var wire 2 2 SEL_A [1:0] $end
$var wire 4 3 JMP [3:0] $end
$var wire 4 4 IMM [3:0] $end
$upscope $end
$upscope $end
$enddefinitions $end
#0
$dumpvars
bx 4
bx 3
bx 2
bx 1
bx 0
x/
x.
x-
x,
x+
b0 *
b0 )
bx (
bx '
bx &
bx %
bx $
x#
x"
x!
$end
#1
0"
1+
1,
1-
0#
b0 &
b0 2
b0 %
b0 1
b0 $
b0 0
b0 (
b0 4
b0 '
b0 3
#4
1.
1/
#7
1!
b11111111111 )
b11111111111 *
#8
1"
0+
0,
0-
1#
b11 &
b11 2
b11 %
b11 1
b11 $
b11 0
b1111 (
b1111 4
b1111 '
b1111 3
#14
b10101010101 )
b10101010101 *
#15
0"
1+
b1 &
b1 2
b1 %
b1 1
b1 $
b1 0
b101 (
b101 4
b101 '
b101 3
#21
b1010101010 )
b1010101010 *
#22
1"
0+
1,
1-
0#
b10 &
b10 2
b10 %
b10 1
b10 $
b10 0
b1010 (
b1010 4
b1010 '
b1010 3
#28
b10000000000 )
b10000000000 *
#29
0"
1+
0-
b0 &
b0 2
b0 %
b0 1
b0 $
b0 0
b0 (
b0 4
b0 '
b0 3
#32
0/
#35
0!
b1100000000 )
b1100000000 *
#36
1"
0+
0,
1-
1#
#38
1/
#39
0.
