fa/fa.v
module fa(a, b, c_in, sum, c_out);
   input a;
   input b;
   input c_in;
   output sum;
   output c_out;
   wire   w0;
   xor #(4) xor0(w0, a, b);
   wire   w1;
   and #(3) and0(w1, a, b);
   wire   w2;
   and #(3) and1(w2, w0, c_in);
   xor #(4) xor1(sum, w0, c_in);
   or #(3) or0(c_out, w1, w2);
endmodule

rca/rca.v
// Critical path delay: 44 ns
module rca(A, B, SUM, ovf);
   input [3:0] A;
   input [3:0] B;
   output [3:0] SUM;
   output       ovf;
   wire         c_out0;
   fa fa0(.a(A[0]), .b(B[0]), .c_in(1'b0), .sum(SUM[0]), .c_out(c_out0));
   wire         c_out1;
   fa fa1(.a(A[1]), .b(B[1]), .c_in(c_out0), .sum(SUM[1]), .c_out(c_out1));
   wire         c_out2;
   fa fa2(.a(A[2]), .b(B[2]), .c_in(c_out1), .sum(SUM[2]), .c_out(c_out2));
   wire         c_out3;
   fa fa3(.a(A[3]), .b(B[3]), .c_in(c_out2), .sum(SUM[3]), .c_out(c_out3));
   xor #(4) xor_0(ovf, c_out2, c_out3);
endmodule

sr_latch/sr_latch.v
// Critical path delay = 6ns
module sr_latch(r, s, q, qb);
   input r;
   input s;
   output q;
   output qb;
   nor #(2) nor0(q, r, qb);
   nor #(2) nor1(qb, q, s);
endmodule; // d_latch

d_latch/d_latch.v
// Critical path delay = 6ns
module d_latch(d, g, q, qb);
   input d;
   input g;
   output q;
   output qb;
   wire   nd;
   not #(1) not0(nd, d);
   wire   r;
   and #(3) and0(r, nd, g);
   wire   s;
   and #(3) and1(s, d, g);
   sr_latch sr_latch_0(.r(r), .s(s), .q(q), .qb(qb));
endmodule // d_latch

dff/dff.v
// Setup delay = hold delay = 17ns
module dff(d, clk, q, qb);
   input d;
   input clk;
   output q;
   output qb;
   
   wire nclk;
   not #(1) not0(nclk, clk);
   wire q_tmp;
   wire qb_tmp;
   d_latch d_latch_0(.d(d), .g(nclk), .q(q_tmp), .qb(qb_tmp));
   d_latch d_latch_1(.d(q_tmp), .g(clk), .q(q), .qb(qb));
endmodule; // dff

reg4/reg4.v
// Implementation of a PIPO shift register
// Setup delay = hold delay = 17ns
module reg4(D, clk, Q, QB);
   input [3:0] D;
   input       clk;
   output [3:0] Q;
   output [3:0] QB;

   dff DFF[3:0](.d(D), .clk(clk), .q(Q), .qb(QB));
endmodule; // reg4

mux_2_1_1b/mux_2_1_1b.v
// Critical path delay = 7ns
// 0 -> copy a
// 1 -> copy b
module mux_2_1_1b(a, b, sel, res);
   input a;
   input b;
   input sel;
   output res;
   wire   not_sel;
   not #(1) not0(not_sel, sel);
   wire   a_out;
   and #(3) and0(a_out, a, not_sel);
   wire   b_out;
   and #(3) and1(b_out, b, sel);
   or #(3) and2(res, a_out, b_out);
endmodule // mux1

mux_2_1_4b/mux_2_1_4b.v
// Critical path delay = 7ns
module mux_2_1_4b(A, B, sel, RES);
   input [3:0] A;
   input [3:0] B;
   input       sel;
   output [3:0] RES;
   mux_2_1_1b mux_2_1_1b_0[3:0](.a(A), .b(B), .sel(sel), .res(RES));
endmodule; // mux4

pc/pc.v
// Min setup time = 35 ns
// Min hold time = 61 ns
module pc(set_pc, alu_eq, clk, INS, PC_CURR);
   input set_pc;
   input alu_eq;
   input clk;
   input [10:0] INS;
   output [3:0] PC_CURR;
   wire w1;
   not #(1) not_1(w1, INS[9]);
   wire w0;
   not #(1) not_0(w0, INS[8]);
   wire set_next;
   and #(3) and_0(set_next, alu_eq, INS[10], w1, w0);
   wire [3:0]   PC_PLUS_JMP;
   wire [3:0]   PC_PLUS_ONE;
   wire [3:0]   PC_NEXT;
   mux_2_1_4b mux_2_1_4b_0(.A(PC_PLUS_ONE), .B(PC_PLUS_JMP), .sel(set_next), .RES(PC_NEXT));
   wire [3:0]   PC_REG_IN;
   mux_2_1_4b mux_2_1_4b_1(.A(PC_NEXT), .B(4'b0000), .sel(set_pc), .RES(PC_REG_IN));
   wire [3:0] PC_CURR_INV;
   reg4 pc_reg(.D(PC_REG_IN), .clk(clk), .Q(PC_CURR), .QB(PC_CURR_INV));
   rca rca_0(.A(4'b0001), .B(PC_CURR), .SUM(PC_PLUS_ONE));
   rca rca_1(.A(INS[7:4]), .B(PC_CURR), .SUM(PC_PLUS_JMP));
endmodule;

pc/testbench.v
`timescale 1 ns/1 ns	//time scale for simulation

module testbench;
   reg set_pc;
   reg alu_eq;
   reg clk;
   reg [10:0] INS;
   wire [3:0] PC_CURR;
   pc my_pc(.set_pc(set_pc), .alu_eq(alu_eq), .clk(clk), .INS(INS), .PC_CURR(PC_CURR));

   initial begin
      $dumpfile("test.vcd");
      $dumpvars(0, testbench);
      /*
       test 0
       time: 0 ns
       PC_CURR = 4'bxxxx
       */
      INS = 11'b01100000000;
      alu_eq = 1;
      clk = 0;
      set_pc = 1;
      #75;
      clk = 1;
      #17;
      
      /*
       test 1
       time: 92 ns
       PC_CURR = 4'b0000
       */
      clk = 0;
      set_pc = 0;
      #75;
      clk = 1;
      #17;

      /*
       test 2
       time: 184 ns
       PC_CURR = 4'b0001
       */
      clk = 0;
      #75;
      clk = 1;
      #17;

      /*
       test 3
       time: 276 ns
       PC_CURR = 4'b0010
       */
      clk = 0;
      #75;
      clk = 1;
      #17;

      /*
       test 4
       time: 368 ns
       PC_CURR = 4'b0011
       */
      clk = 0;
      #75;
      clk = 1;
      #17;

      /*
       test 5
       time: 460 ns
       PC_CURR = 4'b0100
       */
      clk = 0;
      #75;
      clk = 1;
      #17;

      /*
       test 6
       time: 552 ns
       PC_CURR = 4'b0101
       */
      clk = 0;
      #75;
      clk = 1;
      #17;

      /*
       test 7
       time: 644 ns
       PC_CURR = 4'b0110
       */
      clk = 0;
      #75;
      clk = 1;
      #17;

      /*
       test 8
       time: 736 ns
       PC_CURR = 4'b0111
       */
      clk = 0;
      #75;
      clk = 1;
      #17;

      /*
       test 9
       time: 828 ns
       PC_CURR = 4'b1000
       */
      clk = 0;
      #75;
      clk = 1;
      #17;

      /*
       test 10
       time: 920 ns
       PC_CURR = 4'b1001
       */
      clk = 0;
      #75;
      clk = 1;
      #17;

      /*
       test 11
       time: 1012 ns
       PC_CURR = 4'b1010
       */
      clk = 0;
      #75;
      clk = 1;
      #17;

      /*
       test 12
       time: 1104 ns
       PC_CURR = 4'b1011
       */
      clk = 0;
      #75;
      clk = 1;
      #17;

      /*
       test 13
       time: 1196 ns
       PC_CURR = 4'b1100
       */
      clk = 0;
      #75;
      clk = 1;
      #17;

      /*
       test 14
       time: 1288 ns
       PC_CURR = 4'b1101
       */
      clk = 0;
      #75;
      clk = 1;
      #17;

      /*
       test 15
       time: 1380 ns
       PC_CURR = 4'b1110
       */
      clk = 0;
      #75;
      clk = 1;
      #17;

      /*
       test 16
       time: 1472 ns
       PC_CURR = 4'b1111
       */
      clk = 0;
      #75;
      clk = 1;
      #17;

      /*
       test 17
       time: 1564 ns
       PC_CURR = 4'b0000
       INS -> branch + 7
       */
      INS = 11'b10001110000;
      clk = 0;
      #75;
      clk = 1;
      #17;

      /*
       test 18
       time: 1656 ns
       PC_CURR = 4'b0111
       INS -> branch - 8
       */
      INS = 11'b10011100000;
      clk = 0;
      #75;
      clk = 1;
      #17;

      /*
       test 19
       time: 1748 ns
       PC_CURR = 4'b1111
       INS -> branch + 0
       */
      INS = 11'b10000000000;
      clk = 0;
      #75;
      clk = 1;
      #17;

      /*
       test 20
       time: 1840 ns
       PC_CURR = 4'b1111
       */
      clk = 0;
      #75;
      clk = 1;
      #17;
      
      $finish;
   end
endmodule

pc/test.vcd
$date
	Fri Sep  9 11:39:09 2022
$end
$version
	Icarus Verilog
$end
$timescale
	1ns
$end
$scope module testbench $end
$var wire 4 ! PC_CURR [3:0] $end
$var reg 11 " INS [10:0] $end
$var reg 1 # alu_eq $end
$var reg 1 $ clk $end
$var reg 1 % set_pc $end
$scope module my_pc $end
$var wire 11 & INS [10:0] $end
$var wire 1 # alu_eq $end
$var wire 1 $ clk $end
$var wire 1 ' set_next $end
$var wire 1 % set_pc $end
$var wire 1 ( w0 $end
$var wire 1 ) w1 $end
$var wire 4 * PC_REG_IN [3:0] $end
$var wire 4 + PC_PLUS_ONE [3:0] $end
$var wire 4 , PC_PLUS_JMP [3:0] $end
$var wire 4 - PC_NEXT [3:0] $end
$var wire 4 . PC_CURR_INV [3:0] $end
$var wire 4 / PC_CURR [3:0] $end
$scope module mux_2_1_4b_0 $end
$var wire 1 ' sel $end
$var wire 4 0 RES [3:0] $end
$var wire 4 1 B [3:0] $end
$var wire 4 2 A [3:0] $end
$scope module mux_2_1_1b_0[0] $end
$var wire 1 3 a $end
$var wire 1 4 a_out $end
$var wire 1 5 b $end
$var wire 1 6 b_out $end
$var wire 1 7 not_sel $end
$var wire 1 8 res $end
$var wire 1 ' sel $end
$upscope $end
$scope module mux_2_1_1b_0[1] $end
$var wire 1 9 a $end
$var wire 1 : a_out $end
$var wire 1 ; b $end
$var wire 1 < b_out $end
$var wire 1 = not_sel $end
$var wire 1 > res $end
$var wire 1 ' sel $end
$upscope $end
$scope module mux_2_1_1b_0[2] $end
$var wire 1 ? a $end
$var wire 1 @ a_out $end
$var wire 1 A b $end
$var wire 1 B b_out $end
$var wire 1 C not_sel $end
$var wire 1 D res $end
$var wire 1 ' sel $end
$upscope $end
$scope module mux_2_1_1b_0[3] $end
$var wire 1 E a $end
$var wire 1 F a_out $end
$var wire 1 G b $end
$var wire 1 H b_out $end
$var wire 1 I not_sel $end
$var wire 1 J res $end
$var wire 1 ' sel $end
$upscope $end
$upscope $end
$scope module mux_2_1_4b_1 $end
$var wire 4 K A [3:0] $end
$var wire 4 L B [3:0] $end
$var wire 1 % sel $end
$var wire 4 M RES [3:0] $end
$scope module mux_2_1_1b_0[0] $end
$var wire 1 N a $end
$var wire 1 O a_out $end
$var wire 1 P b $end
$var wire 1 Q b_out $end
$var wire 1 R not_sel $end
$var wire 1 S res $end
$var wire 1 % sel $end
$upscope $end
$scope module mux_2_1_1b_0[1] $end
$var wire 1 T a $end
$var wire 1 U a_out $end
$var wire 1 V b $end
$var wire 1 W b_out $end
$var wire 1 X not_sel $end
$var wire 1 Y res $end
$var wire 1 % sel $end
$upscope $end
$scope module mux_2_1_1b_0[2] $end
$var wire 1 Z a $end
$var wire 1 [ a_out $end
$var wire 1 \ b $end
$var wire 1 ] b_out $end
$var wire 1 ^ not_sel $end
$var wire 1 _ res $end
$var wire 1 % sel $end
$upscope $end
$scope module mux_2_1_1b_0[3] $end
$var wire 1 ` a $end
$var wire 1 a a_out $end
$var wire 1 b b $end
$var wire 1 c b_out $end
$var wire 1 d not_sel $end
$var wire 1 e res $end
$var wire 1 % sel $end
$upscope $end
$upscope $end
$scope module pc_reg $end
$var wire 4 f D [3:0] $end
$var wire 1 $ clk $end
$var wire 4 g QB [3:0] $end
$var wire 4 h Q [3:0] $end
$scope module DFF[0] $end
$var wire 1 $ clk $end
$var wire 1 i d $end
$var wire 1 j nclk $end
$var wire 1 k qb_tmp $end
$var wire 1 l qb $end
$var wire 1 m q_tmp $end
$var wire 1 n q $end
$scope module d_latch_0 $end
$var wire 1 i d $end
$var wire 1 j g $end
$var wire 1 o nd $end
$var wire 1 p r $end
$var wire 1 q s $end
$var wire 1 k qb $end
$var wire 1 m q $end
$scope module sr_latch_0 $end
$var wire 1 m q $end
$var wire 1 k qb $end
$var wire 1 p r $end
$var wire 1 q s $end
$upscope $end
$upscope $end
$scope module d_latch_1 $end
$var wire 1 m d $end
$var wire 1 $ g $end
$var wire 1 r nd $end
$var wire 1 s r $end
$var wire 1 t s $end
$var wire 1 l qb $end
$var wire 1 n q $end
$scope module sr_latch_0 $end
$var wire 1 n q $end
$var wire 1 l qb $end
$var wire 1 s r $end
$var wire 1 t s $end
$upscope $end
$upscope $end
$upscope $end
$scope module DFF[1] $end
$var wire 1 $ clk $end
$var wire 1 u d $end
$var wire 1 v nclk $end
$var wire 1 w qb_tmp $end
$var wire 1 x qb $end
$var wire 1 y q_tmp $end
$var wire 1 z q $end
$scope module d_latch_0 $end
$var wire 1 u d $end
$var wire 1 v g $end
$var wire 1 { nd $end
$var wire 1 | r $end
$var wire 1 } s $end
$var wire 1 w qb $end
$var wire 1 y q $end
$scope module sr_latch_0 $end
$var wire 1 y q $end
$var wire 1 w qb $end
$var wire 1 | r $end
$var wire 1 } s $end
$upscope $end
$upscope $end
$scope module d_latch_1 $end
$var wire 1 y d $end
$var wire 1 $ g $end
$var wire 1 ~ nd $end
$var wire 1 !" r $end
$var wire 1 "" s $end
$var wire 1 x qb $end
$var wire 1 z q $end
$scope module sr_latch_0 $end
$var wire 1 z q $end
$var wire 1 x qb $end
$var wire 1 !" r $end
$var wire 1 "" s $end
$upscope $end
$upscope $end
$upscope $end
$scope module DFF[2] $end
$var wire 1 $ clk $end
$var wire 1 #" d $end
$var wire 1 $" nclk $end
$var wire 1 %" qb_tmp $end
$var wire 1 &" qb $end
$var wire 1 '" q_tmp $end
$var wire 1 (" q $end
$scope module d_latch_0 $end
$var wire 1 #" d $end
$var wire 1 $" g $end
$var wire 1 )" nd $end
$var wire 1 *" r $end
$var wire 1 +" s $end
$var wire 1 %" qb $end
$var wire 1 '" q $end
$scope module sr_latch_0 $end
$var wire 1 '" q $end
$var wire 1 %" qb $end
$var wire 1 *" r $end
$var wire 1 +" s $end
$upscope $end
$upscope $end
$scope module d_latch_1 $end
$var wire 1 '" d $end
$var wire 1 $ g $end
$var wire 1 ," nd $end
$var wire 1 -" r $end
$var wire 1 ." s $end
$var wire 1 &" qb $end
$var wire 1 (" q $end
$scope module sr_latch_0 $end
$var wire 1 (" q $end
$var wire 1 &" qb $end
$var wire 1 -" r $end
$var wire 1 ." s $end
$upscope $end
$upscope $end
$upscope $end
$scope module DFF[3] $end
$var wire 1 $ clk $end
$var wire 1 /" d $end
$var wire 1 0" nclk $end
$var wire 1 1" qb_tmp $end
$var wire 1 2" qb $end
$var wire 1 3" q_tmp $end
$var wire 1 4" q $end
$scope module d_latch_0 $end
$var wire 1 /" d $end
$var wire 1 0" g $end
$var wire 1 5" nd $end
$var wire 1 6" r $end
$var wire 1 7" s $end
$var wire 1 1" qb $end
$var wire 1 3" q $end
$scope module sr_latch_0 $end
$var wire 1 3" q $end
$var wire 1 1" qb $end
$var wire 1 6" r $end
$var wire 1 7" s $end
$upscope $end
$upscope $end
$scope module d_latch_1 $end
$var wire 1 3" d $end
$var wire 1 $ g $end
$var wire 1 8" nd $end
$var wire 1 9" r $end
$var wire 1 :" s $end
$var wire 1 2" qb $end
$var wire 1 4" q $end
$scope module sr_latch_0 $end
$var wire 1 4" q $end
$var wire 1 2" qb $end
$var wire 1 9" r $end
$var wire 1 :" s $end
$upscope $end
$upscope $end
$upscope $end
$upscope $end
$scope module rca_0 $end
$var wire 4 ;" A [3:0] $end
$var wire 4 <" B [3:0] $end
$var wire 1 =" ovf $end
$var wire 1 >" c_out3 $end
$var wire 1 ?" c_out2 $end
$var wire 1 @" c_out1 $end
$var wire 1 A" c_out0 $end
$var wire 4 B" SUM [3:0] $end
$scope module fa0 $end
$var wire 1 C" a $end
$var wire 1 D" b $end
$var wire 1 E" c_in $end
$var wire 1 A" c_out $end
$var wire 1 F" sum $end
$var wire 1 G" w0 $end
$var wire 1 H" w1 $end
$var wire 1 I" w2 $end
$upscope $end
$scope module fa1 $end
$var wire 1 J" a $end
$var wire 1 K" b $end
$var wire 1 A" c_in $end
$var wire 1 @" c_out $end
$var wire 1 L" sum $end
$var wire 1 M" w0 $end
$var wire 1 N" w1 $end
$var wire 1 O" w2 $end
$upscope $end
$scope module fa2 $end
$var wire 1 P" a $end
$var wire 1 Q" b $end
$var wire 1 @" c_in $end
$var wire 1 ?" c_out $end
$var wire 1 R" sum $end
$var wire 1 S" w0 $end
$var wire 1 T" w1 $end
$var wire 1 U" w2 $end
$upscope $end
$scope module fa3 $end
$var wire 1 V" a $end
$var wire 1 W" b $end
$var wire 1 ?" c_in $end
$var wire 1 >" c_out $end
$var wire 1 X" sum $end
$var wire 1 Y" w0 $end
$var wire 1 Z" w1 $end
$var wire 1 [" w2 $end
$upscope $end
$upscope $end
$scope module rca_1 $end
$var wire 4 \" A [3:0] $end
$var wire 4 ]" B [3:0] $end
$var wire 1 ^" ovf $end
$var wire 1 _" c_out3 $end
$var wire 1 `" c_out2 $end
$var wire 1 a" c_out1 $end
$var wire 1 b" c_out0 $end
$var wire 4 c" SUM [3:0] $end
$scope module fa0 $end
$var wire 1 d" a $end
$var wire 1 e" b $end
$var wire 1 f" c_in $end
$var wire 1 b" c_out $end
$var wire 1 g" sum $end
$var wire 1 h" w0 $end
$var wire 1 i" w1 $end
$var wire 1 j" w2 $end
$upscope $end
$scope module fa1 $end
$var wire 1 k" a $end
$var wire 1 l" b $end
$var wire 1 b" c_in $end
$var wire 1 a" c_out $end
$var wire 1 m" sum $end
$var wire 1 n" w0 $end
$var wire 1 o" w1 $end
$var wire 1 p" w2 $end
$upscope $end
$scope module fa2 $end
$var wire 1 q" a $end
$var wire 1 r" b $end
$var wire 1 a" c_in $end
$var wire 1 `" c_out $end
$var wire 1 s" sum $end
$var wire 1 t" w0 $end
$var wire 1 u" w1 $end
$var wire 1 v" w2 $end
$upscope $end
$scope module fa3 $end
$var wire 1 w" a $end
$var wire 1 x" b $end
$var wire 1 `" c_in $end
$var wire 1 _" c_out $end
$var wire 1 y" sum $end
$var wire 1 z" w0 $end
$var wire 1 {" w1 $end
$var wire 1 |" w2 $end
$upscope $end
$upscope $end
$upscope $end
$upscope $end
$enddefinitions $end
#0
$dumpvars
x|"
x{"
xz"
xy"
xx"
0w"
xv"
xu"
xt"
xs"
xr"
0q"
xp"
xo"
xn"
xm"
xl"
0k"
xj"
xi"
xh"
xg"
0f"
xe"
0d"
bx c"
xb"
xa"
x`"
x_"
x^"
bx ]"
b0 \"
x["
xZ"
xY"
xX"
xW"
0V"
xU"
xT"
xS"
xR"
xQ"
0P"
xO"
xN"
xM"
xL"
xK"
0J"
xI"
xH"
xG"
xF"
0E"
xD"
1C"
bx B"
xA"
x@"
x?"
x>"
x="
bx <"
b1 ;"
x:"
x9"
x8"
x7"
x6"
x5"
x4"
x3"
x2"
x1"
x0"
x/"
x."
x-"
x,"
x+"
x*"
x)"
x("
x'"
x&"
x%"
x$"
x#"
x""
x!"
x~
x}
x|
x{
xz
xy
xx
xw
xv
xu
xt
xs
xr
xq
xp
xo
xn
xm
xl
xk
xj
xi
bx h
bx g
bx f
xe
xd
xc
0b
xa
x`
x_
x^
x]
0\
x[
xZ
xY
xX
xW
0V
xU
xT
xS
xR
xQ
0P
xO
xN
bx M
b0 L
bx K
xJ
xI
xH
xG
xF
xE
xD
xC
xB
xA
x@
x?
x>
x=
x<
x;
x:
x9
x8
x7
x6
x5
x4
x3
bx 2
bx 1
bx 0
bx /
bx .
bx -
bx ,
bx +
bx *
x)
x(
x'
b1100000000 &
1%
0$
1#
b1100000000 "
bx !
$end
#1
0)
0(
0R
0X
0^
0d
1j
1v
1$"
10"
#3
0i"
0o"
0u"
0{"
0'
0j"
0Z"
0T"
0N"
0I"
0:"
09"
0."
0-"
0""
0!"
0t
0s
0c
0]
0W
0Q
#4
17
1=
1C
1I
0O
0U
0[
0a
#6
06
0<
0B
0H
0b"
#7
0i
0u
0#"
0/"
0S
0Y
0_
b0 *
b0 M
b0 f
0e
#8
1o
1{
1)"
15"
#9
0p"
#10
0q
0}
0+"
07"
#11
1p
1|
1*"
16"
#12
0a"
#13
0m
0y
0'"
03"
#14
1r
1~
1,"
18"
#15
1k
1w
1%"
11"
0v"
#18
0`"
#21
0|"
#24
0_"
#28
0^"
#75
1$
#76
0j
0v
0$"
00"
#78
1s
1!"
1-"
19"
#79
0p
0|
0*"
06"
#80
0D"
0e"
0K"
0l"
0Q"
0r"
0W"
0x"
0n
0z
0("
b0 !
b0 /
b0 h
b0 <"
b0 ]"
04"
#82
1l
1x
1&"
b1111 .
b1111 g
12"
#83
0H"
#84
1G"
0h"
0M"
0n"
0S"
0t"
0Y"
0z"
#86
0A"
#87
0O"
0U"
0["
#88
13
05
0;
0A
0G
bx1 +
bx1 2
bx1 B"
1F"
0g"
0m"
0s"
b0 ,
b0 1
b0 c"
0y"
#90
09
0@"
0?"
0>"
bx01 +
bx01 2
bx01 B"
0L"
#91
14
#92
0%
0$
#93
1R
1X
1^
1d
1j
1v
1$"
10"
0:
#94
1N
0?
0E
bx1 -
bx1 0
bx1 K
18
0R"
b1 +
b1 2
b1 B"
0X"
0="
#95
0s
0!"
0-"
09"
#96
0T
xU
x[
xa
1p
1|
1*"
16"
bx01 -
bx01 0
bx01 K
0>
#97
1O
0@
0F
#99
xu
x#"
x/"
0U
xY
x_
bx0 *
bx0 M
bx0 f
xe
#100
1i
0Z
0`
x{
x)"
x5"
bx1 *
bx1 M
bx1 f
1S
0D
b1 -
b1 0
b1 K
0J
#101
0o
#102
0u
x}
x+"
x7"
bx01 *
bx01 M
bx01 f
0Y
#103
1{
1q
0[
0a
x|
x*"
x6"
#104
xw
x%"
x1"
0p
#105
0k
0}
#106
0#"
0/"
xy
x'"
x3"
1|
0_
b1 *
b1 M
b1 f
0e
#107
1)"
15"
x~
x,"
x8"
1m
#108
0r
0y
#109
1~
0+"
07"
#110
1w
1*"
16"
#112
0'"
03"
#113
1,"
18"
#114
1%"
11"
#167
1$
#168
0j
0v
0$"
00"
#170
1t
1!"
1-"
19"
#171
0q
0|
0*"
06"
#172
b1110 .
b1110 g
0l
#174
1D"
1e"
b1 !
b1 /
b1 h
b1 <"
b1 ]"
1n
#177
1H"
#178
0G"
1h"
#180
1A"
#182
03
15
b0 +
b0 2
b0 B"
0F"
b1 ,
b1 1
b1 c"
1g"
#184
19
b10 +
b10 2
b10 B"
1L"
0$
#185
1j
1v
1$"
10"
04
#187
1:
0t
0!"
0-"
09"
#188
0N
1q
1|
1*"
16"
b0 -
b0 0
b0 K
08
#190
1T
b10 -
b10 0
b10 K
1>
#191
0O
#193
1U
#194
0i
b0 *
b0 M
b0 f
0S
#195
1o
#196
1u
b10 *
b10 M
b10 f
1Y
#197
0{
0q
#198
1p
#199
1}
#200
0m
0|
#201
1r
0w
#202
1k
#203
1y
#204
0~
#259
1$
#260
0j
0v
0$"
00"
#262
1s
1""
1-"
19"
#263
0p
0}
0*"
06"
#264
0D"
0e"
b0 !
b0 /
b0 h
b0 <"
b0 ]"
0n
b1100 .
b1100 g
0x
#266
1K"
1l"
b1101 .
b1101 g
1l
b10 !
b10 /
b10 h
b10 <"
b10 ]"
1z
#267
0H"
#268
1G"
0h"
#270
0A"
1M"
1n"
#272
13
05
b11 +
b11 2
b11 B"
1F"
b0 ,
b0 1
b0 c"
0g"
#274
1;
b10 ,
b10 1
b10 c"
1m"
#275
14
#276
0$
#277
1j
1v
1$"
10"
#278
1N
b11 -
b11 0
b11 K
18
#279
0s
0""
0-"
09"
#280
1p
1}
1*"
16"
#281
1O
#284
1i
b11 *
b11 M
b11 f
1S
#285
0o
#287
1q
#288
0p
#289
0k
#291
1m
#292
0r
#351
1$
#352
0j
0v
0$"
00"
#354
1t
1""
1-"
19"
#355
0q
0}
0*"
06"
#356
b1100 .
b1100 g
0l
#358
1D"
1e"
b11 !
b11 /
b11 h
b11 <"
b11 ]"
1n
#361
1H"
#362
0G"
1h"
#364
1A"
#366
03
15
b10 +
b10 2
b10 B"
0F"
b11 ,
b11 1
b11 c"
1g"
#367
1O"
#368
09
b0 +
b0 2
b0 B"
0L"
0$
#369
1j
1v
1$"
10"
04
#370
1@"
#371
0:
0t
0""
0-"
09"
#372
0N
1q
1}
1*"
16"
b10 -
b10 0
b10 K
08
#374
0T
1?
b0 -
b0 0
b0 K
0>
b100 +
b100 2
b100 B"
1R"
#375
0O
#377
0U
1@
#378
0i
b10 *
b10 M
b10 f
0S
#379
1o
#380
0u
1Z
b0 *
b0 M
b0 f
0Y
b100 -
b100 0
b100 K
1D
#381
1{
0q
#382
1p
#383
0}
1[
#384
0m
1|
#385
1r
#386
1#"
1k
0y
b100 *
b100 M
b100 f
1_
#387
0)"
1~
#388
1w
#389
1+"
#390
0*"
#391
0%"
#393
1'"
#394
0,"
#443
1$
#444
0j
0v
0$"
00"
#446
1s
1!"
1."
19"
#447
0p
0|
0+"
06"
#448
0D"
0e"
0K"
0l"
0n
b0 !
b0 /
b0 h
b0 <"
b0 ]"
0z
b1000 .
b1000 g
0&"
#450
1Q"
1r"
1l
b1011 .
b1011 g
1x
b100 !
b100 /
b100 h
b100 <"
b100 ]"
1("
#451
0H"
#452
1G"
0h"
0M"
0n"
#454
0A"
1S"
1t"
#455
0O"
#456
13
05
0;
b101 +
b101 2
b101 B"
1F"
0g"
b0 ,
b0 1
b0 c"
0m"
#457
1U"
#458
0?
1A
0@"
b1 +
b1 2
b1 B"
0R"
b100 ,
b100 1
b100 c"
1s"
#459
14
#460
1?"
0$
#461
1j
1v
1$"
10"
0@
0U"
#462
1N
1?
b101 -
b101 0
b101 K
18
b101 +
b101 2
b101 B"
1R"
#463
0s
0!"
0."
09"
#464
0Z
1E
1p
1|
1+"
16"
b1 -
b1 0
b1 K
0D
0?"
b1101 +
b1101 2
b1101 B"
1X"
1="
#465
1O
1@
#467
0[
1F
#468
1i
1Z
0E
b101 *
b101 M
b101 f
1S
b101 -
b101 0
b101 K
1D
b101 +
b101 2
b101 B"
0X"
0="
#469
0o
#470
0#"
1`
b1 *
b1 M
b1 f
0_
b1101 -
b1101 0
b1101 K
1J
#471
1)"
1q
1[
0F
#472
0p
#473
0k
0+"
1a
#474
1#"
0`
1*"
b101 *
b101 M
b101 f
1_
b101 -
b101 0
b101 K
0J
#475
0)"
1m
#476
1/"
0r
0'"
b1101 *
b1101 M
b1101 f
1e
#477
05"
1,"
1+"
0a
#478
0*"
#479
17"
#480
0/"
1'"
06"
b101 *
b101 M
b101 f
0e
#481
15"
0,"
01"
#483
13"
07"
#484
08"
16"
#486
03"
#487
18"
#488
11"
#535
1$
#536
0j
0v
0$"
00"
#538
1t
1!"
1."
19"
#539
0q
0|
0+"
06"
#540
b1010 .
b1010 g
0l
#542
1D"
1e"
b101 !
b101 /
b101 h
b101 <"
b101 ]"
1n
#545
1H"
#546
0G"
1h"
#548
1A"
#550
03
15
b100 +
b100 2
b100 B"
0F"
b101 ,
b101 1
b101 c"
1g"
#552
19
b110 +
b110 2
b110 B"
1L"
0$
#553
1j
1v
1$"
10"
04
#555
1:
0t
0!"
0."
09"
#556
0N
1q
1|
1+"
16"
b100 -
b100 0
b100 K
08
#558
1T
b110 -
b110 0
b110 K
1>
#559
0O
#561
1U
#562
0i
b100 *
b100 M
b100 f
0S
#563
1o
#564
1u
b110 *
b110 M
b110 f
1Y
#565
0{
0q
#566
1p
#567
1}
#568
0m
0|
#569
1r
0w
#570
1k
#571
1y
#572
0~
#627
1$
#628
0j
0v
0$"
00"
#630
1s
1""
1."
19"
#631
0p
0}
0+"
06"
#632
0D"
0e"
b100 !
b100 /
b100 h
b100 <"
b100 ]"
0n
b1000 .
b1000 g
0x
#634
1K"
1l"
b1001 .
b1001 g
1l
b110 !
b110 /
b110 h
b110 <"
b110 ]"
1z
#635
0H"
#636
1G"
0h"
#638
0A"
1M"
1n"
#640
13
05
b111 +
b111 2
b111 B"
1F"
b100 ,
b100 1
b100 c"
0g"
#642
1;
b110 ,
b110 1
b110 c"
1m"
#643
14
#644
0$
#645
1j
1v
1$"
10"
#646
1N
b111 -
b111 0
b111 K
18
#647
0s
0""
0."
09"
#648
1p
1}
1+"
16"
#649
1O
#652
1i
b111 *
b111 M
b111 f
1S
#653
0o
#655
1q
#656
0p
#657
0k
#659
1m
#660
0r
#719
1$
#720
0j
0v
0$"
00"
#722
1t
1""
1."
19"
#723
0q
0}
0+"
06"
#724
b1000 .
b1000 g
0l
#726
1D"
1e"
b111 !
b111 /
b111 h
b111 <"
b111 ]"
1n
#729
1H"
#730
0G"
1h"
#732
1A"
#734
03
15
b110 +
b110 2
b110 B"
0F"
b111 ,
b111 1
b111 c"
1g"
#735
1O"
#736
09
b100 +
b100 2
b100 B"
0L"
0$
#737
1j
1v
1$"
10"
04
#738
1@"
#739
0:
0t
0""
0."
09"
#740
0N
1q
1}
1+"
16"
b110 -
b110 0
b110 K
08
#741
1U"
#742
0T
0?
b100 -
b100 0
b100 K
0>
b0 +
b0 2
b0 B"
0R"
#743
0O
#744
1?"
#745
0U
0@
#746
0i
b110 *
b110 M
b110 f
0S
#747
1o
#748
0u
0Z
1E
b100 *
b100 M
b100 f
0Y
b0 -
b0 0
b0 K
0D
b1000 +
b1000 2
b1000 B"
1X"
1="
#749
1{
0q
#750
1p
#751
0}
0[
1F
#752
0m
1|
#753
1r
#754
0#"
1`
1k
0y
b0 *
b0 M
b0 f
0_
b1000 -
b1000 0
b1000 K
1J
#755
1)"
1~
#756
1w
#757
0+"
1a
#758
1*"
#760
1/"
0'"
b1000 *
b1000 M
b1000 f
1e
#761
05"
1,"
#762
1%"
#763
17"
#764
06"
#765
01"
#767
13"
#768
08"
#811
1$
#812
0j
0v
0$"
00"
#814
1s
1!"
1-"
1:"
#815
0p
0|
0*"
07"
#816
0D"
0e"
0K"
0l"
0Q"
0r"
0n
0z
b0 !
b0 /
b0 h
b0 <"
b0 ]"
0("
b0 .
b0 g
02"
#818
1W"
1x"
1l
1x
b111 .
b111 g
1&"
b1000 !
b1000 /
b1000 h
b1000 <"
b1000 ]"
14"
#819
0H"
#820
1G"
0h"
0M"
0n"
0S"
0t"
#822
0A"
1Y"
1z"
#823
0O"
0U"
#824
13
05
0;
1?
0A
1F"
0g"
0m"
b1101 +
b1101 2
b1101 B"
1R"
b0 ,
b0 1
b0 c"
0s"
#825
1["
