fa/fa.v
module fa(a, b, c_in, sum, c_out);
   input a;
   input b;
   input c_in;
   output sum;
   output c_out;
   wire   w0;
   xor #(4) xor0(w0, a, b);
   wire   w1;
   and #(3) and0(w1, a, b);
   wire   w2;
   and #(3) and1(w2, w0, c_in);
   xor #(4) xor1(sum, w0, c_in);
   or #(3) or0(c_out, w1, w2);
endmodule

rca/rca.v
module rca(A, B, SUM);
   input [3:0] A;
   input [3:0] B;
   output [3:0] SUM;
   wire         c_out0;
   fa fa0(.a(A[0]), .b(B[0]), .c_in(1'b0), .sum(SUM[0]), .c_out(c_out0));
   wire         c_out1;
   fa fa1(.a(A[1]), .b(B[1]), .c_in(c_out0), .sum(SUM[1]), .c_out(c_out1));
   wire         c_out2;
   fa fa2(.a(A[2]), .b(B[2]), .c_in(c_out1), .sum(SUM[2]), .c_out(c_out2));
   wire         c_out3;
   fa fa3(.a(A[3]), .b(B[3]), .c_in(c_out2), .sum(SUM[3]), .c_out(c_out3));
endmodule

sr_latch/sr_latch.v
// Critical path delay = 6ns
module sr_latch(r, s, q, qb);
   input r;
   input s;
   output q;
   output qb;
   nor #(2) nor0(q, r, qb);
   nor #(2) nor1(qb, q, s);
endmodule; // d_latch

d_latch/d_latch.v
// Critical path delay = 6ns
module d_latch(d, g, q, qb);
   input d;
   input g;
   output q;
   output qb;
   wire   nd;
   not #(1) not0(nd, d);
   wire   r;
   and #(3) and0(r, nd, g);
   wire   s;
   and #(3) and1(s, d, g);
   sr_latch sr_latch_0(.r(r), .s(s), .q(q), .qb(qb));
endmodule // d_latch

dff/dff.v
// Setup delay = hold delay = 17ns
module dff(d, clk, q, qb);
   input d;
   input clk;
   output q;
   output qb;
   
   wire nclk;
   not #(1) not0(nclk, clk);
   wire q_tmp;
   wire qb_tmp;
   d_latch d_latch_0(.d(d), .g(nclk), .q(q_tmp), .qb(qb_tmp));
   d_latch d_latch_1(.d(q_tmp), .g(clk), .q(q), .qb(qb));
endmodule; // dff

reg4/reg4.v
// Implementation of a PIPO shift register
// Setup delay = hold delay = 17ns
module reg4(D, clk, Q, QB);
   input [3:0] D;
   input       clk;
   output [3:0] Q;
   output [3:0] QB;

   dff DFF[3:0](.d(D), .clk(clk), .q(Q), .qb(QB));
endmodule; // reg4

mux_2_1_1b/mux_2_1_1b.v
// Critical path delay = 7ns
// 0 -> copy a
// 1 -> copy b
module mux_2_1_1b(a, b, sel, res);
   input a;
   input b;
   input sel;
   output res;
   wire   not_sel;
   not #(1) not0(not_sel, sel);
   wire   a_out;
   and #(3) and0(a_out, a, not_sel);
   wire   b_out;
   and #(3) and1(b_out, b, sel);
   or #(3) and2(res, a_out, b_out);
endmodule // mux1

mux_2_1_4b/mux_2_1_4b.v
// Critical path delay = 7ns
module mux_2_1_4b(A, B, sel, RES);
   input [3:0] A;
   input [3:0] B;
   input       sel;
   output [3:0] RES;
   mux_2_1_1b mux_2_1_1b_0[3:0](.a(A), .b(B), .sel(sel), .res(RES));
endmodule; // mux4

pc/pc.v
// Min setup time = 17 ns
// Min hold time = 40 ns
module pc(set_pc, clk, PC_CURR);
   input       set_pc;
   input clk;
   output [3:0] PC_CURR;
   wire [3:0]   PC_PLUS_1;
   wire [3:0]   PC_REG_IN;
   mux_2_1_4b mux_2_1_4b_0(.A(PC_PLUS_1), .B(4'b0000), .sel(set_pc), .RES(PC_REG_IN));
   wire [3:0] PC_CURR_INV;
   reg4 pc_reg(.D(PC_REG_IN), .clk(clk), .Q(PC_CURR), .QB(PC_CURR_INV));
   rca pc_adder(.A(4'b0001), .B(PC_CURR), .SUM(PC_PLUS_1));
endmodule;

oscillator/oscillator.v
// Critical path = period/2 = 136 ns
module oscillator(en, w0);
   parameter N = 133; // # of not gates
   input en;
   output w0;
   wire   [N:0] w;
   and #(3) and_0(w[N], en, w[0]);
   genvar i;
   generate
      for (i = N-1; i >= 0; i = i-1) begin
         not #(1) not_i(/*输出*/w[i], /*输入*/w[i+1]);
      end
   endgenerate
   buf buf_0(w0, w[0]);
endmodule;

pc/testbench.v
`timescale 1 ns/1 ns	//time scale for simulation

module testbench;
   reg osc_en;
   wire clk;
   oscillator my_oscillator(.en(osc_en), .w0(clk));
   
   reg       set_pc;
   wire [3:0] PC_CURR;
   pc my_pc(.set_pc(set_pc), .clk(clk), .PC_CURR(PC_CURR));

   initial begin
      $dumpfile("test.vcd");
      $dumpvars(0, testbench);

      // Clock init
      osc_en = 0;
      #136;
      osc_en = 1;
      #136;
      
      /*
       test 0
       time: 116 ns
       PC_CURR = 4'bxxxx
       */
      // clk = 0
      set_pc = 1;
      #136; // mux_21_4b + pc_reg_set
      // clk = 1
      #136; // pc_reg_hold + rca
      
      /*
       test 1
       time: 232
       PC_CURR = 4'b0000
       */
      // clk = 0
      set_pc = 0;
      #136; // mux_21_4b + pc_reg_set
      // clk = 1;
      #136; // pc_reg_hold + rca

      #4352; // range
      $finish;
   end
endmodule

pc/test.vcd
$date
	Sun Aug 21 17:20:31 2022
$end
$version
	Icarus Verilog
$end
$timescale
	1ns
$end
$scope module testbench $end
$var wire 1 ! clk $end
$var wire 4 " PC_CURR [3:0] $end
$var reg 1 # osc_en $end
$var reg 1 $ set_pc $end
$scope module my_oscillator $end
$var wire 1 # en $end
$var wire 1 ! w0 $end
$var wire 134 % w [133:0] $end
$scope begin genblk1[0] $end
$upscope $end
$scope begin genblk1[1] $end
$upscope $end
$scope begin genblk1[2] $end
$upscope $end
$scope begin genblk1[3] $end
$upscope $end
$scope begin genblk1[4] $end
$upscope $end
$scope begin genblk1[5] $end
$upscope $end
$scope begin genblk1[6] $end
$upscope $end
$scope begin genblk1[7] $end
$upscope $end
$scope begin genblk1[8] $end
$upscope $end
$scope begin genblk1[9] $end
$upscope $end
$scope begin genblk1[10] $end
$upscope $end
$scope begin genblk1[11] $end
$upscope $end
$scope begin genblk1[12] $end
$upscope $end
$scope begin genblk1[13] $end
$upscope $end
$scope begin genblk1[14] $end
$upscope $end
$scope begin genblk1[15] $end
$upscope $end
$scope begin genblk1[16] $end
$upscope $end
$scope begin genblk1[17] $end
$upscope $end
$scope begin genblk1[18] $end
$upscope $end
$scope begin genblk1[19] $end
$upscope $end
$scope begin genblk1[20] $end
$upscope $end
$scope begin genblk1[21] $end
$upscope $end
$scope begin genblk1[22] $end
$upscope $end
$scope begin genblk1[23] $end
$upscope $end
$scope begin genblk1[24] $end
$upscope $end
$scope begin genblk1[25] $end
$upscope $end
$scope begin genblk1[26] $end
$upscope $end
$scope begin genblk1[27] $end
$upscope $end
$scope begin genblk1[28] $end
$upscope $end
$scope begin genblk1[29] $end
$upscope $end
$scope begin genblk1[30] $end
$upscope $end
$scope begin genblk1[31] $end
$upscope $end
$scope begin genblk1[32] $end
$upscope $end
$scope begin genblk1[33] $end
$upscope $end
$scope begin genblk1[34] $end
$upscope $end
$scope begin genblk1[35] $end
$upscope $end
$scope begin genblk1[36] $end
$upscope $end
$scope begin genblk1[37] $end
$upscope $end
$scope begin genblk1[38] $end
$upscope $end
$scope begin genblk1[39] $end
$upscope $end
$scope begin genblk1[40] $end
$upscope $end
$scope begin genblk1[41] $end
$upscope $end
$scope begin genblk1[42] $end
$upscope $end
$scope begin genblk1[43] $end
$upscope $end
$scope begin genblk1[44] $end
$upscope $end
$scope begin genblk1[45] $end
$upscope $end
$scope begin genblk1[46] $end
$upscope $end
$scope begin genblk1[47] $end
$upscope $end
$scope begin genblk1[48] $end
$upscope $end
$scope begin genblk1[49] $end
$upscope $end
$scope begin genblk1[50] $end
$upscope $end
$scope begin genblk1[51] $end
$upscope $end
$scope begin genblk1[52] $end
$upscope $end
$scope begin genblk1[53] $end
$upscope $end
$scope begin genblk1[54] $end
$upscope $end
$scope begin genblk1[55] $end
$upscope $end
$scope begin genblk1[56] $end
$upscope $end
$scope begin genblk1[57] $end
$upscope $end
$scope begin genblk1[58] $end
$upscope $end
$scope begin genblk1[59] $end
$upscope $end
$scope begin genblk1[60] $end
$upscope $end
$scope begin genblk1[61] $end
$upscope $end
$scope begin genblk1[62] $end
$upscope $end
$scope begin genblk1[63] $end
$upscope $end
$scope begin genblk1[64] $end
$upscope $end
$scope begin genblk1[65] $end
$upscope $end
$scope begin genblk1[66] $end
$upscope $end
$scope begin genblk1[67] $end
$upscope $end
$scope begin genblk1[68] $end
$upscope $end
$scope begin genblk1[69] $end
$upscope $end
$scope begin genblk1[70] $end
$upscope $end
$scope begin genblk1[71] $end
$upscope $end
$scope begin genblk1[72] $end
$upscope $end
$scope begin genblk1[73] $end
$upscope $end
$scope begin genblk1[74] $end
$upscope $end
$scope begin genblk1[75] $end
$upscope $end
$scope begin genblk1[76] $end
$upscope $end
$scope begin genblk1[77] $end
$upscope $end
$scope begin genblk1[78] $end
$upscope $end
$scope begin genblk1[79] $end
$upscope $end
$scope begin genblk1[80] $end
$upscope $end
$scope begin genblk1[81] $end
$upscope $end
$scope begin genblk1[82] $end
$upscope $end
$scope begin genblk1[83] $end
$upscope $end
$scope begin genblk1[84] $end
$upscope $end
$scope begin genblk1[85] $end
$upscope $end
$scope begin genblk1[86] $end
$upscope $end
$scope begin genblk1[87] $end
$upscope $end
$scope begin genblk1[88] $end
$upscope $end
$scope begin genblk1[89] $end
$upscope $end
$scope begin genblk1[90] $end
$upscope $end
$scope begin genblk1[91] $end
$upscope $end
$scope begin genblk1[92] $end
$upscope $end
$scope begin genblk1[93] $end
$upscope $end
$scope begin genblk1[94] $end
$upscope $end
$scope begin genblk1[95] $end
$upscope $end
$scope begin genblk1[96] $end
$upscope $end
$scope begin genblk1[97] $end
$upscope $end
$scope begin genblk1[98] $end
$upscope $end
$scope begin genblk1[99] $end
$upscope $end
$scope begin genblk1[100] $end
$upscope $end
$scope begin genblk1[101] $end
$upscope $end
$scope begin genblk1[102] $end
$upscope $end
$scope begin genblk1[103] $end
$upscope $end
$scope begin genblk1[104] $end
$upscope $end
$scope begin genblk1[105] $end
$upscope $end
$scope begin genblk1[106] $end
$upscope $end
$scope begin genblk1[107] $end
$upscope $end
$scope begin genblk1[108] $end
$upscope $end
$scope begin genblk1[109] $end
$upscope $end
$scope begin genblk1[110] $end
$upscope $end
$scope begin genblk1[111] $end
$upscope $end
$scope begin genblk1[112] $end
$upscope $end
$scope begin genblk1[113] $end
$upscope $end
$scope begin genblk1[114] $end
$upscope $end
$scope begin genblk1[115] $end
$upscope $end
$scope begin genblk1[116] $end
$upscope $end
$scope begin genblk1[117] $end
$upscope $end
$scope begin genblk1[118] $end
$upscope $end
$scope begin genblk1[119] $end
$upscope $end
$scope begin genblk1[120] $end
$upscope $end
$scope begin genblk1[121] $end
$upscope $end
$scope begin genblk1[122] $end
$upscope $end
$scope begin genblk1[123] $end
$upscope $end
$scope begin genblk1[124] $end
$upscope $end
$scope begin genblk1[125] $end
$upscope $end
$scope begin genblk1[126] $end
$upscope $end
$scope begin genblk1[127] $end
$upscope $end
$scope begin genblk1[128] $end
$upscope $end
$scope begin genblk1[129] $end
$upscope $end
$scope begin genblk1[130] $end
$upscope $end
$scope begin genblk1[131] $end
$upscope $end
$scope begin genblk1[132] $end
$upscope $end
$upscope $end
$scope module my_pc $end
$var wire 1 ! clk $end
$var wire 1 $ set_pc $end
$var wire 4 & PC_REG_IN [3:0] $end
$var wire 4 ' PC_PLUS_1 [3:0] $end
$var wire 4 ( PC_CURR_INV [3:0] $end
$var wire 4 ) PC_CURR [3:0] $end
$scope module mux_2_1_4b_0 $end
$var wire 4 * B [3:0] $end
$var wire 1 $ sel $end
$var wire 4 + RES [3:0] $end
$var wire 4 , A [3:0] $end
$scope module mux_2_1_1b_0[0] $end
$var wire 1 - a $end
$var wire 1 . a_out $end
$var wire 1 / b $end
$var wire 1 0 b_out $end
$var wire 1 1 not_sel $end
$var wire 1 2 res $end
$var wire 1 $ sel $end
$upscope $end
$scope module mux_2_1_1b_0[1] $end
$var wire 1 3 a $end
$var wire 1 4 a_out $end
$var wire 1 5 b $end
$var wire 1 6 b_out $end
$var wire 1 7 not_sel $end
$var wire 1 8 res $end
$var wire 1 $ sel $end
$upscope $end
$scope module mux_2_1_1b_0[2] $end
$var wire 1 9 a $end
$var wire 1 : a_out $end
$var wire 1 ; b $end
$var wire 1 < b_out $end
$var wire 1 = not_sel $end
$var wire 1 > res $end
$var wire 1 $ sel $end
$upscope $end
$scope module mux_2_1_1b_0[3] $end
$var wire 1 ? a $end
$var wire 1 @ a_out $end
$var wire 1 A b $end
$var wire 1 B b_out $end
$var wire 1 C not_sel $end
$var wire 1 D res $end
$var wire 1 $ sel $end
$upscope $end
$upscope $end
$scope module pc_adder $end
$var wire 4 E A [3:0] $end
$var wire 1 F c_out3 $end
$var wire 1 G c_out2 $end
$var wire 1 H c_out1 $end
$var wire 1 I c_out0 $end
$var wire 4 J SUM [3:0] $end
$var wire 4 K B [3:0] $end
$scope module fa0 $end
$var wire 1 L a $end
$var wire 1 M b $end
$var wire 1 N c_in $end
$var wire 1 I c_out $end
$var wire 1 O sum $end
$var wire 1 P w0 $end
$var wire 1 Q w1 $end
$var wire 1 R w2 $end
$upscope $end
$scope module fa1 $end
$var wire 1 S a $end
$var wire 1 T b $end
$var wire 1 I c_in $end
$var wire 1 H c_out $end
$var wire 1 U sum $end
$var wire 1 V w0 $end
$var wire 1 W w1 $end
$var wire 1 X w2 $end
$upscope $end
$scope module fa2 $end
$var wire 1 Y a $end
$var wire 1 Z b $end
$var wire 1 H c_in $end
$var wire 1 G c_out $end
$var wire 1 [ sum $end
$var wire 1 \ w0 $end
$var wire 1 ] w1 $end
$var wire 1 ^ w2 $end
$upscope $end
$scope module fa3 $end
$var wire 1 _ a $end
$var wire 1 ` b $end
$var wire 1 G c_in $end
$var wire 1 F c_out $end
$var wire 1 a sum $end
$var wire 1 b w0 $end
$var wire 1 c w1 $end
$var wire 1 d w2 $end
$upscope $end
$upscope $end
$scope module pc_reg $end
$var wire 4 e D [3:0] $end
$var wire 1 ! clk $end
$var wire 4 f QB [3:0] $end
$var wire 4 g Q [3:0] $end
$scope module DFF[0] $end
$var wire 1 ! clk $end
$var wire 1 h d $end
$var wire 1 i nclk $end
$var wire 1 j qb_tmp $end
$var wire 1 k qb $end
$var wire 1 l q_tmp $end
$var wire 1 m q $end
$scope module d_latch_0 $end
$var wire 1 h d $end
$var wire 1 i g $end
$var wire 1 n nd $end
$var wire 1 o r $end
$var wire 1 p s $end
$var wire 1 j qb $end
$var wire 1 l q $end
$scope module sr_latch_0 $end
$var wire 1 l q $end
$var wire 1 j qb $end
$var wire 1 o r $end
$var wire 1 p s $end
$upscope $end
$upscope $end
$scope module d_latch_1 $end
$var wire 1 l d $end
$var wire 1 ! g $end
$var wire 1 q nd $end
$var wire 1 r r $end
$var wire 1 s s $end
$var wire 1 k qb $end
$var wire 1 m q $end
$scope module sr_latch_0 $end
$var wire 1 m q $end
$var wire 1 k qb $end
$var wire 1 r r $end
$var wire 1 s s $end
$upscope $end
$upscope $end
$upscope $end
$scope module DFF[1] $end
$var wire 1 ! clk $end
$var wire 1 t d $end
$var wire 1 u nclk $end
$var wire 1 v qb_tmp $end
$var wire 1 w qb $end
$var wire 1 x q_tmp $end
$var wire 1 y q $end
$scope module d_latch_0 $end
$var wire 1 t d $end
$var wire 1 u g $end
$var wire 1 z nd $end
$var wire 1 { r $end
$var wire 1 | s $end
$var wire 1 v qb $end
$var wire 1 x q $end
$scope module sr_latch_0 $end
$var wire 1 x q $end
$var wire 1 v qb $end
$var wire 1 { r $end
$var wire 1 | s $end
$upscope $end
$upscope $end
$scope module d_latch_1 $end
$var wire 1 x d $end
$var wire 1 ! g $end
$var wire 1 } nd $end
$var wire 1 ~ r $end
$var wire 1 !" s $end
$var wire 1 w qb $end
$var wire 1 y q $end
$scope module sr_latch_0 $end
$var wire 1 y q $end
$var wire 1 w qb $end
$var wire 1 ~ r $end
$var wire 1 !" s $end
$upscope $end
$upscope $end
$upscope $end
$scope module DFF[2] $end
$var wire 1 ! clk $end
$var wire 1 "" d $end
$var wire 1 #" nclk $end
$var wire 1 $" qb_tmp $end
$var wire 1 %" qb $end
$var wire 1 &" q_tmp $end
$var wire 1 '" q $end
$scope module d_latch_0 $end
$var wire 1 "" d $end
$var wire 1 #" g $end
$var wire 1 (" nd $end
$var wire 1 )" r $end
$var wire 1 *" s $end
$var wire 1 $" qb $end
$var wire 1 &" q $end
$scope module sr_latch_0 $end
$var wire 1 &" q $end
$var wire 1 $" qb $end
$var wire 1 )" r $end
$var wire 1 *" s $end
$upscope $end
$upscope $end
$scope module d_latch_1 $end
$var wire 1 &" d $end
$var wire 1 ! g $end
$var wire 1 +" nd $end
$var wire 1 ," r $end
$var wire 1 -" s $end
$var wire 1 %" qb $end
$var wire 1 '" q $end
$scope module sr_latch_0 $end
$var wire 1 '" q $end
$var wire 1 %" qb $end
$var wire 1 ," r $end
$var wire 1 -" s $end
$upscope $end
$upscope $end
$upscope $end
$scope module DFF[3] $end
$var wire 1 ! clk $end
$var wire 1 ." d $end
$var wire 1 /" nclk $end
$var wire 1 0" qb_tmp $end
$var wire 1 1" qb $end
$var wire 1 2" q_tmp $end
$var wire 1 3" q $end
$scope module d_latch_0 $end
$var wire 1 ." d $end
$var wire 1 /" g $end
$var wire 1 4" nd $end
$var wire 1 5" r $end
$var wire 1 6" s $end
$var wire 1 0" qb $end
$var wire 1 2" q $end
$scope module sr_latch_0 $end
$var wire 1 2" q $end
$var wire 1 0" qb $end
$var wire 1 5" r $end
$var wire 1 6" s $end
$upscope $end
$upscope $end
$scope module d_latch_1 $end
$var wire 1 2" d $end
$var wire 1 ! g $end
$var wire 1 7" nd $end
$var wire 1 8" r $end
$var wire 1 9" s $end
$var wire 1 1" qb $end
$var wire 1 3" q $end
$scope module sr_latch_0 $end
$var wire 1 3" q $end
$var wire 1 1" qb $end
$var wire 1 8" r $end
$var wire 1 9" s $end
$upscope $end
$upscope $end
$upscope $end
$upscope $end
$upscope $end
$upscope $end
$enddefinitions $end
#0
$dumpvars
x9"
x8"
x7"
x6"
x5"
x4"
x3"
x2"
x1"
x0"
x/"
x."
x-"
x,"
x+"
x*"
x)"
x("
x'"
x&"
x%"
x$"
x#"
x""
x!"
x~
x}
x|
x{
xz
xy
xx
xw
xv
xu
xt
xs
xr
xq
xp
xo
xn
xm
xl
xk
xj
xi
xh
bx g
bx f
bx e
xd
xc
xb
xa
x`
0_
x^
x]
x\
x[
xZ
0Y
xX
xW
xV
xU
xT
0S
xR
xQ
xP
xO
0N
xM
1L
bx K
bx J
xI
xH
xG
xF
b1 E
xD
xC
xB
0A
x@
x?
x>
x=
x<
0;
x:
x9
x8
x7
x6
05
x4
x3
x2
x1
x0
0/
x.
x-
bx ,
bx +
b0 *
bx )
bx (
bx '
bx &
bx %
x$
0#
bx "
x!
$end
#3
0c
0]
0W
0R
0B
0<
06
00
b0xxxxxxxxxxxxxxxxxxxxxxxxxxxxxxxxxxxxxxxxxxxxxxxxxxxxxxxxxxxxxxxxxxxxxxxxxxxxxxxxxxxxxxxxxxxxxxxxxxxxxxxxxxxxxxxxxxxxxxxxxxxxxxxxxxxxx %
#4
b1xxxxxxxxxxxxxxxxxxxxxxxxxxxxxxxxxxxxxxxxxxxxxxxxxxxxxxxxxxxxxxxxxxxxxxxxxxxxxxxxxxxxxxxxxxxxxxxxxxxxxxxxxxxxxxxxxxxxxxxxxxxxxxxxxxxx %
#5
b10xxxxxxxxxxxxxxxxxxxxxxxxxxxxxxxxxxxxxxxxxxxxxxxxxxxxxxxxxxxxxxxxxxxxxxxxxxxxxxxxxxxxxxxxxxxxxxxxxxxxxxxxxxxxxxxxxxxxxxxxxxxxxxxxxxx %
#6
b101xxxxxxxxxxxxxxxxxxxxxxxxxxxxxxxxxxxxxxxxxxxxxxxxxxxxxxxxxxxxxxxxxxxxxxxxxxxxxxxxxxxxxxxxxxxxxxxxxxxxxxxxxxxxxxxxxxxxxxxxxxxxxxxxxx %
#7
b1010xxxxxxxxxxxxxxxxxxxxxxxxxxxxxxxxxxxxxxxxxxxxxxxxxxxxxxxxxxxxxxxxxxxxxxxxxxxxxxxxxxxxxxxxxxxxxxxxxxxxxxxxxxxxxxxxxxxxxxxxxxxxxxxxx %
#8
b10101xxxxxxxxxxxxxxxxxxxxxxxxxxxxxxxxxxxxxxxxxxxxxxxxxxxxxxxxxxxxxxxxxxxxxxxxxxxxxxxxxxxxxxxxxxxxxxxxxxxxxxxxxxxxxxxxxxxxxxxxxxxxxxxx %
#9
b101010xxxxxxxxxxxxxxxxxxxxxxxxxxxxxxxxxxxxxxxxxxxxxxxxxxxxxxxxxxxxxxxxxxxxxxxxxxxxxxxxxxxxxxxxxxxxxxxxxxxxxxxxxxxxxxxxxxxxxxxxxxxxxxx %
#10
b1010101xxxxxxxxxxxxxxxxxxxxxxxxxxxxxxxxxxxxxxxxxxxxxxxxxxxxxxxxxxxxxxxxxxxxxxxxxxxxxxxxxxxxxxxxxxxxxxxxxxxxxxxxxxxxxxxxxxxxxxxxxxxxxx %
#11
b10101010xxxxxxxxxxxxxxxxxxxxxxxxxxxxxxxxxxxxxxxxxxxxxxxxxxxxxxxxxxxxxxxxxxxxxxxxxxxxxxxxxxxxxxxxxxxxxxxxxxxxxxxxxxxxxxxxxxxxxxxxxxxxx %
#12
b101010101xxxxxxxxxxxxxxxxxxxxxxxxxxxxxxxxxxxxxxxxxxxxxxxxxxxxxxxxxxxxxxxxxxxxxxxxxxxxxxxxxxxxxxxxxxxxxxxxxxxxxxxxxxxxxxxxxxxxxxxxxxxx %
#13
b1010101010xxxxxxxxxxxxxxxxxxxxxxxxxxxxxxxxxxxxxxxxxxxxxxxxxxxxxxxxxxxxxxxxxxxxxxxxxxxxxxxxxxxxxxxxxxxxxxxxxxxxxxxxxxxxxxxxxxxxxxxxxxx %
#14
b10101010101xxxxxxxxxxxxxxxxxxxxxxxxxxxxxxxxxxxxxxxxxxxxxxxxxxxxxxxxxxxxxxxxxxxxxxxxxxxxxxxxxxxxxxxxxxxxxxxxxxxxxxxxxxxxxxxxxxxxxxxxxx %
#15
b101010101010xxxxxxxxxxxxxxxxxxxxxxxxxxxxxxxxxxxxxxxxxxxxxxxxxxxxxxxxxxxxxxxxxxxxxxxxxxxxxxxxxxxxxxxxxxxxxxxxxxxxxxxxxxxxxxxxxxxxxxxxx %
#16
b1010101010101xxxxxxxxxxxxxxxxxxxxxxxxxxxxxxxxxxxxxxxxxxxxxxxxxxxxxxxxxxxxxxxxxxxxxxxxxxxxxxxxxxxxxxxxxxxxxxxxxxxxxxxxxxxxxxxxxxxxxxxx %
#17
b10101010101010xxxxxxxxxxxxxxxxxxxxxxxxxxxxxxxxxxxxxxxxxxxxxxxxxxxxxxxxxxxxxxxxxxxxxxxxxxxxxxxxxxxxxxxxxxxxxxxxxxxxxxxxxxxxxxxxxxxxxxx %
#18
b101010101010101xxxxxxxxxxxxxxxxxxxxxxxxxxxxxxxxxxxxxxxxxxxxxxxxxxxxxxxxxxxxxxxxxxxxxxxxxxxxxxxxxxxxxxxxxxxxxxxxxxxxxxxxxxxxxxxxxxxxxx %
#19
b1010101010101010xxxxxxxxxxxxxxxxxxxxxxxxxxxxxxxxxxxxxxxxxxxxxxxxxxxxxxxxxxxxxxxxxxxxxxxxxxxxxxxxxxxxxxxxxxxxxxxxxxxxxxxxxxxxxxxxxxxxx %
#20
b10101010101010101xxxxxxxxxxxxxxxxxxxxxxxxxxxxxxxxxxxxxxxxxxxxxxxxxxxxxxxxxxxxxxxxxxxxxxxxxxxxxxxxxxxxxxxxxxxxxxxxxxxxxxxxxxxxxxxxxxxx %
#21
b101010101010101010xxxxxxxxxxxxxxxxxxxxxxxxxxxxxxxxxxxxxxxxxxxxxxxxxxxxxxxxxxxxxxxxxxxxxxxxxxxxxxxxxxxxxxxxxxxxxxxxxxxxxxxxxxxxxxxxxxx %
#22
b1010101010101010101xxxxxxxxxxxxxxxxxxxxxxxxxxxxxxxxxxxxxxxxxxxxxxxxxxxxxxxxxxxxxxxxxxxxxxxxxxxxxxxxxxxxxxxxxxxxxxxxxxxxxxxxxxxxxxxxxx %
#23
b10101010101010101010xxxxxxxxxxxxxxxxxxxxxxxxxxxxxxxxxxxxxxxxxxxxxxxxxxxxxxxxxxxxxxxxxxxxxxxxxxxxxxxxxxxxxxxxxxxxxxxxxxxxxxxxxxxxxxxxx %
#24
b101010101010101010101xxxxxxxxxxxxxxxxxxxxxxxxxxxxxxxxxxxxxxxxxxxxxxxxxxxxxxxxxxxxxxxxxxxxxxxxxxxxxxxxxxxxxxxxxxxxxxxxxxxxxxxxxxxxxxxx %
#25
b1010101010101010101010xxxxxxxxxxxxxxxxxxxxxxxxxxxxxxxxxxxxxxxxxxxxxxxxxxxxxxxxxxxxxxxxxxxxxxxxxxxxxxxxxxxxxxxxxxxxxxxxxxxxxxxxxxxxxxx %
#26
b10101010101010101010101xxxxxxxxxxxxxxxxxxxxxxxxxxxxxxxxxxxxxxxxxxxxxxxxxxxxxxxxxxxxxxxxxxxxxxxxxxxxxxxxxxxxxxxxxxxxxxxxxxxxxxxxxxxxxx %
#27
b101010101010101010101010xxxxxxxxxxxxxxxxxxxxxxxxxxxxxxxxxxxxxxxxxxxxxxxxxxxxxxxxxxxxxxxxxxxxxxxxxxxxxxxxxxxxxxxxxxxxxxxxxxxxxxxxxxxxx %
#28
b1010101010101010101010101xxxxxxxxxxxxxxxxxxxxxxxxxxxxxxxxxxxxxxxxxxxxxxxxxxxxxxxxxxxxxxxxxxxxxxxxxxxxxxxxxxxxxxxxxxxxxxxxxxxxxxxxxxxx %
#29
b10101010101010101010101010xxxxxxxxxxxxxxxxxxxxxxxxxxxxxxxxxxxxxxxxxxxxxxxxxxxxxxxxxxxxxxxxxxxxxxxxxxxxxxxxxxxxxxxxxxxxxxxxxxxxxxxxxxx %
#30
b101010101010101010101010101xxxxxxxxxxxxxxxxxxxxxxxxxxxxxxxxxxxxxxxxxxxxxxxxxxxxxxxxxxxxxxxxxxxxxxxxxxxxxxxxxxxxxxxxxxxxxxxxxxxxxxxxxx %
#31
b1010101010101010101010101010xxxxxxxxxxxxxxxxxxxxxxxxxxxxxxxxxxxxxxxxxxxxxxxxxxxxxxxxxxxxxxxxxxxxxxxxxxxxxxxxxxxxxxxxxxxxxxxxxxxxxxxxx %
#32
b10101010101010101010101010101xxxxxxxxxxxxxxxxxxxxxxxxxxxxxxxxxxxxxxxxxxxxxxxxxxxxxxxxxxxxxxxxxxxxxxxxxxxxxxxxxxxxxxxxxxxxxxxxxxxxxxxx %
#33
b101010101010101010101010101010xxxxxxxxxxxxxxxxxxxxxxxxxxxxxxxxxxxxxxxxxxxxxxxxxxxxxxxxxxxxxxxxxxxxxxxxxxxxxxxxxxxxxxxxxxxxxxxxxxxxxxx %
#34
b1010101010101010101010101010101xxxxxxxxxxxxxxxxxxxxxxxxxxxxxxxxxxxxxxxxxxxxxxxxxxxxxxxxxxxxxxxxxxxxxxxxxxxxxxxxxxxxxxxxxxxxxxxxxxxxxx %
#35
b10101010101010101010101010101010xxxxxxxxxxxxxxxxxxxxxxxxxxxxxxxxxxxxxxxxxxxxxxxxxxxxxxxxxxxxxxxxxxxxxxxxxxxxxxxxxxxxxxxxxxxxxxxxxxxxx %
#36
b101010101010101010101010101010101xxxxxxxxxxxxxxxxxxxxxxxxxxxxxxxxxxxxxxxxxxxxxxxxxxxxxxxxxxxxxxxxxxxxxxxxxxxxxxxxxxxxxxxxxxxxxxxxxxxx %
#37
b1010101010101010101010101010101010xxxxxxxxxxxxxxxxxxxxxxxxxxxxxxxxxxxxxxxxxxxxxxxxxxxxxxxxxxxxxxxxxxxxxxxxxxxxxxxxxxxxxxxxxxxxxxxxxxx %
#38
b10101010101010101010101010101010101xxxxxxxxxxxxxxxxxxxxxxxxxxxxxxxxxxxxxxxxxxxxxxxxxxxxxxxxxxxxxxxxxxxxxxxxxxxxxxxxxxxxxxxxxxxxxxxxxx %
#39
b101010101010101010101010101010101010xxxxxxxxxxxxxxxxxxxxxxxxxxxxxxxxxxxxxxxxxxxxxxxxxxxxxxxxxxxxxxxxxxxxxxxxxxxxxxxxxxxxxxxxxxxxxxxxx %
#40
b1010101010101010101010101010101010101xxxxxxxxxxxxxxxxxxxxxxxxxxxxxxxxxxxxxxxxxxxxxxxxxxxxxxxxxxxxxxxxxxxxxxxxxxxxxxxxxxxxxxxxxxxxxxxx %
#41
b10101010101010101010101010101010101010xxxxxxxxxxxxxxxxxxxxxxxxxxxxxxxxxxxxxxxxxxxxxxxxxxxxxxxxxxxxxxxxxxxxxxxxxxxxxxxxxxxxxxxxxxxxxxx %
#42
b101010101010101010101010101010101010101xxxxxxxxxxxxxxxxxxxxxxxxxxxxxxxxxxxxxxxxxxxxxxxxxxxxxxxxxxxxxxxxxxxxxxxxxxxxxxxxxxxxxxxxxxxxxx %
#43
b1010101010101010101010101010101010101010xxxxxxxxxxxxxxxxxxxxxxxxxxxxxxxxxxxxxxxxxxxxxxxxxxxxxxxxxxxxxxxxxxxxxxxxxxxxxxxxxxxxxxxxxxxxx %
#44
b10101010101010101010101010101010101010101xxxxxxxxxxxxxxxxxxxxxxxxxxxxxxxxxxxxxxxxxxxxxxxxxxxxxxxxxxxxxxxxxxxxxxxxxxxxxxxxxxxxxxxxxxxx %
#45
b101010101010101010101010101010101010101010xxxxxxxxxxxxxxxxxxxxxxxxxxxxxxxxxxxxxxxxxxxxxxxxxxxxxxxxxxxxxxxxxxxxxxxxxxxxxxxxxxxxxxxxxxx %
#46
b1010101010101010101010101010101010101010101xxxxxxxxxxxxxxxxxxxxxxxxxxxxxxxxxxxxxxxxxxxxxxxxxxxxxxxxxxxxxxxxxxxxxxxxxxxxxxxxxxxxxxxxxx %
