mux_2_1_1b/mux_2_1_1b.v
// Critical path delay = 7ns
// 0 -> copy a
// 1 -> copy b
module mux_2_1_1b(a, b, sel, res);
   input a;
   input b;
   input sel;
   output res;
   wire   not_sel;
   not #(1) not0(not_sel, sel);
   wire   a_out;
   and #(3) and0(a_out, a, not_sel);
   wire   b_out;
   and #(3) and1(b_out, b, sel);
   or #(3) and2(res, a_out, b_out);
endmodule // mux1

mux_2_1_4b/mux_2_1_4b.v
// Critical path delay = 7ns
module mux_2_1_4b(A, B, sel, RES);
   input [3:0] A;
   input [3:0] B;
   input       sel;
   output [3:0] RES;
   mux_2_1_1b mux_2_1_1b_0[3:0](.a(A), .b(B), .sel(sel), .res(RES));
endmodule; // mux4

fa/fa.v
module fa(a, b, c_in, sum, c_out);
   input a;
   input b;
   input c_in;
   output sum;
   output c_out;
   wire   w0;
   xor #(4) xor0(w0, a, b);
   wire   w1;
   and #(3) and0(w1, a, b);
   wire   w2;
   and #(3) and1(w2, w0, c_in);
   xor #(4) xor1(sum, w0, c_in);
   or #(3) or0(c_out, w1, w2);
endmodule

rca/rca.v
// Critical path delay: 44 ns
module rca(A, B, SUM, ovf);
   input [3:0] A;
   input [3:0] B;
   output [3:0] SUM;
   output       ovf;
   wire         c_out0;
   fa fa0(.a(A[0]), .b(B[0]), .c_in(1'b0), .sum(SUM[0]), .c_out(c_out0));
   wire         c_out1;
   fa fa1(.a(A[1]), .b(B[1]), .c_in(c_out0), .sum(SUM[1]), .c_out(c_out1));
   wire         c_out2;
   fa fa2(.a(A[2]), .b(B[2]), .c_in(c_out1), .sum(SUM[2]), .c_out(c_out2));
   wire         c_out3;
   fa fa3(.a(A[3]), .b(B[3]), .c_in(c_out2), .sum(SUM[3]), .c_out(c_out3));
   xor #(4) xor_0(ovf, c_out2, c_out3);
endmodule

alu/alu.v
// Critical path delay = 51 ns
module alu(A, B, sel, RES, eq);
   input [3:0] A;
   input [3:0] B;
   input       sel;
   output [3:0] RES;
   output       eq;
   
   wire [3:0]  W0;
   rca rca_0(.A(A), .B(B), .SUM(W0));
   wire [3:0] W1;
   wire [3:0] W2;
   genvar i;
   generate
      for (i = 3; i >= 0; i = i-1) begin
	 nand #(2) nand_0(W1[i], A[i], B[i]);
         xnor #(5) xnor_0(W2[i], A[i], B[i]);
      end
   endgenerate
   mux_2_1_4b mux_2_1_4b_0(.A(W0), .B(W1), .sel(sel), .RES(RES));
   and #(3) and_0(eq, W2[3], W2[2], W2[1], W2[0]);
endmodule

alu/testbench.v
`timescale 1 ns/1 ns	//time scale for simulation

module testbench;
   reg [3:0] A;
   reg [3:0] B;
   reg       sel;   
   wire [3:0] RES;
   wire       eq;
   alu my_alu(.A(A), .B(B), .sel(sel), .RES(RES), .eq(eq));

   initial begin
      $dumpfile("test.vcd");
      $dumpvars(0, testbench);
      // test0: -1 + -5 = -6, eq = 0
      A = 4'b1111;
      B = 4'b1011;
      sel = 0;
      #51;
      // test1: -2 nand -2 = 1, eq = 1
      A = 4'b1110;
      B = 4'b1110;
      sel = 1;
      #51;
      // test2: -8 + -3 = 5 (ovf: should be -11), eq = 0
      A = 4'b1000;
      B = 4'b1101;
      sel = 0;
      #51;
      // test3: 5 + 5 = -6 (ovf: should be 10), eq = 1
      A = 4'b0101;
      B = 4'b0101;
      sel = 0;
      #51;
   end
endmodule

alu/test.vcd
$date
	Sat Sep  3 20:07:52 2022
$end
$version
	Icarus Verilog
$end
$timescale
	1ns
$end
$scope module testbench $end
$var wire 1 ! eq $end
$var wire 4 " RES [3:0] $end
$var reg 4 # A [3:0] $end
$var reg 4 $ B [3:0] $end
$var reg 1 % sel $end
$scope module my_alu $end
$var wire 4 & A [3:0] $end
$var wire 4 ' B [3:0] $end
$var wire 1 ! eq $end
$var wire 1 % sel $end
$var wire 4 ( W2 [3:0] $end
$var wire 4 ) W1 [3:0] $end
$var wire 4 * W0 [3:0] $end
$var wire 4 + RES [3:0] $end
$scope begin genblk1[0] $end
$upscope $end
$scope begin genblk1[1] $end
$upscope $end
$scope begin genblk1[2] $end
$upscope $end
$scope begin genblk1[3] $end
$upscope $end
$scope module mux_2_1_4b_0 $end
$var wire 4 , B [3:0] $end
$var wire 1 % sel $end
$var wire 4 - RES [3:0] $end
$var wire 4 . A [3:0] $end
$scope module mux_2_1_1b_0[0] $end
$var wire 1 / a $end
$var wire 1 0 a_out $end
$var wire 1 1 b $end
$var wire 1 2 b_out $end
$var wire 1 3 not_sel $end
$var wire 1 4 res $end
$var wire 1 % sel $end
$upscope $end
$scope module mux_2_1_1b_0[1] $end
$var wire 1 5 a $end
$var wire 1 6 a_out $end
$var wire 1 7 b $end
$var wire 1 8 b_out $end
$var wire 1 9 not_sel $end
$var wire 1 : res $end
$var wire 1 % sel $end
$upscope $end
$scope module mux_2_1_1b_0[2] $end
$var wire 1 ; a $end
$var wire 1 < a_out $end
$var wire 1 = b $end
$var wire 1 > b_out $end
$var wire 1 ? not_sel $end
$var wire 1 @ res $end
$var wire 1 % sel $end
$upscope $end
$scope module mux_2_1_1b_0[3] $end
$var wire 1 A a $end
$var wire 1 B a_out $end
$var wire 1 C b $end
$var wire 1 D b_out $end
$var wire 1 E not_sel $end
$var wire 1 F res $end
$var wire 1 % sel $end
$upscope $end
$upscope $end
$scope module rca_0 $end
$var wire 4 G A [3:0] $end
$var wire 4 H B [3:0] $end
$var wire 1 I ovf $end
$var wire 1 J c_out3 $end
$var wire 1 K c_out2 $end
$var wire 1 L c_out1 $end
$var wire 1 M c_out0 $end
$var wire 4 N SUM [3:0] $end
$scope module fa0 $end
$var wire 1 O a $end
$var wire 1 P b $end
$var wire 1 Q c_in $end
$var wire 1 M c_out $end
$var wire 1 R sum $end
$var wire 1 S w0 $end
$var wire 1 T w1 $end
$var wire 1 U w2 $end
$upscope $end
$scope module fa1 $end
$var wire 1 V a $end
$var wire 1 W b $end
$var wire 1 M c_in $end
$var wire 1 L c_out $end
$var wire 1 X sum $end
$var wire 1 Y w0 $end
$var wire 1 Z w1 $end
$var wire 1 [ w2 $end
$upscope $end
$scope module fa2 $end
$var wire 1 \ a $end
$var wire 1 ] b $end
$var wire 1 L c_in $end
$var wire 1 K c_out $end
$var wire 1 ^ sum $end
$var wire 1 _ w0 $end
$var wire 1 ` w1 $end
$var wire 1 a w2 $end
$upscope $end
$scope module fa3 $end
$var wire 1 b a $end
$var wire 1 c b $end
$var wire 1 K c_in $end
$var wire 1 J c_out $end
$var wire 1 d sum $end
$var wire 1 e w0 $end
$var wire 1 f w1 $end
$var wire 1 g w2 $end
$upscope $end
$upscope $end
$upscope $end
$upscope $end
$enddefinitions $end
#0
$dumpvars
xg
xf
xe
xd
1c
1b
xa
x`
x_
x^
0]
1\
x[
xZ
xY
xX
1W
1V
xU
xT
xS
xR
0Q
1P
1O
bx N
xM
xL
xK
xJ
xI
b1011 H
b1111 G
xF
xE
xD
xC
xB
xA
x@
x?
x>
x=
x<
x;
x:
x9
x8
x7
x6
x5
x4
x3
x2
x1
x0
x/
bx .
bx -
bx ,
bx +
bx *
bx )
bx (
b1011 '
b1111 &
0%
b1011 $
b1111 #
bx "
x!
$end
#1
13
19
1?
1E
#2
0C
1=
07
01
b100 )
b100 ,
#3
1T
1Z
0`
1f
0U
0D
0>
08
02
#4
0S
0Y
1_
0e
#5
b1011 (
#6
1L
1J
1M
#7
0[
0g
#8
0/
0!
bx0 *
bx0 .
bx0 N
0R
#9
1a
#10
0;
15
0^
bx010 *
bx010 .
bx010 N
1X
#11
00
#12
1K
#13
0<
16
#14
bx0 "
bx0 +
bx0 -
04
#16
1A
0@
bx010 "
bx010 +
bx010 -
1:
b1010 *
b1010 .
b1010 N
1d
0I
#19
1B
#22
b1010 "
b1010 +
b1010 -
1F
#51
0P
1]
0O
1%
b1110 $
b1110 '
b1110 H
b1110 #
b1110 &
b1110 G
#52
03
09
0?
0E
#53
0=
11
b1 )
b1 ,
#54
1`
0T
#55
06
0B
0_
#56
12
b1111 (
#57
0M
#58
0:
b0 "
b0 +
b0 -
0F
0a
#59
1;
1!
b1 "
b1 +
b1 -
14
b1110 *
b1110 .
b1110 N
1^
#61
05
b1100 *
b1100 .
b1100 N
0X
#102
1P
0W
0V
0\
0%
b1101 $
b1101 '
b1101 H
b1000 #
b1000 &
b1000 G
#103
13
19
1?
1E
#104
1=
17
b111 )
b111 ,
#105
0Z
0`
02
#106
1<
1B
1S
1_
#107
b1010 (
#108
0L
0K
b0 "
b0 +
b0 -
04
#109
1@
b1100 "
b1100 +
b1100 -
1F
#110
1/
0!
b1101 *
b1101 .
b1101 N
1R
#112
0A
b101 *
b101 .
b101 N
0d
1I
#113
10
#115
0B
#116
b1101 "
b1101 +
b1101 -
14
#118
b101 "
b101 +
b101 -
0F
#153
0c
1O
1\
0b
b101 $
b101 '
b101 H
b101 #
b101 &
b101 G
#155
1C
0=
01
b1010 )
b1010 ,
#156
1T
1`
0f
#157
0S
0_
#158
b1111 (
#159
1M
1K
0J
#161
0/
0;
1!
0R
b0 *
b0 .
b0 N
0^
#163
15
1A
1X
b1010 *
b1010 .
b1010 N
1d
#164
00
0<
#166
16
1B
#167
04
b0 "
b0 +
b0 -
0@
#169
1:
b1010 "
b1010 +
b1010 -
1F
