mux_2_1_1b/mux_2_1_1b.v
// Critical path delay = 7ns
// 0 -> copy a
// 1 -> copy b
module mux_2_1_1b(a, b, sel, res);
   input a;
   input b;
   input sel;
   output res;
   wire   not_sel;
   not #(1) not0(not_sel, sel);
   wire   a_out;
   and #(3) and0(a_out, a, not_sel);
   wire   b_out;
   and #(3) and1(b_out, b, sel);
   or #(3) and2(res, a_out, b_out);
endmodule // mux1

mux_2_1_4b/mux_2_1_4b.v
// Critical path delay = 7ns
module mux_2_1_4b(A, B, sel, RES);
   input [3:0] A;
   input [3:0] B;
   input       sel;
   output [3:0] RES;
   mux_2_1_1b mux_2_1_1b_0[3:0](.a(A), .b(B), .sel(sel), .res(RES));
endmodule; // mux4

fa/fa.v
module fa(a, b, c_in, sum, c_out);
   input a;
   input b;
   input c_in;
   output sum;
   output c_out;
   wire   w0;
   xor #(4) xor0(w0, a, b);
   wire   w1;
   and #(3) and0(w1, a, b);
   wire   w2;
   and #(3) and1(w2, w0, c_in);
   xor #(4) xor1(sum, w0, c_in);
   or #(3) or0(c_out, w1, w2);
endmodule

rca/rca.v
// Critical path delay: 44 ns
module rca(A, B, SUM, ovf);
   input [3:0] A;
   input [3:0] B;
   output [3:0] SUM;
   output       ovf;
   wire         c_out0;
   fa fa0(.a(A[0]), .b(B[0]), .c_in(1'b0), .sum(SUM[0]), .c_out(c_out0));
   wire         c_out1;
   fa fa1(.a(A[1]), .b(B[1]), .c_in(c_out0), .sum(SUM[1]), .c_out(c_out1));
   wire         c_out2;
   fa fa2(.a(A[2]), .b(B[2]), .c_in(c_out1), .sum(SUM[2]), .c_out(c_out2));
   wire         c_out3;
   fa fa3(.a(A[3]), .b(B[3]), .c_in(c_out2), .sum(SUM[3]), .c_out(c_out3));
   xor #(4) xor_0(ovf, c_out2, c_out3);
endmodule

alu/alu.v
// Critical path delay = 51 ns
module alu(A, B, sel, RES, eq, ovf);
   input [3:0] A;
   input [3:0] B;
   input sel;
   output [3:0] RES;
   output eq;
   output ovf;
   
   wire [3:0]  W0;
   rca rca_0(.A(A), .B(B), .SUM(W0), .ovf(ovf));
   wire [3:0] W1;
   wire [3:0] W2;
   genvar i;
   generate
      for (i = 3; i >= 0; i = i-1) begin
	 nand #(2) nand_0(W1[i], A[i], B[i]);
         xnor #(5) xnor_0(W2[i], A[i], B[i]);
      end
   endgenerate
   mux_2_1_4b mux_2_1_4b_0(.A(W0), .B(W1), .sel(sel), .RES(RES));
   and #(3) and_0(eq, W2[3], W2[2], W2[1], W2[0]);
endmodule

alu/testbench.v
`timescale 1 ns/1 ns	//time scale for simulation

module testbench;
   reg [3:0] A;
   reg [3:0] B;
   reg sel;   
   wire [3:0] RES;
   wire eq;
   wire ovf;
   alu my_alu(.A(A), .B(B), .sel(sel), .RES(RES), .eq(eq), .ovf(ovf));

   initial begin
      $dumpfile("test.vcd");
      $dumpvars(0, testbench);
      // test0: -1 + -5 = -6, eq = 0
      A = 4'b1111;
      B = 4'b1011;
      sel = 0;
      #51;
      // test1: -2 nand -2 = 1, eq = 1
      A = 4'b1110;
      B = 4'b1110;
      sel = 1;
      #51;
      // test2: -8 + -3 = 5 (ovf: should be -11), eq = 0
      A = 4'b1000;
      B = 4'b1101;
      sel = 0;
      #51;
      // test3: 5 + 5 = -6 (ovf: should be 10), eq = 1
      A = 4'b0101;
      B = 4'b0101;
      sel = 0;
      #51;
   end
endmodule

alu/test.vcd
$date
	Fri Sep  9 13:10:28 2022
$end
$version
	Icarus Verilog
$end
$timescale
	1ns
$end
$scope module testbench $end
$var wire 1 ! ovf $end
$var wire 1 " eq $end
$var wire 4 # RES [3:0] $end
$var reg 4 $ A [3:0] $end
$var reg 4 % B [3:0] $end
$var reg 1 & sel $end
$scope module my_alu $end
$var wire 4 ' A [3:0] $end
$var wire 4 ( B [3:0] $end
$var wire 1 " eq $end
$var wire 1 & sel $end
$var wire 1 ! ovf $end
$var wire 4 ) W2 [3:0] $end
$var wire 4 * W1 [3:0] $end
$var wire 4 + W0 [3:0] $end
$var wire 4 , RES [3:0] $end
$scope begin genblk1[0] $end
$upscope $end
$scope begin genblk1[1] $end
$upscope $end
$scope begin genblk1[2] $end
$upscope $end
$scope begin genblk1[3] $end
$upscope $end
$scope module mux_2_1_4b_0 $end
$var wire 4 - B [3:0] $end
$var wire 1 & sel $end
$var wire 4 . RES [3:0] $end
$var wire 4 / A [3:0] $end
$scope module mux_2_1_1b_0[0] $end
$var wire 1 0 a $end
$var wire 1 1 a_out $end
$var wire 1 2 b $end
$var wire 1 3 b_out $end
$var wire 1 4 not_sel $end
$var wire 1 5 res $end
$var wire 1 & sel $end
$upscope $end
$scope module mux_2_1_1b_0[1] $end
$var wire 1 6 a $end
$var wire 1 7 a_out $end
$var wire 1 8 b $end
$var wire 1 9 b_out $end
$var wire 1 : not_sel $end
$var wire 1 ; res $end
$var wire 1 & sel $end
$upscope $end
$scope module mux_2_1_1b_0[2] $end
$var wire 1 < a $end
$var wire 1 = a_out $end
$var wire 1 > b $end
$var wire 1 ? b_out $end
$var wire 1 @ not_sel $end
$var wire 1 A res $end
$var wire 1 & sel $end
$upscope $end
$scope module mux_2_1_1b_0[3] $end
$var wire 1 B a $end
$var wire 1 C a_out $end
$var wire 1 D b $end
$var wire 1 E b_out $end
$var wire 1 F not_sel $end
$var wire 1 G res $end
$var wire 1 & sel $end
$upscope $end
$upscope $end
$scope module rca_0 $end
$var wire 4 H A [3:0] $end
$var wire 4 I B [3:0] $end
$var wire 1 ! ovf $end
$var wire 1 J c_out3 $end
$var wire 1 K c_out2 $end
$var wire 1 L c_out1 $end
$var wire 1 M c_out0 $end
$var wire 4 N SUM [3:0] $end
$scope module fa0 $end
$var wire 1 O a $end
$var wire 1 P b $end
$var wire 1 Q c_in $end
$var wire 1 M c_out $end
$var wire 1 R sum $end
$var wire 1 S w0 $end
$var wire 1 T w1 $end
$var wire 1 U w2 $end
$upscope $end
$scope module fa1 $end
$var wire 1 V a $end
$var wire 1 W b $end
$var wire 1 M c_in $end
$var wire 1 L c_out $end
$var wire 1 X sum $end
$var wire 1 Y w0 $end
$var wire 1 Z w1 $end
$var wire 1 [ w2 $end
$upscope $end
$scope module fa2 $end
$var wire 1 \ a $end
$var wire 1 ] b $end
$var wire 1 L c_in $end
$var wire 1 K c_out $end
$var wire 1 ^ sum $end
$var wire 1 _ w0 $end
$var wire 1 ` w1 $end
$var wire 1 a w2 $end
$upscope $end
$scope module fa3 $end
$var wire 1 b a $end
$var wire 1 c b $end
$var wire 1 K c_in $end
$var wire 1 J c_out $end
$var wire 1 d sum $end
$var wire 1 e w0 $end
$var wire 1 f w1 $end
$var wire 1 g w2 $end
$upscope $end
$upscope $end
$upscope $end
$upscope $end
$enddefinitions $end
#0
$dumpvars
xg
xf
xe
xd
1c
1b
xa
x`
x_
x^
0]
1\
x[
xZ
xY
xX
1W
1V
xU
xT
xS
xR
0Q
1P
1O
bx N
xM
xL
xK
xJ
b1011 I
b1111 H
xG
xF
xE
xD
xC
xB
xA
x@
x?
x>
x=
x<
x;
x:
x9
x8
x7
x6
x5
x4
x3
x2
x1
x0
bx /
bx .
bx -
bx ,
bx +
bx *
bx )
b1011 (
b1111 '
0&
b1011 %
b1111 $
bx #
x"
x!
$end
#1
14
1:
1@
1F
#2
0D
1>
08
02
b100 *
b100 -
#3
1T
1Z
0`
1f
0U
0E
0?
09
03
#4
0S
0Y
1_
0e
#5
b1011 )
#6
1L
1J
1M
#7
0[
0g
#8
00
0"
bx0 +
bx0 /
bx0 N
0R
#9
1a
#10
0<
16
0^
bx010 +
bx010 /
bx010 N
1X
#11
01
#12
1K
#13
0=
17
#14
bx0 #
bx0 ,
bx0 .
05
#16
1B
0A
bx010 #
bx010 ,
bx010 .
1;
b1010 +
b1010 /
b1010 N
1d
0!
#19
1C
#22
b1010 #
b1010 ,
b1010 .
1G
#51
0P
1]
0O
1&
b1110 %
b1110 (
b1110 I
b1110 $
b1110 '
b1110 H
#52
04
0:
0@
0F
#53
0>
12
b1 *
b1 -
#54
1`
0T
#55
07
0C
0_
#56
13
b1111 )
#57
0M
#58
0;
b0 #
b0 ,
b0 .
0G
0a
#59
1<
1"
b1 #
b1 ,
b1 .
15
b1110 +
b1110 /
b1110 N
1^
#61
06
b1100 +
b1100 /
b1100 N
0X
#102
1P
0W
0V
0\
0&
b1101 %
b1101 (
b1101 I
b1000 $
b1000 '
b1000 H
#103
14
1:
1@
1F
#104
1>
18
b111 *
b111 -
#105
0Z
0`
03
#106
1=
1C
1S
1_
#107
b1010 )
#108
0L
0K
b0 #
b0 ,
b0 .
05
#109
1A
b1100 #
b1100 ,
b1100 .
1G
#110
10
0"
b1101 +
b1101 /
b1101 N
1R
#112
0B
b101 +
b101 /
b101 N
0d
1!
#113
11
#115
0C
#116
b1101 #
b1101 ,
b1101 .
15
#118
b101 #
b101 ,
b101 .
0G
#153
0c
1O
1\
0b
b101 %
b101 (
b101 I
b101 $
b101 '
b101 H
#155
1D
0>
02
b1010 *
b1010 -
#156
1T
1`
0f
#157
0S
0_
#158
b1111 )
#159
1M
1K
0J
#161
00
0<
1"
0R
b0 +
b0 /
b0 N
0^
#163
16
1B
1X
b1010 +
b1010 /
b1010 N
1d
#164
01
0=
#166
17
1C
#167
05
b0 #
b0 ,
b0 .
0A
#169
1;
b1010 #
b1010 ,
b1010 .
1G
